Workbook
Name IQ_CH: 110000
Name IQ_CQ: 5000
Name IQ_CY: 10000
Name IQ_DAILY: 500000
Name IQ_FH: 100000
Name IQ_FQ: 500
Name IQ_FY: 1000
Name IQ_LTM: 2000
Name IQ_MONTH: 15000
Name IQ_NTM: 6000
Name IQ_WEEK: 50000
Name IQ_YTD: 3000

Sheet Original
A1: Status | B1: Area | C1: Auditable Entity | D1: Auditable Sub - Entity | E1: Area | F1: SOL ID | G1: Accountable Exec. Role (N-1) | H1: Accountable Executive | I1: Business Owner (N-2) | J1: Business Owner (N-3) | K1: Audit Owner | L1: Inherent Risk | M1: Control Environment | N1: Calculated Residual Risk | O1: Original Audit Cycle | P1: Manually Adjusted Residual Risk | Q1: Regulatory | R1: Adjusted Audit Cycle | S1: Manual Override | T1: Last Audit Year | U1: Last Audit Rating | V1: Audit Plan 2022 | W1: Audit Plan 2023 | X1: Audit Plan 2024 | Y1: Audit Plan 2025 | Z1: In CY Audit Plan | AA1: Covered in Last 3 Years | AB1: Comments
A2: Original | B2: Retail Channels | C2: Branches | D2: Ajman | E2: Branches | F2: 019 | G2: MD Business Banking | H2: Dhiraj Kunwar | I2: Saud (Naji) Mohd. | K2: Sangeetha Abraham | L2: Medium | M2: =IF(T2>2017,U2,"N/A") -> Sat | N2: Medium | O2: =IF(Q2="y",1,SUMIFS('Rating Grid'!$D$11:$D$34,'Rating Grid'!$B$11:$B$34,Original!$L$30:$L$172,'Rating Grid'!$C$11:$C$34,Original!$M$30:$M$172)) -> 0 | P2: Low | Q2: N | R2: =IF(O2>S2,O2,S2) -> 0 | T2: 2020 | U2: Sat | V2: =IF($T2+$R2<=2022,"2022","-") -> 2022 | W2: =IF($T2+$R2=2023,"2023","-") -> - | X2: =IF($T2+$R2=2024,"2024","-") -> - | Y2: =IF($T2+$R2=2025,"2025","-") -> - | AA2: =IF($T2>2018,"Y","N") -> Y
A3: Original | B3: Retail Channels | C3: Branches | D3: Al Ain | E3: Branches | F3: 014 | G3: MD Business Banking | H3: Dhiraj Kunwar | I3: Saud (Naji) Mohd. | K3: Sangeetha Abraham | L3: Medium | M3: =IF(T3>2017,U3,"N/A") -> NI | N3: Medium | O3: =IF(Q3="y",1,SUMIFS('Rating Grid'!$D$11:$D$34,'Rating Grid'!$B$11:$B$34,Original!$L$30:$L$172,'Rating Grid'!$C$11:$C$34,Original!$M$30:$M$172)) -> 0 | P3: Medium | Q3: N | R3: =IF(O3>S3,O3,S3) -> 0 | T3: 2021 | U3: NI | V3: =IF($T3+$R3<=2022,"2022","-") -> 2022 | W3: =IF($T3+$R3=2023,"2023","-") -> - | X3: =IF($T3+$R3=2024,"2024","-") -> - | Y3: =IF($T3+$R3=2025,"2025","-") -> - | AA3: =IF($T3>2018,"Y","N") -> Y
A4: Original | B4: Retail Channels | C4: Branches | D4: Al Dhait | E4: Branches | F4: 031 | G4: MD Business Banking | H4: Dhiraj Kunwar | I4: Saud (Naji) Mohd. | K4: Sangeetha Abraham | L4: Medium | M4: =IF(T4>2017,U4,"N/A") -> NI | N4: Low | O4: =IF(Q4="y",1,SUMIFS('Rating Grid'!$D$11:$D$34,'Rating Grid'!$B$11:$B$34,Original!$L$30:$L$172,'Rating Grid'!$C$11:$C$34,Original!$M$30:$M$172)) -> 0 | P4: Medium | Q4: N | R4: =IF(O4>S4,O4,S4) -> 0 | T4: 2021 | U4: NI | V4: =IF($T4+$R4<=2022,"2022","-") -> 2022 | W4: =IF($T4+$R4=2023,"2023","-") -> - | X4: =IF($T4+$R4=2024,"2024","-") -> - | Y4: =IF($T4+$R4=2025,"2025","-") -> - | AA4: =IF($T4>2018,"Y","N") -> Y
A5: Original | B5: Retail Channels | C5: Branches | D5: Al Hamra | E5: Branches | F5: 065 | G5: MD Business Banking | H5: Dhiraj Kunwar | I5: Saud (Naji) Mohd. | K5: Sangeetha Abraham | L5: Medium | M5: =IF(T5>2017,U5,"N/A") -> Sat | N5: Low | O5: =IF(Q5="y",1,SUMIFS('Rating Grid'!$D$11:$D$34,'Rating Grid'!$B$11:$B$34,Original!$L$30:$L$172,'Rating Grid'!$C$11:$C$34,Original!$M$30:$M$172)) -> 0 | P5: Low | Q5: N | R5: =IF(O5>S5,O5,S5) -> 0 | T5: 2019 | U5: Sat | V5: =IF($T5+$R5<=2022,"2022","-") -> 2022 | W5: =IF($T5+$R5=2023,"2023","-") -> - | X5: =IF($T5+$R5=2024,"2024","-") -> - | Y5: =IF($T5+$R5=2025,"2025","-") -> - | AA5: =IF($T5>2018,"Y","N") -> Y
A6: Original | B6: Retail Channels | C6: Branches | D6: Al Kharan | E6: Branches | F6: 008 | G6: MD Business Banking | H6: Dhiraj Kunwar | I6: Saud (Naji) Mohd. | K6: Sangeetha Abraham | L6: Medium | M6: =IF(T6>2017,U6,"N/A") -> NI | N6: Low | O6: =IF(Q6="y",1,SUMIFS('Rating Grid'!$D$11:$D$34,'Rating Grid'!$B$11:$B$34,Original!$L$30:$L$172,'Rating Grid'!$C$11:$C$34,Original!$M$30:$M$172)) -> 0 | P6: Medium | Q6: N | R6: =IF(O6>S6,O6,S6) -> 0 | T6: 2020 | U6: NI | V6: =IF($T6+$R6<=2022,"2022","-") -> 2022 | W6: =IF($T6+$R6=2023,"2023","-") -> - | X6: =IF($T6+$R6=2024,"2024","-") -> - | Y6: =IF($T6+$R6=2025,"2025","-") -> - | AA6: =IF($T6>2018,"Y","N") -> Y
A7: Original | B7: Retail Channels | C7: Branches | D7: Al Madinah | E7: Branches | F7: 005 | G7: MD Business Banking | H7: Dhiraj Kunwar | I7: Saud (Naji) Mohd. | K7: Sangeetha Abraham | L7: Medium | M7: =IF(T7>2017,U7,"N/A") -> NI | N7: Medium | O7: =IF(Q7="y",1,SUMIFS('Rating Grid'!$D$11:$D$34,'Rating Grid'!$B$11:$B$34,Original!$L$30:$L$172,'Rating Grid'!$C$11:$C$34,Original!$M$30:$M$172)) -> 0 | P7: Medium | Q7: N | R7: =IF(O7>S7,O7,S7) -> 0 | T7: 2020 | U7: NI | V7: =IF($T7+$R7<=2022,"2022","-") -> 2022 | W7: =IF($T7+$R7=2023,"2023","-") -> - | X7: =IF($T7+$R7=2024,"2024","-") -> - | Y7: =IF($T7+$R7=2025,"2025","-") -> - | Z7: Y | AA7: =IF($T7>2018,"Y","N") -> Y | AB7: Q1 2022
A8: Original | B8: Retail Channels | C8: Branches | D8: Al Mannai | E8: Branches | F8: 016 | G8: MD Business Banking | H8: Dhiraj Kunwar | I8: Saud (Naji) Mohd. | K8: Sangeetha Abraham | L8: Medium | M8: =IF(T8>2017,U8,"N/A") -> NI | N8: Low | O8: =IF(Q8="y",1,SUMIFS('Rating Grid'!$D$11:$D$34,'Rating Grid'!$B$11:$B$34,Original!$L$30:$L$172,'Rating Grid'!$C$11:$C$34,Original!$M$30:$M$172)) -> 0 | P8: Medium | Q8: N | R8: =IF(O8>S8,O8,S8) -> 0 | T8: 2021 | U8: NI | V8: =IF($T8+$R8<=2022,"2022","-") -> 2022 | W8: =IF($T8+$R8=2023,"2023","-") -> - | X8: =IF($T8+$R8=2024,"2024","-") -> - | Y8: =IF($T8+$R8=2025,"2025","-") -> - | AA8: =IF($T8>2018,"Y","N") -> Y
A9: Original | B9: Retail Channels | C9: Branches | D9: Al Nakheel | E9: Branches | F9: 002 | G9: MD Business Banking | H9: Dhiraj Kunwar | I9: Saud (Naji) Mohd. | K9: Sangeetha Abraham | L9: Medium | M9: =IF(T9>2017,U9,"N/A") -> Sat | N9: Low | O9: =IF(Q9="y",1,SUMIFS('Rating Grid'!$D$11:$D$34,'Rating Grid'!$B$11:$B$34,Original!$L$30:$L$172,'Rating Grid'!$C$11:$C$34,Original!$M$30:$M$172)) -> 0 | P9: Low | Q9: N | R9: =IF(O9>S9,O9,S9) -> 0 | T9: 2019 | U9: Sat | V9: =IF($T9+$R9<=2022,"2022","-") -> 2022 | W9: =IF($T9+$R9=2023,"2023","-") -> - | X9: =IF($T9+$R9=2024,"2024","-") -> - | Y9: =IF($T9+$R9=2025,"2025","-") -> - | AA9: =IF($T9>2018,"Y","N") -> Y
A10: Original | B10: Retail Channels | C10: Branches | D10: Al Quoz | E10: Branches | F10: 035 | G10: MD Business Banking | H10: Dhiraj Kunwar | I10: Saud (Naji) Mohd. | K10: Sangeetha Abraham | L10: Medium | M10: =IF(T10>2017,U10,"N/A") -> Sat | N10: Low | O10: =IF(Q10="y",1,SUMIFS('Rating Grid'!$D$11:$D$34,'Rating Grid'!$B$11:$B$34,Original!$L$30:$L$172,'Rating Grid'!$C$11:$C$34,Original!$M$30:$M$172)) -> 0 | P10: Low | Q10: N | R10: =IF(O10>S10,O10,S10) -> 0 | T10: 2019 | U10: Sat | V10: =IF($T10+$R10<=2022,"2022","-") -> 2022 | W10: =IF($T10+$R10=2023,"2023","-") -> - | X10: =IF($T10+$R10=2024,"2024","-") -> - | Y10: =IF($T10+$R10=2025,"2025","-") -> - | AA10: =IF($T10>2018,"Y","N") -> Y
A11: Original | B11: Retail Channels | C11: Branches | D11: Al Qusais | E11: Branches | F11: 037 | G11: MD Business Banking | H11: Dhiraj Kunwar | I11: Saud (Naji) Mohd. | K11: Sangeetha Abraham | L11: Medium | M11: =IF(T11>2017,U11,"N/A") -> Sat | N11: Low | O11: =IF(Q11="y",1,SUMIFS('Rating Grid'!$D$11:$D$34,'Rating Grid'!$B$11:$B$34,Original!$L$30:$L$172,'Rating Grid'!$C$11:$C$34,Original!$M$30:$M$172)) -> 0 | P11: Low | Q11: N | R11: =IF(O11>S11,O11,S11) -> 0 | T11: 2020 | U11: Sat | V11: =IF($T11+$R11<=2022,"2022","-") -> 2022 | W11: =IF($T11+$R11=2023,"2023","-") -> - | X11: =IF($T11+$R11=2024,"2024","-") -> - | Y11: =IF($T11+$R11=2025,"2025","-") -> - | Z11: Y | AA11: =IF($T11>2018,"Y","N") -> Y | AB11: Q1 2022
A12: Original | B12: Retail Channels | C12: Branches | D12: Al Rams | E12: Branches | F12: 011 | G12: MD Business Banking | H12: Dhiraj Kunwar | I12: Saud (Naji) Mohd. | K12: Sangeetha Abraham | L12: Medium | M12: =IF(T12>2017,U12,"N/A") -> Sat | N12: Low | O12: =IF(Q12="y",1,SUMIFS('Rating Grid'!$D$11:$D$34,'Rating Grid'!$B$11:$B$34,Original!$L$30:$L$172,'Rating Grid'!$C$11:$C$34,Original!$M$30:$M$172)) -> 0 | P12: Low | Q12: N | R12: =IF(O12>S12,O12,S12) -> 0 | T12: 2019 | U12: Sat | V12: =IF($T12+$R12<=2022,"2022","-") -> 2022 | W12: =IF($T12+$R12=2023,"2023","-") -> - | X12: =IF($T12+$R12=2024,"2024","-") -> - | Y12: =IF($T12+$R12=2025,"2025","-") -> - | AA12: =IF($T12>2018,"Y","N") -> Y
A13: Original | B13: Retail Channels | C13: Branches | D13: Al Rolla | E13: Branches | F13: 057 | G13: MD Business Banking | H13: Dhiraj Kunwar | I13: Saud (Naji) Mohd. | K13: Sangeetha Abraham | L13: Medium | M13: =IF(T13>2017,U13,"N/A") -> Sat | N13: Low | O13: =IF(Q13="y",1,SUMIFS('Rating Grid'!$D$11:$D$34,'Rating Grid'!$B$11:$B$34,Original!$L$30:$L$172,'Rating Grid'!$C$11:$C$34,Original!$M$30:$M$172)) -> 0 | P13: Low | Q13: N | R13: =IF(O13>S13,O13,S13) -> 0 | T13: 2020 | U13: Sat | V13: =IF($T13+$R13<=2022,"2022","-") -> 2022 | W13: =IF($T13+$R13=2023,"2023","-") -> - | X13: =IF($T13+$R13=2024,"2024","-") -> - | Y13: =IF($T13+$R13=2025,"2025","-") -> - | AA13: =IF($T13>2018,"Y","N") -> Y
A14: Original | B14: Retail Channels | C14: Branches | D14: Deira Maktoum Street | E14: Branches | F14: 003 | G14: MD Business Banking | H14: Dhiraj Kunwar | I14: Saud (Naji) Mohd. | K14: Sangeetha Abraham | L14: Medium | M14: =IF(T14>2017,U14,"N/A") -> Sat | N14: Low | O14: =IF(Q14="y",1,SUMIFS('Rating Grid'!$D$11:$D$34,'Rating Grid'!$B$11:$B$34,Original!$L$30:$L$172,'Rating Grid'!$C$11:$C$34,Original!$M$30:$M$172)) -> 0 | P14: Low | Q14: N | R14: =IF(O14>S14,O14,S14) -> 0 | T14: 2020 | U14: Sat | V14: =IF($T14+$R14<=2022,"2022","-") -> 2022 | W14: =IF($T14+$R14=2023,"2023","-") -> - | X14: =IF($T14+$R14=2024,"2024","-") -> - | Y14: =IF($T14+$R14=2025,"2025","-") -> - | AA14: =IF($T14>2018,"Y","N") -> Y
A15: Original | B15: Retail Channels | C15: Branches | D15: Deira Souq | E15: Branches | F15: 025 | G15: MD Business Banking | H15: Dhiraj Kunwar | I15: Saud (Naji) Mohd. | K15: Sangeetha Abraham | L15: Medium | M15: =IF(T15>2017,U15,"N/A") -> Sat | N15: Low | O15: =IF(Q15="y",1,SUMIFS('Rating Grid'!$D$11:$D$34,'Rating Grid'!$B$11:$B$34,Original!$L$30:$L$172,'Rating Grid'!$C$11:$C$34,Original!$M$30:$M$172)) -> 0 | P15: Low | Q15: N | R15: =IF(O15>S15,O15,S15) -> 0 | T15: 2021 | U15: Sat | V15: =IF($T15+$R15<=2022,"2022","-") -> 2022 | W15: =IF($T15+$R15=2023,"2023","-") -> - | X15: =IF($T15+$R15=2024,"2024","-") -> - | Y15: =IF($T15+$R15=2025,"2025","-") -> - | AA15: =IF($T15>2018,"Y","N") -> Y
A16: Original | B16: Retail Channels | C16: Branches | D16: Dragon Mart | E16: Branches | F16: 088 | G16: MD Business Banking | H16: Dhiraj Kunwar | I16: Saud (Naji) Mohd. | K16: Sangeetha Abraham | L16: Medium | M16: =IF(T16>2017,U16,"N/A") -> NI | N16: Medium | O16: =IF(Q16="y",1,SUMIFS('Rating Grid'!$D$11:$D$34,'Rating Grid'!$B$11:$B$34,Original!$L$30:$L$172,'Rating Grid'!$C$11:$C$34,Original!$M$30:$M$172)) -> 0 | P16: Medium | Q16: N | R16: =IF(O16>S16,O16,S16) -> 0 | T16: 2020 | U16: NI | V16: =IF($T16+$R16<=2022,"2022","-") -> 2022 | W16: =IF($T16+$R16=2023,"2023","-") -> - | X16: =IF($T16+$R16=2024,"2024","-") -> - | Y16: =IF($T16+$R16=2025,"2025","-") -> - | AA16: =IF($T16>2018,"Y","N") -> Y
A17: Original | B17: Retail Channels | C17: Branches | D17: Emaar Business Park | E17: Branches | F17: 032 | G17: MD Business Banking | H17: Dhiraj Kunwar | I17: Saud (Naji) Mohd. | K17: Sangeetha Abraham | L17: Medium | M17: =IF(T17>2017,U17,"N/A") -> Sat | N17: Low | O17: =IF(Q17="y",1,SUMIFS('Rating Grid'!$D$11:$D$34,'Rating Grid'!$B$11:$B$34,Original!$L$30:$L$172,'Rating Grid'!$C$11:$C$34,Original!$M$30:$M$172)) -> 0 | P17: Low | Q17: N | R17: =IF(O17>S17,O17,S17) -> 0 | T17: 2020 | U17: Sat | V17: =IF($T17+$R17<=2022,"2022","-") -> 2022 | W17: =IF($T17+$R17=2023,"2023","-") -> - | X17: =IF($T17+$R17=2024,"2024","-") -> - | Y17: =IF($T17+$R17=2025,"2025","-") -> - | AA17: =IF($T17>2018,"Y","N") -> Y
A18: Original | B18: Retail Channels | C18: Branches | D18: Fujairah | E18: Branches | F18: 058 | G18: MD Business Banking | H18: Dhiraj Kunwar | I18: Saud (Naji) Mohd. | K18: Sangeetha Abraham | L18: Medium | M18: =IF(T18>2017,U18,"N/A") -> NI | N18: Low | O18: =IF(Q18="y",1,SUMIFS('Rating Grid'!$D$11:$D$34,'Rating Grid'!$B$11:$B$34,Original!$L$30:$L$172,'Rating Grid'!$C$11:$C$34,Original!$M$30:$M$172)) -> 0 | P18: Medium | Q18: N | R18: =IF(O18>S18,O18,S18) -> 0 | T18: 2019 | U18: NI | V18: =IF($T18+$R18<=2022,"2022","-") -> 2022 | W18: =IF($T18+$R18=2023,"2023","-") -> - | X18: =IF($T18+$R18=2024,"2024","-") -> - | Y18: =IF($T18+$R18=2025,"2025","-") -> - | AA18: =IF($T18>2018,"Y","N") -> Y
A19: Original | B19: Retail Channels | C19: Branches | D19: Ibn Battuta Mall | E19: Branches | F19: 029 | G19: MD Business Banking | H19: Dhiraj Kunwar | I19: Saud (Naji) Mohd. | K19: Sangeetha Abraham | L19: Medium | M19: =IF(T19>2017,U19,"N/A") -> NI | N19: Low | O19: =IF(Q19="y",1,SUMIFS('Rating Grid'!$D$11:$D$34,'Rating Grid'!$B$11:$B$34,Original!$L$30:$L$172,'Rating Grid'!$C$11:$C$34,Original!$M$30:$M$172)) -> 0 | P19: Medium | Q19: N | R19: =IF(O19>S19,O19,S19) -> 0 | T19: 2019 | U19: NI | V19: =IF($T19+$R19<=2022,"2022","-") -> 2022 | W19: =IF($T19+$R19=2023,"2023","-") -> - | X19: =IF($T19+$R19=2024,"2024","-") -> - | Y19: =IF($T19+$R19=2025,"2025","-") -> - | AA19: =IF($T19>2018,"Y","N") -> Y
A20: Original | B20: Retail Channels | C20: Branches | D20: Kalba | E20: Branches | F20: 007 | G20: MD Business Banking | H20: Dhiraj Kunwar | I20: Saud (Naji) Mohd. | K20: Sangeetha Abraham | L20: Medium | M20: =IF(T20>2017,U20,"N/A") -> NI | N20: Low | O20: =IF(Q20="y",1,SUMIFS('Rating Grid'!$D$11:$D$34,'Rating Grid'!$B$11:$B$34,Original!$L$30:$L$172,'Rating Grid'!$C$11:$C$34,Original!$M$30:$M$172)) -> 0 | P20: Medium | Q20: N | R20: =IF(O20>S20,O20,S20) -> 0 | T20: 2021 | U20: NI | V20: =IF($T20+$R20<=2022,"2022","-") -> 2022 | W20: =IF($T20+$R20=2023,"2023","-") -> - | X20: =IF($T20+$R20=2024,"2024","-") -> - | Y20: =IF($T20+$R20=2025,"2025","-") -> - | AA20: =IF($T20>2018,"Y","N") -> Y
A21: Original | B21: Retail Channels | C21: Branches | D21: Khalidiya | E21: Branches | F21: 030 | G21: MD Business Banking | H21: Dhiraj Kunwar | I21: Saud (Naji) Mohd. | K21: Sangeetha Abraham | L21: Medium | M21: =IF(T21>2017,U21,"N/A") -> NI | N21: Low | O21: =IF(Q21="y",1,SUMIFS('Rating Grid'!$D$11:$D$34,'Rating Grid'!$B$11:$B$34,Original!$L$30:$L$172,'Rating Grid'!$C$11:$C$34,Original!$M$30:$M$172)) -> 0 | P21: Medium | Q21: N | R21: =IF(O21>S21,O21,S21) -> 0 | T21: 2021 | U21: NI | V21: =IF($T21+$R21<=2022,"2022","-") -> 2022 | W21: =IF($T21+$R21=2023,"2023","-") -> - | X21: =IF($T21+$R21=2024,"2024","-") -> - | Y21: =IF($T21+$R21=2025,"2025","-") -> - | AA21: =IF($T21>2018,"Y","N") -> Y
A22: Original | B22: Retail Channels | C22: Branches | D22: King Faisal Street | E22: Branches | F22: 024 | G22: MD Business Banking | H22: Dhiraj Kunwar | I22: Saud (Naji) Mohd. | K22: Sangeetha Abraham | L22: Medium | M22: =IF(T22>2017,U22,"N/A") -> Sat | N22: Low | O22: =IF(Q22="y",1,SUMIFS('Rating Grid'!$D$11:$D$34,'Rating Grid'!$B$11:$B$34,Original!$L$30:$L$172,'Rating Grid'!$C$11:$C$34,Original!$M$30:$M$172)) -> 0 | P22: Low | Q22: N | R22: =IF(O22>S22,O22,S22) -> 0 | T22: 2019 | U22: Sat | V22: =IF($T22+$R22<=2022,"2022","-") -> 2022 | W22: =IF($T22+$R22=2023,"2023","-") -> - | X22: =IF($T22+$R22=2024,"2024","-") -> - | Y22: =IF($T22+$R22=2025,"2025","-") -> - | AA22: =IF($T22>2018,"Y","N") -> Y
A23: Original | B23: Retail Channels | C23: Branches | D23: Motor City | E23: Branches | F23: 033 | G23: MD Business Banking | H23: Dhiraj Kunwar | I23: Saud (Naji) Mohd. | K23: Sangeetha Abraham | L23: Medium | M23: =IF(T23>2017,U23,"N/A") -> Sat | N23: Low | O23: =IF(Q23="y",1,SUMIFS('Rating Grid'!$D$11:$D$34,'Rating Grid'!$B$11:$B$34,Original!$L$30:$L$172,'Rating Grid'!$C$11:$C$34,Original!$M$30:$M$172)) -> 0 | P23: Low | Q23: N | R23: =IF(O23>S23,O23,S23) -> 0 | T23: 2021 | U23: Sat | V23: =IF($T23+$R23<=2022,"2022","-") -> 2022 | W23: =IF($T23+$R23=2023,"2023","-") -> - | X23: =IF($T23+$R23=2024,"2024","-") -> - | Y23: =IF($T23+$R23=2025,"2025","-") -> - | AA23: =IF($T23>2018,"Y","N") -> Y
... A29: Original | B29: Retail Channels | C29: Branches | D29: Umm Hurair | E29: Branches | F29: 033 | G29: MD Business Banking | H29: Dhiraj Kunwar | I29: Saud (Naji) Mohd. | K29: Sangeetha Abraham | L29: Medium | M29: =IF(T29>2017,U29,"N/A") -> Sat | N29: Medium | O29: =IF(Q29="y",1,SUMIFS('Rating Grid'!$D$11:$D$34,'Rating Grid'!$B$11:$B$34,Original!$L$30:$L$172,'Rating Grid'!$C$11:$C$34,Original!$M$30:$M$172)) -> 0 | P29: Low | Q29: N | R29: =IF(O29>S29,O29,S29) -> 0 | T29: 2021 | U29: Sat | V29: =IF($T29+$R29<=2022,"2022","-") -> 2022 | W29: =IF($T29+$R29=2023,"2023","-") -> - | X29: =IF($T29+$R29=2024,"2024","-") -> - | Y29: =IF($T29+$R29=2025,"2025","-") -> - | AA29: =IF($T29>2018,"Y","N") -> Y
A30: Original | B30: Business Banking | C30: BBG - Liabilities | D30: BBG - Liabilities | E30: Business Banking | G30: MD Business Banking | H30: Dhiraj Kunwar | I30: Sulaiman Awan | K30: Neil Jarman | L30: Medium | M30: =IF(T30>2017,U30,"N/A") -> NI | N30: Medium | O30: =IF(Q30="y",1,SUMIFS('Rating Grid'!$D$11:$D$34,'Rating Grid'!$B$11:$B$34,Original!$L$30:$L$172,'Rating Grid'!$C$11:$C$34,Original!$M$30:$M$172)) -> 3 | P30: Medium | Q30: N | R30: =IF(O30>S30,O30,S30) -> 3 | T30: 2020 | U30: NI | V30: =IF($T30+$R30<=2022,"2022","-") -> - | W30: =IF($T30+$R30=2023,"2023","-") -> 2023 | X30: =IF($T30+$R30=2024,"2024","-") -> - | Y30: =IF($T30+$R30=2025,"2025","-") -> - | AA30: =IF($T30>2018,"Y","N") -> Y
A31: Original | B31: Business Banking | C31: BBG - National & Commercial Segment | D31: BBG - National & Commercial Segment | E31: Business Banking | G31: MD Business Banking | H31: Dhiraj Kunwar | I31: Emad Ahmed | K31: Neil Jarman | L31: Medium | M31: N/A | N31: Medium | O31: =IF(Q31="y",1,SUMIFS('Rating Grid'!$D$11:$D$34,'Rating Grid'!$B$11:$B$34,Original!$L$30:$L$172,'Rating Grid'!$C$11:$C$34,Original!$M$30:$M$172)) -> 3 | P31: Medium | Q31: N | R31: =IF(O31>S31,O31,S31) -> 3 | T31: 2021 | U31: Sat | V31: =IF($T31+$R31<=2022,"2022","-") -> - | W31: =IF($T31+$R31=2023,"2023","-") -> - | X31: =IF($T31+$R31=2024,"2024","-") -> 2024 | Y31: =IF($T31+$R31=2025,"2025","-") -> - | AA31: =IF($T31>2018,"Y","N") -> Y | AB31: Commercial Audit to be deferred on a prioritisation
A32: Original | B32: Corporate Functions | C32: Corporate Governance | D32: CEO's Office (Management Committees, Oversight, Strategy, Corp Communication) | E32: Corporate Functions | F32: 702 | G32: CEO | H32: Raheel Ahmed | I32: Amel B | K32: Moez Sassi | L32: Medium | M32: =IF(T32>2017,U32,"N/A") -> Sat | N32: Medium | O32: =IF(Q32="y",1,SUMIFS('Rating Grid'!$D$11:$D$34,'Rating Grid'!$B$11:$B$34,Original!$L$30:$L$172,'Rating Grid'!$C$11:$C$34,Original!$M$30:$M$172)) -> 3 | P32: Medium | Q32: N | R32: =IF(O32>S32,O32,S32) -> 3 | T32: 2018 | U32: Sat | V32: =IF($T32+$R32<=2022,"2022","-") -> 2022 | W32: =IF($T32+$R32=2023,"2023","-") -> - | X32: =IF($T32+$R32=2024,"2024","-") -> - | Y32: =IF($T32+$R32=2025,"2025","-") -> - | Z32: Y | AA32: =IF($T32>2018,"Y","N") -> N | AB32: Action plan till 2022, strategy due for revision
A33: Addition | B33: Corporate Functions | C33: Corporate Governance | D33: Company Secretary (Governance, Board and Board Committees) | E33: Corporate Functions | G33: Chief Legal Officer | H33: Ghalia Bushnaq | I33: Imad Khalil | K33: Moez Sassi | L33: Medium | M33: =IF(T33>2017,U33,"N/A") -> Sat | N33: Medium | O33: =IF(Q33="y",1,SUMIFS('Rating Grid'!$D$11:$D$34,'Rating Grid'!$B$11:$B$34,Original!$L$30:$L$172,'Rating Grid'!$C$11:$C$34,Original!$M$30:$M$172)) -> 3 | P33: Medium | Q33: N | R33: =IF(O33>S33,O33,S33) -> 3 | T33: 2018 | U33: Sat | V33: =IF($T33+$R33<=2022,"2022","-") -> 2022 | W33: =IF($T33+$R33=2023,"2023","-") -> - | X33: =IF($T33+$R33=2024,"2024","-") -> - | Y33: =IF($T33+$R33=2025,"2025","-") -> -
A34: Original | B34: Corporate Functions | C34: Strategic Planning & Initiatives | D34: Strategy | E34: Corporate Functions | F34: 702 | G34: Chief Customer Officer | H34: Dongjun Choi | I34: Gregory Thomas | K34: Moez Sassi | L34: Medium | M34: =IF(T34>2017,U34,"N/A") -> Unrated | N34: High | O34: =IF(Q34="y",1,SUMIFS('Rating Grid'!$D$11:$D$34,'Rating Grid'!$B$11:$B$34,Original!$L$30:$L$172,'Rating Grid'!$C$11:$C$34,Original!$M$30:$M$172)) -> 2 | P34: High | Q34: N | R34: =IF(O34>S34,O34,S34) -> 2 | T34: 2020 | U34: Unrated | V34: =IF($T34+$R34<=2022,"2022","-") -> 2022 | W34: =IF($T34+$R34=2023,"2023","-") -> - | X34: =IF($T34+$R34=2024,"2024","-") -> - | Y34: =IF($T34+$R34=2025,"2025","-") -> - | Z34: Y | AA34: =IF($T34>2018,"Y","N") -> Y
A35: Original | B35: Corporate Functions | C35: Investor Relations & Corp Comms | D35: Corporate Communications | E35: Corporate Functions | F35: 702 | G35: Chief Legal Officer | H35: Ghalia Bushnaq | I35: Imad Khalil | K35: Moez Sassi | L35: Low | M35: =IF(T35>2017,U35,"N/A") -> N/A | N35: Medium | O35: =IF(Q35="y",1,SUMIFS('Rating Grid'!$D$11:$D$34,'Rating Grid'!$B$11:$B$34,Original!$L$30:$L$172,'Rating Grid'!$C$11:$C$34,Original!$M$30:$M$172)) -> 4 | P35: Low | Q35: N | R35: =IF(O35>S35,O35,S35) -> 4 | U35: - | V35: =IF($T35+$R35<=2022,"2022","-") -> 2022 | W35: =IF($T35+$R35=2023,"2023","-") -> - | X35: =IF($T35+$R35=2024,"2024","-") -> - | Y35: =IF($T35+$R35=2025,"2025","-") -> -
A36: Original | B36: Corporate Functions | C36: HR | D36: Human Resources (Emiratisation & BRF Reporting) | E36: Corporate Functions | F36: 522, 703, 715 | G36: CHRO | H36: Ahmed Yousef | I36: Ahmed / Manal Ali | K36: Sangeetha Abraham | L36: Medium | M36: =IF(T36>2017,U36,"N/A") -> Sat | N36: Low | O36: =IF(Q36="y",1,SUMIFS('Rating Grid'!$D$11:$D$34,'Rating Grid'!$B$11:$B$34,Original!$L$30:$L$172,'Rating Grid'!$C$11:$C$34,Original!$M$30:$M$172)) -> 3 | P36: Medium | Q36: N | R36: =IF(O36>S36,O36,S36) -> 3 | T36: 2021 | U36: Sat | V36: =IF($T36+$R36<=2022,"2022","-") -> - | W36: =IF($T36+$R36=2023,"2023","-") -> - | X36: =IF($T36+$R36=2024,"2024","-") -> 2024 | Y36: =IF($T36+$R36=2025,"2025","-") -> - | AA36: =IF($T36>2018,"Y","N") -> Y | AB36: Emiratisation and BRF covered in 2019. The rating is changed from NI to SAT
A37: Original | B37: Corporate Functions | C37: HR | D37: Human Resources (Learning & Development) | E37: Corporate Functions | G37: CHRO | H37: Ahmed Yousef | I37: Ahmed / Sultan | K37: Sangeetha Abraham | L37: Medium | M37: =IF(T37>2017,U37,"N/A") -> N/A | N37: Low | O37: =IF(Q37="y",1,SUMIFS('Rating Grid'!$D$11:$D$34,'Rating Grid'!$B$11:$B$34,Original!$L$30:$L$172,'Rating Grid'!$C$11:$C$34,Original!$M$30:$M$172)) -> 3 | P37: Medium | Q37: N | R37: =IF(O37>S37,O37,S37) -> 3 | T37: 2015 | U37: Sat | V37: =IF($T37+$R37<=2022,"2022","-") -> 2022 | W37: =IF($T37+$R37=2023,"2023","-") -> - | X37: =IF($T37+$R37=2024,"2024","-") -> - | Y37: =IF($T37+$R37=2025,"2025","-") -> - | AA37: =IF($T37>2018,"Y","N") -> N
A38: Original | B38: Corporate Functions | C38: HR | D38: Human Resources (Organisational Effectiveness & Business Partnership) | E38: Corporate Functions | F38: 522, 703, 715 | G38: CHRO | H38: Ahmed Yousef | I38: Ahmed / Rajive Nair | K38: Sangeetha Abraham | L38: Medium | M38: =IF(T38>2017,U38,"N/A") -> NI | N38: Low | O38: =IF(Q38="y",1,SUMIFS('Rating Grid'!$D$11:$D$34,'Rating Grid'!$B$11:$B$34,Original!$L$30:$L$172,'Rating Grid'!$C$11:$C$34,Original!$M$30:$M$172)) -> 3 | P38: Medium | Q38: N | R38: =IF(O38>S38,O38,S38) -> 3 | T38: 2021 | U38: NI | V38: =IF($T38+$R38<=2022,"2022","-") -> - | W38: =IF($T38+$R38=2023,"2023","-") -> - | X38: =IF($T38+$R38=2024,"2024","-") -> 2024 | Y38: =IF($T38+$R38=2025,"2025","-") -> - | AA38: =IF($T38>2018,"Y","N") -> Y
A39: Original | B39: Corporate Functions | C39: HR | D39: Human Resources (Reward Strategy, Remuneration, Incentives) | E39: Corporate Functions | F39: 522, 703, 715 | G39: CHRO | H39: Ahmed Yousef | I39: Ahmed / Pooja | K39: Sangeetha Abraham | L39: Medium | M39: =IF(T39>2017,U39,"N/A") -> NI | N39: Low | O39: =IF(Q39="y",1,SUMIFS('Rating Grid'!$D$11:$D$34,'Rating Grid'!$B$11:$B$34,Original!$L$30:$L$172,'Rating Grid'!$C$11:$C$34,Original!$M$30:$M$172)) -> 3 | P39: Medium | Q39: N | R39: =IF(O39>S39,O39,S39) -> 3 | T39: 2021 | U39: NI | V39: =IF($T39+$R39<=2022,"2022","-") -> - | W39: =IF($T39+$R39=2023,"2023","-") -> - | X39: =IF($T39+$R39=2024,"2024","-") -> 2024 | Y39: =IF($T39+$R39=2025,"2025","-") -> - | AA39: =IF($T39>2018,"Y","N") -> Y
A40: Original | B40: Corporate Functions | C40: HR | D40: Human Resources (Talent Acquisition & HR Services) | E40: Corporate Functions | F40: 522, 703, 715 | G40: CHRO | H40: Ahmed Yousef | I40: Ahmed / Rajive | K40: Sangeetha Abraham | L40: Medium | M40: =IF(T40>2017,U40,"N/A") -> NI | N40: Low | O40: =IF(Q40="y",1,SUMIFS('Rating Grid'!$D$11:$D$34,'Rating Grid'!$B$11:$B$34,Original!$L$30:$L$172,'Rating Grid'!$C$11:$C$34,Original!$M$30:$M$172)) -> 3 | P40: Medium | Q40: N | R40: =IF(O40>S40,O40,S40) -> 3 | T40: 2021 | U40: NI | V40: =IF($T40+$R40<=2022,"2022","-") -> - | W40: =IF($T40+$R40=2023,"2023","-") -> - | X40: =IF($T40+$R40=2024,"2024","-") -> 2024 | Y40: =IF($T40+$R40=2025,"2025","-") -> - | AA40: =IF($T40>2018,"Y","N") -> Y
A41: Original | B41: Corporate Functions | C41: Legal | D41: Legal - Advisory | E41: Corporate Functions | F41: 736 | G41: Chief Legal Officer | H41: Ghalia Bushnaq | I41: Raunaq Baid | K41: Moez Sassi | L41: Medium | M41: =IF(T41>2017,U41,"N/A") -> Sat | N41: Medium | O41: =IF(Q41="y",1,SUMIFS('Rating Grid'!$D$11:$D$34,'Rating Grid'!$B$11:$B$34,Original!$L$30:$L$172,'Rating Grid'!$C$11:$C$34,Original!$M$30:$M$172)) -> 3 | P41: Medium | Q41: N | R41: =IF(O41>S41,O41,S41) -> 3 | T41: 2021 | U41: Sat | V41: =IF($T41+$R41<=2022,"2022","-") -> - | W41: =IF($T41+$R41=2023,"2023","-") -> - | X41: =IF($T41+$R41=2024,"2024","-") -> 2024 | Y41: =IF($T41+$R41=2025,"2025","-") -> - | AA41: =IF($T41>2018,"Y","N") -> Y
A42: Original | B42: Corporate Functions | C42: Legal | D42: Legal - Litigation | E42: Corporate Functions | G42: Chief Legal Officer | H42: Ghalia Bushnaq | I42: Abdulrahman Khesro | K42: Moez Sassi | L42: Medium | M42: =IF(T42>2017,U42,"N/A") -> Sat | N42: Medium | O42: =IF(Q42="y",1,SUMIFS('Rating Grid'!$D$11:$D$34,'Rating Grid'!$B$11:$B$34,Original!$L$30:$L$172,'Rating Grid'!$C$11:$C$34,Original!$M$30:$M$172)) -> 3 | P42: Medium | Q42: N | R42: =IF(O42>S42,O42,S42) -> 3 | T42: 2021 | U42: Sat | V42: =IF($T42+$R42<=2022,"2022","-") -> - | W42: =IF($T42+$R42=2023,"2023","-") -> - | X42: =IF($T42+$R42=2024,"2024","-") -> 2024 | Y42: =IF($T42+$R42=2025,"2025","-") -> - | AA42: Y
A43: Original | B43: Corporate Functions | C43: Marketing | D43: Marketing | E43: Corporate Functions | F43: 541 | G43: Chief Customer Officer | H43: Dongjun Choi | I43: Gary XX (resigned) | K43: Sangeetha Abraham | L43: Medium | M43: =IF(T43>2017,U43,"N/A") -> NI | N43: Medium | O43: =IF(Q43="y",1,SUMIFS('Rating Grid'!$D$11:$D$34,'Rating Grid'!$B$11:$B$34,Original!$L$30:$L$172,'Rating Grid'!$C$11:$C$34,Original!$M$30:$M$172)) -> 3 | P43: Medium | Q43: N | R43: =IF(O43>S43,O43,S43) -> 4 | S43: 4 | T43: 2019 | U43: NI | V43: =IF($T43+$R43<=2022,"2022","-") -> - | W43: =IF($T43+$R43=2023,"2023","-") -> 2023 | X43: =IF($T43+$R43=2024,"2024","-") -> - | Y43: =IF($T43+$R43=2025,"2025","-") -> - | Z43: y | AA43: =IF($T43>2018,"Y","N") -> Y | AB43: Manual override to 2023.
A44: Original | B44: Corporate Functions | C44: Project Management | D44: Project Management | E44: Operations | G44: CTO | H44: Saket | I44: James | K44: Neil Jarman | L44: High | M44: =IF(T44>2017,U44,"N/A") -> Unrated | N44: Medium | O44: =IF(Q44="y",1,SUMIFS('Rating Grid'!$D$11:$D$34,'Rating Grid'!$B$11:$B$34,Original!$L$30:$L$172,'Rating Grid'!$C$11:$C$34,Original!$M$30:$M$172)) -> 1 | P44: Medium | Q44: N | R44: =IF(O44>S44,O44,S44) -> 3 | S44: 3 | T44: 2021 | U44: Unrated | V44: =IF($T44+$R44<=2022,"2022","-") -> - | W44: =IF($T44+$R44=2023,"2023","-") -> - | X44: =IF($T44+$R44=2024,"2024","-") -> 2024 | Y44: =IF($T44+$R44=2025,"2025","-") -> - | Z44: Y | AA44: =IF($T44>2018,"Y","N") -> Y | AB44: Under consideration to be conducted in 2022 - Q3/4
A45: Original | B45: Corporate Functions | C45: Service Excellence | D45: Service Excellence Unit | E45: Corporate Functions | F45: 508, 560, 726 | G45: Chief Customer Officer | H45: Dongjun Choi | I45: Lina Yahya | K45: Sangeetha Abraham | L45: Medium | M45: =IF(T45>2017,U45,"N/A") -> NI | N45: Medium | O45: =IF(Q45="y",1,SUMIFS('Rating Grid'!$D$11:$D$34,'Rating Grid'!$B$11:$B$34,Original!$L$30:$L$172,'Rating Grid'!$C$11:$C$34,Original!$M$30:$M$172)) -> 3 | P45: Medium | Q45: N | R45: =IF(O45>S45,O45,S45) -> 3 | T45: 2019 | U45: NI | V45: =IF($T45+$R45<=2022,"2022","-") -> 2022 | W45: =IF($T45+$R45=2023,"2023","-") -> - | X45: =IF($T45+$R45=2024,"2024","-") -> - | Y45: =IF($T45+$R45=2025,"2025","-") -> - | Z45: Y | AA45: =IF($T45>2018,"Y","N") -> Y | AB45: Consumer Protection Framework (2022 - 5 audits covering implementation programme)
A46: Original | B46: Credit | C46: WBG & FIG Underwriting | D46: Wholesale Banking & Financial Institutions Credit | E46: Credit | G46: Chief Credit Officer | H46: Mahadevan Radhakanthan | I46: Pradeep Nehra | K46: Neil Jarman | L46: Medium | M46: =IF(T46>2017,U46,"N/A") -> NI | N46: Medium | O46: =IF(Q46="y",1,SUMIFS('Rating Grid'!$D$11:$D$34,'Rating Grid'!$B$11:$B$34,Original!$L$30:$L$172,'Rating Grid'!$C$11:$C$34,Original!$M$30:$M$172)) -> 3 | P46: Medium | Q46: N | R46: =IF(O46>S46,O46,S46) -> 3 | T46: 2019 | U46: NI | V46: =IF($T46+$R46<=2022,"2022","-") -> 2022 | W46: =IF($T46+$R46=2023,"2023","-") -> - | X46: =IF($T46+$R46=2024,"2024","-") -> - | Y46: =IF($T46+$R46=2025,"2025","-") -> - | Z46: Y | AA46: =IF($T46>2018,"Y","N") -> Y | AB46: Syndicated Lending - Q1
A47: Original | B47: Credit | C47: PBG - Underwriting | D47: Underwriting - (All Products) | E47: Credit | F47: 165, 166, 570 | G47: Chief Credit Officer | H47: Mahadevan Radhakanthan | I47: Maha / Vinay Nair | K47: Sangeetha Abraham | L47: Medium | M47: =IF(T47>2017,U47,"N/A") -> Sat | N47: Low | O47: =IF(Q47="y",1,SUMIFS('Rating Grid'!$D$11:$D$34,'Rating Grid'!$B$11:$B$34,Original!$L$30:$L$172,'Rating Grid'!$C$11:$C$34,Original!$M$30:$M$172)) -> 3 | P47: Low | Q47: N | R47: =IF(O47>S47,O47,S47) -> 3 | T47: 2020 | U47: Sat | V47: =IF($T47+$R47<=2022,"2022","-") -> - | W47: =IF($T47+$R47=2023,"2023","-") -> 2023 | X47: =IF($T47+$R47=2024,"2024","-") -> - | Y47: =IF($T47+$R47=2025,"2025","-") -> - | AA47: =IF($T47>2018,"Y","N") -> Y
A48: Original | B48: Credit | C48: BBG - Underwriting | D48: Business Banking Credit | E48: Credit | G48: Chief Credit Officer | H48: Mahadevan Radhakanthan | I48: Vinay Ambekar | K48: Neil Jarman | L48: Medium | M48: =IF(T48>2017,U48,"N/A") -> Sat | N48: Low | O48: =IF(Q48="y",1,SUMIFS('Rating Grid'!$D$11:$D$34,'Rating Grid'!$B$11:$B$34,Original!$L$30:$L$172,'Rating Grid'!$C$11:$C$34,Original!$M$30:$M$172)) -> 3 | P48: Low | Q48: N | R48: =IF(O48>S48,O48,S48) -> 3 | T48: 2021 | U48: Sat | V48: =IF($T48+$R48<=2022,"2022","-") -> - | W48: =IF($T48+$R48=2023,"2023","-") -> - | X48: =IF($T48+$R48=2024,"2024","-") -> 2024 | Y48: =IF($T48+$R48=2025,"2025","-") -> - | AA48: =IF($T48>2018,"Y","N") -> Y
A49: Original | B49: Credit | C49: BBG - Collections | D49: BBG Collections - All Products | E49: Credit | G49: Chief Credit Officer | H49: Mahadevan Radhakanthan | I49: Prashant | K49: Neil Jarman | L49: Medium | M49: =IF(T49>2017,U49,"N/A") -> NI | N49: Medium | O49: =IF(Q49="y",1,SUMIFS('Rating Grid'!$D$11:$D$34,'Rating Grid'!$B$11:$B$34,Original!$L$30:$L$172,'Rating Grid'!$C$11:$C$34,Original!$M$30:$M$172)) -> 3 | P49: Low | Q49: N | R49: =IF(O49>S49,O49,S49) -> 3 | T49: 2021 | U49: NI | V49: =IF($T49+$R49<=2022,"2022","-") -> - | W49: =IF($T49+$R49=2023,"2023","-") -> - | X49: =IF($T49+$R49=2024,"2024","-") -> 2024 | Y49: =IF($T49+$R49=2025,"2025","-") -> - | AA49: =IF($T49>2018,"Y","N") -> Y
A50: Original | B50: Credit | C50: WBG & FIG Collections | D50: WBG & FIG Collections (All Products) | E50: Credit | G50: Chief Credit Officer | H50: Mahadevan Radhakanthan | I50: Prashant | K50: Neil Jarman | L50: Medium | M50: =IF(T50>2017,U50,"N/A") -> N/A | N50: Medium | O50: =IF(Q50="y",1,SUMIFS('Rating Grid'!$D$11:$D$34,'Rating Grid'!$B$11:$B$34,Original!$L$30:$L$172,'Rating Grid'!$C$11:$C$34,Original!$M$30:$M$172)) -> 3 | P50: Medium | Q50: N | R50: =IF(O50>S50,O50,S50) -> 3 | T50: 2010 | U50: - | V50: =IF($T50+$R50<=2022,"2022","-") -> 2022 | W50: =IF($T50+$R50=2023,"2023","-") -> - | X50: =IF($T50+$R50=2024,"2024","-") -> - | Y50: =IF($T50+$R50=2025,"2025","-") -> -
A51: Original | B51: Credit | C51: WM - Underwriting | D51: Wealth Management & Investments - Underwriting (Credit) | E51: Credit | F51: 164 | G51: Chief Credit Officer | H51: Mahadevan Radhakanthan | I51: Maha / Vinay Nair | K51: Sangeetha Abraham | L51: Low | M51: =IF(T51>2017,U51,"N/A") -> Sat | N51: Low | O51: =IF(Q51="y",1,SUMIFS('Rating Grid'!$D$11:$D$34,'Rating Grid'!$B$11:$B$34,Original!$L$30:$L$172,'Rating Grid'!$C$11:$C$34,Original!$M$30:$M$172)) -> 4 | P51: Low | Q51: N | R51: =IF(O51>S51,O51,S51) -> 4 | T51: 2018 | U51: Sat | V51: =IF($T51+$R51<=2022,"2022","-") -> 2022 | W51: =IF($T51+$R51=2023,"2023","-") -> - | X51: =IF($T51+$R51=2024,"2024","-") -> - | Y51: =IF($T51+$R51=2025,"2025","-") -> - | Z51: Y | AA51: =IF($T51>2018,"Y","N") -> N | AB51: LAI
A52: Original | B52: Finance | C52: Financial Control | D52: Budgeting & Forecasting | E52: Finance | F52: 701 | G52: CFO | H52: Jaffar Nini | I52: Mridul | K52: Moez Sassi | L52: Medium | M52: =IF(T52>2017,U52,"N/A") -> Sat | N52: Medium | O52: =IF(Q52="y",1,SUMIFS('Rating Grid'!$D$11:$D$34,'Rating Grid'!$B$11:$B$34,Original!$L$30:$L$172,'Rating Grid'!$C$11:$C$34,Original!$M$30:$M$172)) -> 3 | P52: Medium | Q52: N | R52: =IF(O52>S52,O52,S52) -> 3 | T52: 2021 | U52: Sat | V52: =IF($T52+$R52<=2022,"2022","-") -> - | W52: =IF($T52+$R52=2023,"2023","-") -> - | X52: =IF($T52+$R52=2024,"2024","-") -> 2024 | Y52: =IF($T52+$R52=2025,"2025","-") -> - | AA52: =IF($T52>2018,"Y","N") -> Y
A53: Original | B53: Finance | C53: Financial Control | D53: Financial Accounting, Reporting & Controls (incl. provisions) | E53: Finance | F53: 701 | G53: CFO | H53: Jaffar Nini | I53: Manohar Bhoir/ Gireeshan | K53: Moez Sassi | L53: Medium | M53: =IF(T53>2017,U53,"N/A") -> Sat | N53: Medium | O53: =IF(Q53="y",1,SUMIFS('Rating Grid'!$D$11:$D$34,'Rating Grid'!$B$11:$B$34,Original!$L$30:$L$172,'Rating Grid'!$C$11:$C$34,Original!$M$30:$M$172)) -> 3 | P53: Medium | Q53: N | R53: =IF(O53>S53,O53,S53) -> 3 | T53: 2021 | U53: Sat | V53: =IF($T53+$R53<=2022,"2022","-") -> - | W53: =IF($T53+$R53=2023,"2023","-") -> - | X53: =IF($T53+$R53=2024,"2024","-") -> 2024 | Y53: =IF($T53+$R53=2025,"2025","-") -> - | AA53: =IF($T53>2018,"Y","N") -> Y
A54: Original | B54: Risk | C54: WBG - Credit Provisions (WBG, FIG & Treasury) | D54: Provisions - All Products | E54: Risk | G54: Chief Risk Officer | H54: Farhan Mahmoud | K54: Neil Jarman | L54: Medium | M54: =IF(T54>2017,U54,"N/A") -> NI | N54: Medium | O54: =IF(Q54="y",1,SUMIFS('Rating Grid'!$D$11:$D$34,'Rating Grid'!$B$11:$B$34,Original!$L$30:$L$172,'Rating Grid'!$C$11:$C$34,Original!$M$30:$M$172)) -> 1 | P54: Medium | Q54: Y | R54: =IF(O54>S54,O54,S54) -> 1 | T54: 2021 | U54: NI | V54: =IF($T54+$R54<=2022,"2022","-") -> 2022 | W54: =IF($T54+$R54=2023,"2023","-") -> - | X54: =IF($T54+$R54=2024,"2024","-") -> - | Y54: =IF($T54+$R54=2025,"2025","-") -> - | AA54: =IF($T54>2018,"Y","N") -> Y
A55: Original | B55: Finance | C55: Financial Control | D55: Management Reporting | E55: Finance | F55: 701 | G55: CFO | H55: Jaffar Nini | I55: Mridul | K55: Moez Sassi | L55: Medium | M55: =IF(T55>2017,U55,"N/A") -> Sat | N55: Medium | O55: =IF(Q55="y",1,SUMIFS('Rating Grid'!$D$11:$D$34,'Rating Grid'!$B$11:$B$34,Original!$L$30:$L$172,'Rating Grid'!$C$11:$C$34,Original!$M$30:$M$172)) -> 3 | P55: Medium | Q55: N | R55: =IF(O55>S55,O55,S55) -> 3 | T55: 2021 | U55: Sat | V55: =IF($T55+$R55<=2022,"2022","-") -> - | W55: =IF($T55+$R55=2023,"2023","-") -> - | X55: =IF($T55+$R55=2024,"2024","-") -> 2024 | Y55: =IF($T55+$R55=2025,"2025","-") -> - | AA55: =IF($T55>2018,"Y","N") -> Y
A56: Original | B56: Finance | C56: Regulatory Reporting | D56: Regulatory Reporting (BRFs) | E56: Finance | F56: 701 | G56: CFO | H56: Jaffar Nini | I56: Manohar Bhoir | K56: Moez Sassi | L56: Medium | M56: =IF(T56>2017,U56,"N/A") -> Sat | N56: Low | O56: =IF(Q56="y",1,SUMIFS('Rating Grid'!$D$11:$D$34,'Rating Grid'!$B$11:$B$34,Original!$L$30:$L$172,'Rating Grid'!$C$11:$C$34,Original!$M$30:$M$172)) -> 3 | P56: Low | Q56: N | R56: =IF(O56>S56,O56,S56) -> 3 | T56: 2021 | U56: Sat | V56: =IF($T56+$R56<=2022,"2022","-") -> - | W56: =IF($T56+$R56=2023,"2023","-") -> - | X56: =IF($T56+$R56=2024,"2024","-") -> 2024 | Y56: =IF($T56+$R56=2025,"2025","-") -> - | AA56: =IF($T56>2018,"Y","N") -> Y
A57: Original | B57: Finance | C57: Financial Control | D57: Taxation | E57: Finance | F57: 701 | G57: CFO | H57: Jaffar Nini | I57: Manohar Bhoir | K57: Moez Sassi | L57: Medium | M57: =IF(T57>2017,U57,"N/A") -> Unrated | N57: Low | O57: =IF(Q57="y",1,SUMIFS('Rating Grid'!$D$11:$D$34,'Rating Grid'!$B$11:$B$34,Original!$L$30:$L$172,'Rating Grid'!$C$11:$C$34,Original!$M$30:$M$172)) -> 2 | P57: Low | Q57: N | R57: =IF(O57>S57,O57,S57) -> 2 | T57: 2018 | U57: Unrated | V57: =IF($T57+$R57<=2022,"2022","-") -> 2022 | W57: =IF($T57+$R57=2023,"2023","-") -> - | X57: =IF($T57+$R57=2024,"2024","-") -> - | Y57: =IF($T57+$R57=2025,"2025","-") -> - | Z57: Y | AA57: =IF($T57>2018,"Y","N") -> N | AB57: VAT
A58: Original | B58: Wholesale Banking Group | C58: Coverage - Financial Institutions | D58: Financial Institutions | E58: WBG - Coverage | F58: 175 | G58: WBG Co-Head | H58: Jean Pierre Le Roux | I58: Craig Robertson (W); Srinivas Ramadurai (E) | K58: Neil Jarman | L58: Medium | M58: =IF(T58>2017,U58,"N/A") -> Sat | N58: Medium | O58: =IF(Q58="y",1,SUMIFS('Rating Grid'!$D$11:$D$34,'Rating Grid'!$B$11:$B$34,Original!$L$30:$L$172,'Rating Grid'!$C$11:$C$34,Original!$M$30:$M$172)) -> 3 | P58: Medium | Q58: N | R58: =IF(O58>S58,O58,S58) -> 3 | T58: 2019 | U58: Sat | V58: =IF($T58+$R58<=2022,"2022","-") -> 2022 | W58: =IF($T58+$R58=2023,"2023","-") -> - | X58: =IF($T58+$R58=2024,"2024","-") -> - | Y58: =IF($T58+$R58=2025,"2025","-") -> - | AA58: =IF($T58>2018,"Y","N") -> Y | AB58: To be covered under Syndicated Loans across WBG
A59: Original | B59: Wholesale Banking Group | C59: Coverage - Business Operational Risk Management | D59: Business Operational Risk Management | E59: WBG - Coverage | G59: WBG Co-Head | H59: Jean Pierre Le Roux | I59: Kartik Jayaram | K59: Neil Jarman | L59: Low | M59: =IF(T59>2017,U59,"N/A") -> Sat | N59: Low | O59: =IF(Q59="y",1,SUMIFS('Rating Grid'!$D$11:$D$34,'Rating Grid'!$B$11:$B$34,Original!$L$30:$L$172,'Rating Grid'!$C$11:$C$34,Original!$M$30:$M$172)) -> 4 | P59: Low | Q59: N | R59: =IF(O59>S59,O59,S59) -> 4 | T59: 2019 | U59: Sat | V59: 2022 | X59: =IF($T59+$R59=2024,"2024","-") -> - | Y59: =IF($T59+$R59=2025,"2025","-") -> - | Z59: Y | AA59: =IF($T59>2018,"Y","N") -> Y | AB59: Q1 - Syndicated Lending
A60: Original | B60: Wholesale Banking Group | C60: Product - Transaction Banking | D60: Transaction Banking | E60: WBG - Product | F60: 168, 169, 558 | G60: WBG Co-Head | H60: Vikas Suri | I60: Zavone Krotz | K60: Neil Jarman | L60: Medium | M60: Unrated | N60: Medium | O60: 3 | P60: Medium | Q60: N | R60: =IF(O60>S60,O60,S60) -> 3 | T60: 2017 | U60: Sat | V60: - | W60: 2023 | X60: =IF($T60+$R60=2024,"2024","-") -> - | Y60: =IF($T60+$R60=2025,"2025","-") -> - | AA60: =IF($T60>2018,"Y","N") -> N | AB60: TF strategy under development, audit planned post implementation PP2023
A61: Original | B61: Islamic Banking | C61: Sharia Governance & Risk Oversight | D61: Islamic Banking - Governance | E61: Islamic Banking | F61: 905 | G61: Director - Islamic Banking | H61: Abdul Karim Juma | I61: Husain Cuttleriwala | K61: Muhammad Abdulla | L61: Medium | M61: =IF(T61>2017,U61,"N/A") -> NI | N61: Medium | O61: =IF(Q61="y",1,SUMIFS('Rating Grid'!$D$11:$D$34,'Rating Grid'!$B$11:$B$34,Original!$L$30:$L$172,'Rating Grid'!$C$11:$C$34,Original!$M$30:$M$172)) -> 1 | P61: Medium | Q61: Y | R61: =IF(O61>S61,O61,S61) -> 1 | T61: 2021 | U61: NI | V61: =IF($T61+$R61<=2022,"2022","-") -> 2022 | W61: =IF($T61+$R61=2023,"2023","-") -> - | X61: =IF($T61+$R61=2024,"2024","-") -> - | Y61: =IF($T61+$R61=2025,"2025","-") -> - | Z61: Y | AA61: =IF($T61>2018,"Y","N") -> Y | AB61: Q3 / Q4
A62: Original | B62: Islamic Banking | C62: Sharia Operations | D62: Islamic Banking - Operations | E62: Islamic Banking | F62: 904 | G62: Head of Operations | H62: Juzer Netterwala | I62: Zeena Salim | K62: Muhammad Abdulla | L62: Medium | M62: =IF(T62>2017,U62,"N/A") -> NI | N62: Medium | O62: =IF(Q62="y",1,SUMIFS('Rating Grid'!$D$11:$D$34,'Rating Grid'!$B$11:$B$34,Original!$L$30:$L$172,'Rating Grid'!$C$11:$C$34,Original!$M$30:$M$172)) -> 1 | P62: Medium | Q62: Y | R62: =IF(O62>S62,O62,S62) -> 1 | T62: 2021 | U62: NI | V62: =IF($T62+$R62<=2022,"2022","-") -> 2022 | W62: =IF($T62+$R62=2023,"2023","-") -> - | X62: =IF($T62+$R62=2024,"2024","-") -> - | Y62: =IF($T62+$R62=2025,"2025","-") -> - | AA62: =IF($T62>2018,"Y","N") -> Y
A63: Original | B63: Islamic Banking | C63: Sharia Compliance | D63: Islamic Banking - Compliance | E63: Islamic Banking | F63: 905 | G63: Director - Islamic Banking | H63: Abdul Karim Juma | I63: Husain Cuttleriwala | K63: Muhammad Abdulla | L63: Medium | M63: =IF(T63>2017,U63,"N/A") -> NI | N63: Medium | O63: =IF(Q63="y",1,SUMIFS('Rating Grid'!$D$11:$D$34,'Rating Grid'!$B$11:$B$34,Original!$L$30:$L$172,'Rating Grid'!$C$11:$C$34,Original!$M$30:$M$172)) -> 1 | P63: Medium | Q63: Y | R63: =IF(O63>S63,O63,S63) -> 1 | T63: 2021 | U63: NI | V63: =IF($T63+$R63<=2022,"2022","-") -> 2022 | W63: =IF($T63+$R63=2023,"2023","-") -> - | X63: =IF($T63+$R63=2024,"2024","-") -> - | Y63: =IF($T63+$R63=2025,"2025","-") -> - | Z63: Y | AA63: =IF($T63>2018,"Y","N") -> Y | AB63: Q3 / Q4
A64: Original | B64: IT | C64: Business Applications | D64: Finacle Static Data | E64: IT | F64: 705 | G64: CTO | H64: Saket | I64: Robert Lee | J64: Vijay Harshen | K64: Biju Varughese | L64: High | M64: =IF(T64>2017,U64,"N/A") -> N/A | N64: Medium | O64: =IF(Q64="y",1,SUMIFS('Rating Grid'!$D$11:$D$34,'Rating Grid'!$B$11:$B$34,Original!$L$30:$L$172,'Rating Grid'!$C$11:$C$34,Original!$M$30:$M$172)) -> 2 | P64: Medium | Q64: N | R64: =IF(O64>S64,O64,S64) -> 2 | T64: 2017 | U64: Sat | V64: =IF($T64+$R64<=2022,"2022","-") -> 2022 | W64: =IF($T64+$R64=2023,"2023","-") -> - | X64: =IF($T64+$R64=2024,"2024","-") -> - | Y64: =IF($T64+$R64=2025,"2025","-") -> - | Z64: Y | AA64: =IF($T64>2018,"Y","N") -> N
A65: Original | B65: IT | C65: IT Governance, Process & Services | D65: IT Change & Service Management | E65: IT | F65: 705 | G65: CTO | H65: Saket | I65: Robert Lee | J65: Tabrez Sheikh | K65: Biju Varughese | L65: Medium | M65: =IF(T65>2017,U65,"N/A") -> NI | N65: Medium | O65: =IF(Q65="y",1,SUMIFS('Rating Grid'!$D$11:$D$34,'Rating Grid'!$B$11:$B$34,Original!$L$30:$L$172,'Rating Grid'!$C$11:$C$34,Original!$M$30:$M$172)) -> 3 | P65: Medium | Q65: N | R65: =IF(O65>S65,O65,S65) -> 3 | T65: 2021 | U65: NI | V65: =IF($T65+$R65<=2022,"2022","-") -> - | W65: =IF($T65+$R65=2023,"2023","-") -> - | X65: =IF($T65+$R65=2024,"2024","-") -> 2024 | Y65: =IF($T65+$R65=2025,"2025","-") -> - | AA65: =IF($T65>2018,"Y","N") -> Y
A66: Original | B66: IT | C66: IT Infrastructure | D66: Cloud applications | E66: IT | F66: 705 | G66: CTO | H66: Saket | I66: Robert Lee | J66: Jonathan Gonsalves / Shyam Kesarwani | K66: Biju Varughese | L66: Medium | M66: =IF(T66>2017,U66,"N/A") -> N/A | N66: Medium | O66: =IF(Q66="y",1,SUMIFS('Rating Grid'!$D$11:$D$34,'Rating Grid'!$B$11:$B$34,Original!$L$30:$L$172,'Rating Grid'!$C$11:$C$34,Original!$M$30:$M$172)) -> 3 | P66: Medium | Q66: N | R66: =IF(O66>S66,O66,S66) -> 3 | T66: 2010 | U66: - | V66: =IF($T66+$R66<=2022,"2022","-") -> 2022 | W66: =IF($T66+$R66=2023,"2023","-") -> - | X66: =IF($T66+$R66=2024,"2024","-") -> - | Y66: =IF($T66+$R66=2025,"2025","-") -> - | AA66: =IF($T66>2018,"Y","N") -> N
A67: Original | B67: Risk | C67: IT Risk / Information Security | D67: NESA Compliance | E67: IT | F67: 705 | G67: Chief Risk Officer | H67: Farhan Mahmoud | I67: Safwan Ghaleb | J67: Tushar Vartak | K67: Biju Varughese | L67: Medium | M67: =IF(T67>2017,U67,"N/A") -> NI | N67: Medium | O67: =IF(Q67="y",1,SUMIFS('Rating Grid'!$D$11:$D$34,'Rating Grid'!$B$11:$B$34,Original!$L$30:$L$172,'Rating Grid'!$C$11:$C$34,Original!$M$30:$M$172)) -> 3 | P67: Medium | Q67: N | R67: =IF(O67>S67,O67,S67) -> 3 | T67: 2020 | U67: NI | V67: =IF($T67+$R67<=2022,"2022","-") -> - | W67: =IF($T67+$R67=2023,"2023","-") -> 2023 | X67: =IF($T67+$R67=2024,"2024","-") -> - | Y67: =IF($T67+$R67=2025,"2025","-") -> - | AA67: =IF($T67>2018,"Y","N") -> Y
A68: Original | B68: IT | C68: IT Governance, Process & Services | D68: IT Development | E68: IT | F68: 705 | G68: CTO | H68: Saket | I68: Robert Lee | J68: Ajit Pillai | K68: Biju Varughese | L68: Medium | M68: =IF(T68>2017,U68,"N/A") -> Sat | N68: Low | O68: =IF(Q68="y",1,SUMIFS('Rating Grid'!$D$11:$D$34,'Rating Grid'!$B$11:$B$34,Original!$L$30:$L$172,'Rating Grid'!$C$11:$C$34,Original!$M$30:$M$172)) -> 3 | P68: Low | Q68: N | R68: =IF(O68>S68,O68,S68) -> 3 | T68: 2020 | U68: Sat | V68: =IF($T68+$R68<=2022,"2022","-") -> - | W68: =IF($T68+$R68=2023,"2023","-") -> 2023 | X68: =IF($T68+$R68=2024,"2024","-") -> - | Y68: =IF($T68+$R68=2025,"2025","-") -> - | AA68: =IF($T68>2018,"Y","N") -> Y
A69: Original | B69: IT | C69: IT Infrastructure | D69: IT Network Management, Voice and Security | E69: IT | F69: 705 | G69: CTO | H69: Saket | I69: Robert Lee | J69: Jonathan Gonsalves | K69: Biju Varughese | L69: High | M69: =IF(T69>2017,U69,"N/A") -> Sat | N69: Low | O69: =IF(Q69="y",1,SUMIFS('Rating Grid'!$D$11:$D$34,'Rating Grid'!$B$11:$B$34,Original!$L$30:$L$172,'Rating Grid'!$C$11:$C$34,Original!$M$30:$M$172)) -> 2 | P69: Low | Q69: N | R69: =IF(O69>S69,O69,S69) -> 2 | T69: 2019 | U69: Sat | V69: =IF($T69+$R69<=2022,"2022","-") -> 2022 | W69: =IF($T69+$R69=2023,"2023","-") -> - | X69: =IF($T69+$R69=2024,"2024","-") -> - | Y69: =IF($T69+$R69=2025,"2025","-") -> - | Z69: Y | AA69: =IF($T69>2018,"Y","N") -> Y
A70: Original | B70: IT | C70: IT Infrastructure | D70: Middleware (One-off) | E70: IT | F70: 705 | G70: CTO | H70: Saket | I70: Robert Lee | K70: Biju Varughese | L70: Medium | M70: =IF(T70>2017,U70,"N/A") -> N/A | N70: Medium | O70: =IF(Q70="y",1,SUMIFS('Rating Grid'!$D$11:$D$34,'Rating Grid'!$B$11:$B$34,Original!$L$30:$L$172,'Rating Grid'!$C$11:$C$34,Original!$M$30:$M$172)) -> 3 | P70: Medium | Q70: N | R70: =IF(O70>S70,O70,S70) -> 3 | T70: 2010 | U70: - | V70: =IF($T70+$R70<=2022,"2022","-") -> 2022 | W70: =IF($T70+$R70=2023,"2023","-") -> - | X70: =IF($T70+$R70=2024,"2024","-") -> - | Y70: =IF($T70+$R70=2025,"2025","-") -> - | AA70: =IF($T70>2018,"Y","N") -> N | AB70: One-off due to changing Middleware structure
A71: Original | B71: IT | C71: Third Parties | D71: Third party IT controls | E71: IT | F71: 705 | G71: CTO | H71: Saket | I71: BU Director &Robert Lee | K71: Biju Varughese | L71: Medium | M71: =IF(T71>2017,U71,"N/A") -> N/A | N71: Medium | O71: =IF(Q71="y",1,SUMIFS('Rating Grid'!$D$11:$D$34,'Rating Grid'!$B$11:$B$34,Original!$L$30:$L$172,'Rating Grid'!$C$11:$C$34,Original!$M$30:$M$172)) -> 3 | P71: High | Q71: N | R71: =IF(O71>S71,O71,S71) -> 3 | T71: 2010 | U71: - | V71: =IF($T71+$R71<=2022,"2022","-") -> 2022 | W71: =IF($T71+$R71=2023,"2023","-") -> - | X71: =IF($T71+$R71=2024,"2024","-") -> - | Y71: =IF($T71+$R71=2025,"2025","-") -> - | AA71: =IF($T71>2018,"Y","N") -> N
A72: Original | B72: IT | C72: Business Applications | D72: Swift & Payment Gateways | E72: IT | F72: 551 | G72: CTO | H72: Saket | I72: Robert Lee | K72: Biju Varughese | L72: High | M72: =IF(T72>2017,U72,"N/A") -> NI | N72: Medium | O72: =IF(Q72="y",1,SUMIFS('Rating Grid'!$D$11:$D$34,'Rating Grid'!$B$11:$B$34,Original!$L$30:$L$172,'Rating Grid'!$C$11:$C$34,Original!$M$30:$M$172)) -> 2 | P72: High | Q72: N | R72: =IF(O72>S72,O72,S72) -> 2 | T72: 2020 | U72: NI | V72: =IF($T72+$R72<=2022,"2022","-") -> 2022 | W72: =IF($T72+$R72=2023,"2023","-") -> - | X72: =IF($T72+$R72=2024,"2024","-") -> - | Y72: =IF($T72+$R72=2025,"2025","-") -> - | AA72: =IF($T72>2018,"Y","N") -> Y
A73: Original | B73: IT | C73: IT Infrastructure | D73: IT Infrastructure | E73: IT | F73: 705 | G73: CTO | H73: Saket | I73: Robert Lee | J73: Jonathan Gonsalves | K73: Biju Varughese | L73: High | M73: =IF(T73>2017,U73,"N/A") -> NI | N73: Medium | O73: =IF(Q73="y",1,SUMIFS('Rating Grid'!$D$11:$D$34,'Rating Grid'!$B$11:$B$34,Original!$L$30:$L$172,'Rating Grid'!$C$11:$C$34,Original!$M$30:$M$172)) -> 2 | P73: Medium | Q73: N | R73: =IF(O73>S73,O73,S73) -> 3 | S73: 3 | T73: 2019 | U73: NI | V73: =IF($T73+$R73<=2022,"2022","-") -> 2022 | W73: =IF($T73+$R73=2023,"2023","-") -> - | X73: =IF($T73+$R73=2024,"2024","-") -> - | Y73: =IF($T73+$R73=2025,"2025","-") -> - | AA73: =IF($T73>2018,"Y","N") -> Y
A74: Original | B74: IT | C74: Business Applications | D74: User Access Management | E74: IT | F74: 705 | G74: CTO | H74: Saket | I74: Robert Lee | J74: Sh Abdullah | K74: Biju Varughese | L74: Medium | M74: =IF(T74>2017,U74,"N/A") -> NI | N74: Medium | O74: =IF(Q74="y",1,SUMIFS('Rating Grid'!$D$11:$D$34,'Rating Grid'!$B$11:$B$34,Original!$L$30:$L$172,'Rating Grid'!$C$11:$C$34,Original!$M$30:$M$172)) -> 3 | P74: high | Q74: N | R74: =IF(O74>S74,O74,S74) -> 3 | T74: 2018 | U74: NI | V74: =IF($T74+$R74<=2022,"2022","-") -> 2022 | W74: =IF($T74+$R74=2023,"2023","-") -> - | X74: =IF($T74+$R74=2024,"2024","-") -> - | Y74: =IF($T74+$R74=2025,"2025","-") -> - | Z74: Y | AA74: =IF($T74>2018,"Y","N") -> N | AB74: Q1
A75: Original | B75: Corporate Functions | C75: Administration & Asset Management | D75: Administration & Asset Management | E75: Corporate Functions | F75: 704 | G75: CFO | H75: Deepak Majithia | I75: Shameek | K75: Sangeetha Abraham | L75: Low | M75: =IF(T75>2017,U75,"N/A") -> NI | N75: Medium | O75: =IF(Q75="y",1,SUMIFS('Rating Grid'!$D$11:$D$34,'Rating Grid'!$B$11:$B$34,Original!$L$30:$L$172,'Rating Grid'!$C$11:$C$34,Original!$M$30:$M$172)) -> 4 | P75: Medium | Q75: N | R75: =IF(O75>S75,O75,S75) -> 4 | T75: 2019 | U75: NI | V75: =IF($T75+$R75<=2022,"2022","-") -> - | W75: =IF($T75+$R75=2023,"2023","-") -> 2023 | X75: =IF($T75+$R75=2024,"2024","-") -> - | Y75: =IF($T75+$R75=2025,"2025","-") -> - | AA75: =IF($T75>2018,"Y","N") -> Y
A76: Original | B76: Operations | C76: Business Continuity Management | D76: Business Continuity Management & Disaster Recovery | E76: Operations | F76: 709 | G76: CRO | H76: Farhan Mahmoud | I76: Jiju | J76: Prem Achutha | K76: Biju Varughese | L76: High | M76: =IF(T76>2017,U76,"N/A") -> Sat | N76: Medium | O76: =IF(Q76="y",1,SUMIFS('Rating Grid'!$D$11:$D$34,'Rating Grid'!$B$11:$B$34,Original!$L$30:$L$172,'Rating Grid'!$C$11:$C$34,Original!$M$30:$M$172)) -> 2 | P76: Medium | Q76: N | R76: =IF(O76>S76,O76,S76) -> 2 | T76: 2021 | U76: Sat | V76: =IF($T76+$R76<=2022,"2022","-") -> - | W76: =IF($T76+$R76=2023,"2023","-") -> 2023 | X76: =IF($T76+$R76=2024,"2024","-") -> - | Y76: =IF($T76+$R76=2025,"2025","-") -> - | AA76: =IF($T76>2018,"Y","N") -> Y
A77: Original | B77: Operations | C77: Cash Management | D77: Cash Management (Clearing, Nostros) | E77: Operations | G77: COO | H77: Michael Power | I77: Juzer Netterwala | J77: Saeed | K77: Sangeetha Abraham | L77: Medium | M77: =IF(T77>2017,U77,"N/A") -> Sat | N77: Medium | O77: =IF(Q77="y",1,SUMIFS('Rating Grid'!$D$11:$D$34,'Rating Grid'!$B$11:$B$34,Original!$L$30:$L$172,'Rating Grid'!$C$11:$C$34,Original!$M$30:$M$172)) -> 3 | P77: Medium | Q77: N | R77: =IF(O77>S77,O77,S77) -> 3 | T77: 2018 | U77: Sat | V77: =IF($T77+$R77<=2022,"2022","-") -> 2022 | W77: =IF($T77+$R77=2023,"2023","-") -> - | X77: =IF($T77+$R77=2024,"2024","-") -> - | Y77: =IF($T77+$R77=2025,"2025","-") -> - | Z77: Y | AA77: =IF($T77>2018,"Y","N") -> N | AB77: Not in initial audit plan. Not consistent with the rating. Inherent risk should be Medium not High.
A78: Original | B78: Operations | C78: Central Operations (Financial) | D78: Central Operations (Financial) | E78: Operations | F78: 510 | G78: COO | H78: Michael Power | I78: Juzer Netterwala | J78: Saeed | K78: Sangeetha Abraham | L78: Medium | M78: =IF(T78>2017,U78,"N/A") -> Sat | N78: Low | O78: =IF(Q78="y",1,SUMIFS('Rating Grid'!$D$11:$D$34,'Rating Grid'!$B$11:$B$34,Original!$L$30:$L$172,'Rating Grid'!$C$11:$C$34,Original!$M$30:$M$172)) -> 3 | P78: Medium | Q78: N | R78: =IF(O78>S78,O78,S78) -> 3 | T78: 2021 | U78: Sat | V78: =IF($T78+$R78<=2022,"2022","-") -> - | W78: =IF($T78+$R78=2023,"2023","-") -> - | X78: =IF($T78+$R78=2024,"2024","-") -> 2024 | Y78: =IF($T78+$R78=2025,"2025","-") -> - | AA78: =IF($T78>2018,"Y","N") -> Y
A79: Original | B79: Operations | C79: Central Operations (Non-Financial) | D79: Central Operations (Non-Financial) | E79: Operations | F79: 510 | G79: COO | H79: Michael Power | I79: Juzer Netterwala | J79: Saeed | K79: Sangeetha Abraham | L79: Low | M79: =IF(T79>2017,U79,"N/A") -> Sat | N79: Very Low | O79: =IF(Q79="y",1,SUMIFS('Rating Grid'!$D$11:$D$34,'Rating Grid'!$B$11:$B$34,Original!$L$30:$L$172,'Rating Grid'!$C$11:$C$34,Original!$M$30:$M$172)) -> 4 | P79: low | Q79: N | R79: =IF(O79>S79,O79,S79) -> 4 | T79: 2021 | U79: Sat | V79: =IF($T79+$R79<=2022,"2022","-") -> - | W79: =IF($T79+$R79=2023,"2023","-") -> - | X79: =IF($T79+$R79=2024,"2024","-") -> - | Y79: =IF($T79+$R79=2025,"2025","-") -> 2025 | AA79: =IF($T79>2018,"Y","N") -> Y
A80: Original | B80: Operations | C80: BBG - Operations & Acct Monitoring | D80: Commercial Banking - Operations & Account monitoring | E80: Operations | G80: COO | H80: Michael Power | I80: Juzer Netterwala | J80: Shalini Mehta | K80: Neil Jarman | L80: Medium | M80: =IF(T80>2017,U80,"N/A") -> Sat | N80: Low | O80: =IF(Q80="y",1,SUMIFS('Rating Grid'!$D$11:$D$34,'Rating Grid'!$B$11:$B$34,Original!$L$30:$L$172,'Rating Grid'!$C$11:$C$34,Original!$M$30:$M$172)) -> 3 | P80: Medium | Q80: N | R80: =IF(O80>S80,O80,S80) -> 3 | T80: 2021 | U80: Sat | V80: =IF($T80+$R80<=2022,"2022","-") -> - | W80: =IF($T80+$R80=2023,"2023","-") -> - | X80: =IF($T80+$R80=2024,"2024","-") -> 2024 | Y80: =IF($T80+$R80=2025,"2025","-") -> - | AA80: =IF($T80>2018,"Y","N") -> Y
A81: Original | B81: Operations | C81: WBG - Operations & Acct Monitoring | D81: Corporate Banking - Operations & Account monitoring - All Products | E81: Operations | G81: COO | H81: Michael Power | I81: Juzer Netterwala | J81: Shalini Mehta | K81: Neil Jarman | L81: Medium | M81: =IF(T81>2017,U81,"N/A") -> Sat | N81: Low | O81: =IF(Q81="y",1,SUMIFS('Rating Grid'!$D$11:$D$34,'Rating Grid'!$B$11:$B$34,Original!$L$30:$L$172,'Rating Grid'!$C$11:$C$34,Original!$M$30:$M$172)) -> 3 | P81: Medium | Q81: N | R81: =IF(O81>S81,O81,S81) -> 3 | T81: 2020 | U81: Sat | V81: =IF($T81+$R81<=2022,"2022","-") -> - | W81: =IF($T81+$R81=2023,"2023","-") -> 2023 | X81: =IF($T81+$R81=2024,"2024","-") -> - | Y81: =IF($T81+$R81=2025,"2025","-") -> - | Z81: Y | AA81: =IF($T81>2018,"Y","N") -> Y | AB81: Q1
A82: Original | B82: Operations | C82: PBG - Operations & Acct Monitoring | D82: Credit Operations - (All Products) | E82: Operations | F82: 151, 556 | G82: COO | H82: Michael Power | I82: Juzer Netterwala | K82: Sangeetha Abraham | L82: Medium | M82: =IF(T82>2017,U82,"N/A") -> Sat | N82: Low | O82: =IF(Q82="y",1,SUMIFS('Rating Grid'!$D$11:$D$34,'Rating Grid'!$B$11:$B$34,Original!$L$30:$L$172,'Rating Grid'!$C$11:$C$34,Original!$M$30:$M$172)) -> 3 | P82: Medium | Q82: N | R82: =IF(O82>S82,O82,S82) -> 3 | T82: 2020 | U82: Sat | V82: =IF($T82+$R82<=2022,"2022","-") -> - | W82: =IF($T82+$R82=2023,"2023","-") -> 2023 | X82: =IF($T82+$R82=2024,"2024","-") -> - | Y82: =IF($T82+$R82=2025,"2025","-") -> - | AA82: =IF($T82>2018,"Y","N") -> Y | AB82: Information incorrect. The audit was performed in 2019. Included as part of mortgage audit.
A83: Original | B83: Operations | C83: Documents Archival & Retrieval | D83: Documents Archival & Retrieval | E83: Operations | F83: 731 | G83: COO | H83: Michael Power | I83: Shameek | K83: Sangeetha Abraham | L83: Very Low | M83: =IF(T83>2017,U83,"N/A") -> NI | N83: Very Low | O83: =IF(Q83="y",1,SUMIFS('Rating Grid'!$D$11:$D$34,'Rating Grid'!$B$11:$B$34,Original!$L$30:$L$172,'Rating Grid'!$C$11:$C$34,Original!$M$30:$M$172)) -> 0 | P83: Very Low | Q83: N | R83: =IF(O83>S83,O83,S83) -> 4 | S83: 4 | T83: 2019 | U83: NI | V83: =IF($T83+$R83<=2022,"2022","-") -> - | W83: =IF($T83+$R83=2023,"2023","-") -> 2023 | X83: =IF($T83+$R83=2024,"2024","-") -> - | Y83: =IF($T83+$R83=2025,"2025","-") -> - | AA83: =IF($T83>2018,"Y","N") -> Y | AB83: Administrative framework
A84: Original | B84: Operations | C84: Third Parties | D84: Outsourced Activities - General and Strategy | E84: Operations | F84: 705 | G84: COO | H84: Michael Power | I84: Juzer Netterwala | J84: Sandeep Athavale | K84: Sangeetha Abraham | L84: Medium | M84: =IF(T84>2017,U84,"N/A") -> Sat | N84: Medium | O84: =IF(Q84="y",1,SUMIFS('Rating Grid'!$D$11:$D$34,'Rating Grid'!$B$11:$B$34,Original!$L$30:$L$172,'Rating Grid'!$C$11:$C$34,Original!$M$30:$M$172)) -> 3 | P84: Medium | Q84: N | R84: =IF(O84>S84,O84,S84) -> 3 | T84: 2021 | U84: Sat | V84: =IF($T84+$R84<=2022,"2022","-") -> - | W84: =IF($T84+$R84=2023,"2023","-") -> - | X84: =IF($T84+$R84=2024,"2024","-") -> 2024 | Y84: =IF($T84+$R84=2025,"2025","-") -> - | AA84: =IF($T84>2018,"Y","N") -> Y | AB84: WIPRO Only - Covered as central Ops, WM Ops, remittance audit and customer on-boarding 2022.
A85: Original | B85: Corporate Functions | C85: Premises & Facilities Management | D85: Premises & Facilities Management | E85: Corporate Functions | F85: 711 | G85: CFO | H85: Deepak Majithia | I85: Shameek | K85: Sangeetha Abraham | L85: Very Low | M85: =IF(T85>2017,U85,"N/A") -> N/A | N85: Very Low | O85: =IF(Q85="y",1,SUMIFS('Rating Grid'!$D$11:$D$34,'Rating Grid'!$B$11:$B$34,Original!$L$30:$L$172,'Rating Grid'!$C$11:$C$34,Original!$M$30:$M$172)) -> 0 | P85: Very Low | Q85: N | R85: 0 | S85: 4 | T85: 2015 | U85: Sat | W85: 2023 | X85: =IF($T85+$R85=2024,"2024","-") -> - | Y85: =IF($T85+$R85=2025,"2025","-") -> - | AA85: =IF($T85>2018,"Y","N") -> N | AB85: Stakeholder Management only.
A86: Original | B86: Corporate Functions | C86: Procurement & Vendor Management | D86: Procurement / Vendor Management | E86: Corporate Functions | G86: CFO | H86: Deepak Majithia | I86: Shameek | K86: Sangeetha Abraham | L86: Medium | M86: =IF(T86>2017,U86,"N/A") -> NI | N86: Medium | O86: =IF(Q86="y",1,SUMIFS('Rating Grid'!$D$11:$D$34,'Rating Grid'!$B$11:$B$34,Original!$L$30:$L$172,'Rating Grid'!$C$11:$C$34,Original!$M$30:$M$172)) -> 3 | P86: Medium | Q86: N | R86: =IF(O86>S86,O86,S86) -> 3 | T86: 2020 | U86: NI | V86: =IF($T86+$R86<=2022,"2022","-") -> - | W86: =IF($T86+$R86=2023,"2023","-") -> 2023 | X86: =IF($T86+$R86=2024,"2024","-") -> - | Y86: =IF($T86+$R86=2025,"2025","-") -> - | AA86: =IF($T86>2018,"Y","N") -> Y | AB86: Look into IT Audit coverage????
A87: Original | B87: Operations | C87: Remittances (Non-Trade) | D87: Remittances (Non-Trade) | E87: Operations | F87: 551 | G87: COO | H87: Michael Power | I87: Juzer Netterwala | J87: Saeed | K87: Sangeetha Abraham | L87: Medium | M87: =IF(T87>2017,U87,"N/A") -> Sat | N87: Low | O87: =IF(Q87="y",1,SUMIFS('Rating Grid'!$D$11:$D$34,'Rating Grid'!$B$11:$B$34,Original!$L$30:$L$172,'Rating Grid'!$C$11:$C$34,Original!$M$30:$M$172)) -> 3 | P87: Medium | Q87: N | R87: =IF(O87>S87,O87,S87) -> 3 | S87: 3 | T87: 2021 | U87: Sat | V87: =IF($T87+$R87<=2022,"2022","-") -> - | W87: =IF($T87+$R87=2023,"2023","-") -> - | X87: =IF($T87+$R87=2024,"2024","-") -> 2024 | Y87: =IF($T87+$R87=2025,"2025","-") -> - | AA87: =IF($T87>2018,"Y","N") -> Y
A88: Original | B88: Operations | C88: Trade Finance - Operations & Acct Monitoring | D88: Trade Finance - Operations | E88: Operations | G88: COO | H88: Michael Power | I88: Juzer Netterwala | J88: Shalini Mehta | K88: Neil Jarman | L88: Medium | M88: =IF(T88>2017,U88,"N/A") -> N/A | N88: Medium | O88: =IF(Q88="y",1,SUMIFS('Rating Grid'!$D$11:$D$34,'Rating Grid'!$B$11:$B$34,Original!$L$30:$L$172,'Rating Grid'!$C$11:$C$34,Original!$M$30:$M$172)) -> 3 | P88: Medium | Q88: N | R88: =IF(O88>S88,O88,S88) -> 3 | T88: 2017 | U88: Sat | V88: =IF($T88+$R88<=2022,"2022","-") -> 2022 | W88: =IF($T88+$R88=2023,"2023","-") -> - | X88: =IF($T88+$R88=2024,"2024","-") -> - | Y88: =IF($T88+$R88=2025,"2025","-") -> - | Z88: Y | AA88: =IF($T88>2018,"Y","N") -> N | AB88: H2
A89: Original | B89: Operations | C89: WM - Operations & Acct Monitoring | D89: Wealth Management and Investments - Operations | E89: Operations | G89: COO | H89: Michael Power | I89: Juzer Netterwala | J89: Warren | K89: Sangeetha Abraham | L89: Medium | M89: =IF(T89>2017,U89,"N/A") -> Sat | N89: Low | O89: =IF(Q89="y",1,SUMIFS('Rating Grid'!$D$11:$D$34,'Rating Grid'!$B$11:$B$34,Original!$L$30:$L$172,'Rating Grid'!$C$11:$C$34,Original!$M$30:$M$172)) -> 3 | P89: Low | Q89: N | R89: =IF(O89>S89,O89,S89) -> 3 | T89: 2021 | U89: Sat | V89: =IF($T89+$R89<=2022,"2022","-") -> - | W89: =IF($T89+$R89=2023,"2023","-") -> - | X89: =IF($T89+$R89=2024,"2024","-") -> 2024 | Y89: =IF($T89+$R89=2025,"2025","-") -> - | AA89: =IF($T89>2018,"Y","N") -> Y
A90: Original | B90: Personal Banking | C90: Branch Controls | D90: Branch Controls & Distribution | E90: Personal Banking | F90: 578 | G90: MD Personal Banking | H90: Shehzad Hameed | I90: Naji Mohd. | K90: Sangeetha Abraham | L90: Low | M90: =IF(T90>2017,U90,"N/A") -> Sat | N90: Very Low | O90: =IF(Q90="y",1,SUMIFS('Rating Grid'!$D$11:$D$34,'Rating Grid'!$B$11:$B$34,Original!$L$30:$L$172,'Rating Grid'!$C$11:$C$34,Original!$M$30:$M$172)) -> 4 | P90: Low | Q90: N | R90: =IF(O90>S90,O90,S90) -> 4 | T90: 2020 | U90: Sat | V90: =IF($T90+$R90<=2022,"2022","-") -> - | W90: =IF($T90+$R90=2023,"2023","-") -> - | X90: =IF($T90+$R90=2024,"2024","-") -> 2024 | Y90: =IF($T90+$R90=2025,"2025","-") -> - | Z90: Y | AA90: =IF($T90>2018,"Y","N") -> Y | AB90: Embedded as part of on-going branch audits, however will be covered in 2022.
A91: Original | B91: Personal Banking | C91: Business Analytics | D91: Business Performance & Strategic Analytics | E91: Personal Banking | F91: 513 | G91: MD Personal Banking | H91: Shehzad Hameed | I91: HPB / Ramzi | K91: Sangeetha Abraham | L91: Medium | M91: =IF(T91>2017,U91,"N/A") -> Sat | N91: Low | O91: =IF(Q91="y",1,SUMIFS('Rating Grid'!$D$11:$D$34,'Rating Grid'!$B$11:$B$34,Original!$L$30:$L$172,'Rating Grid'!$C$11:$C$34,Original!$M$30:$M$172)) -> 3 | P91: Low | Q91: N | R91: =IF(O91>S91,O91,S91) -> 3 | T91: 2020 | U91: Sat | V91: =IF($T91+$R91<=2022,"2022","-") -> - | W91: =IF($T91+$R91=2023,"2023","-") -> 2023 | X91: =IF($T91+$R91=2024,"2024","-") -> - | Y91: =IF($T91+$R91=2025,"2025","-") -> - | AA91: =IF($T91>2018,"Y","N") -> Y
A92: Original | B92: Credit | C92: PBG - Collections | D92: PBG - Collections (All products) | E92: Credit | F92: 509 | G92: CCO | H92: Mahadevan Radhakanthan | I92: Khadija | K92: Sangeetha Abraham | L92: Medium | M92: =IF(T92>2017,U92,"N/A") -> NI | N92: Medium | O92: =IF(Q92="y",1,SUMIFS('Rating Grid'!$D$11:$D$34,'Rating Grid'!$B$11:$B$34,Original!$L$30:$L$172,'Rating Grid'!$C$11:$C$34,Original!$M$30:$M$172)) -> 3 | P92: Medium | Q92: N | R92: =IF(O92>S92,O92,S92) -> 3 | T92: 2019 | U92: NI | V92: =IF($T92+$R92<=2022,"2022","-") -> 2022 | W92: =IF($T92+$R92=2023,"2023","-") -> - | X92: =IF($T92+$R92=2024,"2024","-") -> - | Y92: =IF($T92+$R92=2025,"2025","-") -> - | Z92: Y | AA92: =IF($T92>2018,"Y","N") -> Y | AB92: CPF - Q2
A93: Original | B93: Personal Banking | C93: PBG - Assets | D93: Sales (All products) | E93: Personal Banking | F93: 513, 523, 550 | G93: MD Personal Banking | H93: Shehzad Hameed | K93: Sangeetha Abraham | L93: Medium | M93: =IF(T93>2017,U93,"N/A") -> Sat | N93: Low | O93: =IF(Q93="y",1,SUMIFS('Rating Grid'!$D$11:$D$34,'Rating Grid'!$B$11:$B$34,Original!$L$30:$L$172,'Rating Grid'!$C$11:$C$34,Original!$M$30:$M$172)) -> 3 | P93: Medium | Q93: N | R93: =IF(O93>S93,O93,S93) -> 3 | T93: 2021 | U93: Sat | V93: =IF($T93+$R93<=2022,"2022","-") -> - | W93: =IF($T93+$R93=2023,"2023","-") -> - | X93: =IF($T93+$R93=2024,"2024","-") -> 2024 | Y93: =IF($T93+$R93=2025,"2025","-") -> - | AA93: =IF($T93>2018,"Y","N") -> Y | AB93: Direct sales for credit card covered
A94: Original | B94: Personal Banking | C94: PBG - Assets | D94: Merchant Acquiring (Product & Sales) | E94: Personal Banking | F94: 174 | G94: MD Personal Banking | H94: Shehzad Hameed | I94: Elcin | K94: Sangeetha Abraham | L94: Medium | M94: =IF(T94>2017,U94,"N/A") -> NI | N94: Medium | O94: =IF(Q94="y",1,SUMIFS('Rating Grid'!$D$11:$D$34,'Rating Grid'!$B$11:$B$34,Original!$L$30:$L$172,'Rating Grid'!$C$11:$C$34,Original!$M$30:$M$172)) -> 3 | P94: Medium | Q94: N | R94: =IF(O94>S94,O94,S94) -> 3 | T94: 2020 | U94: NI | V94: =IF($T94+$R94<=2022,"2022","-") -> - | W94: =IF($T94+$R94=2023,"2023","-") -> 2023 | X94: =IF($T94+$R94=2024,"2024","-") -> - | Y94: =IF($T94+$R94=2025,"2025","-") -> - | Z94: Y | AA94: =IF($T94>2018,"Y","N") -> Y | AB94: Included in the CPF review no.2.
A95: Original | B95: Personal Banking | C95: PBG - Governance, Products & Service | D95: All Products | E95: Personal Banking | F95: 513, 523, 550 | G95: MD Personal Banking | H95: Shehzad Hameed | I95: Shibani / Shalab | K95: Sangeetha Abraham | L95: Medium | M95: =IF(T95>2017,U95,"N/A") -> Sat | N95: Medium | O95: =IF(Q95="y",1,SUMIFS('Rating Grid'!$D$11:$D$34,'Rating Grid'!$B$11:$B$34,Original!$L$30:$L$172,'Rating Grid'!$C$11:$C$34,Original!$M$30:$M$172)) -> 3 | P95: Medium | Q95: N | R95: =IF(O95>S95,O95,S95) -> 3 | T95: 2020 | U95: Sat | V95: =IF($T95+$R95<=2022,"2022","-") -> - | W95: =IF($T95+$R95=2023,"2023","-") -> 2023 | X95: =IF($T95+$R95=2024,"2024","-") -> - | Y95: =IF($T95+$R95=2025,"2025","-") -> - | Z95: Y | AA95: =IF($T95>2018,"Y","N") -> Y | AB95: CPF (LAI - WM)
A96: Original | B96: Personal Banking | C96: WM and Bancassurance - Sales | D96: WM and Bancassurance - Sales | E96: Personal Banking | F96: 159, 160, 163, 164, 534, 535, 536, 548 | G96: MD Personal Banking | H96: Shehzad Hameed | I96: Kieron Franklyn | K96: Sangeetha Abraham | L96: Medium | M96: =IF(T96>2017,U96,"N/A") -> Unrated | N96: Low | O96: =IF(Q96="y",1,SUMIFS('Rating Grid'!$D$11:$D$34,'Rating Grid'!$B$11:$B$34,Original!$L$30:$L$172,'Rating Grid'!$C$11:$C$34,Original!$M$30:$M$172)) -> 2 | P96: Medium | Q96: N | R96: =IF(O96>S96,O96,S96) -> 2 | T96: 2021 | U96: Unrated | V96: =IF($T96+$R96<=2022,"2022","-") -> - | W96: =IF($T96+$R96=2023,"2023","-") -> 2023 | X96: =IF($T96+$R96=2024,"2024","-") -> - | Y96: =IF($T96+$R96=2025,"2025","-") -> - | AA96: =IF($T96>2018,"Y","N") -> Y | AB96: WM and Bancassurance clubbed together.
A97: Original | B97: Personal Banking | C97: WM and Bancassurance - Governance, Products & Service | D97: Wealth Management & Investments - Products | E97: Personal Banking | F97: 548 | G97: MD Personal Banking | H97: Shehzad Hameed | I97: Gaurav Dixit | K97: Sangeetha Abraham | L97: Low | M97: =IF(T97>2017,U97,"N/A") -> Sat | N97: Very Low | O97: =IF(Q97="y",1,SUMIFS('Rating Grid'!$D$11:$D$34,'Rating Grid'!$B$11:$B$34,Original!$L$30:$L$172,'Rating Grid'!$C$11:$C$34,Original!$M$30:$M$172)) -> 4 | P97: Low | Q97: N | R97: =IF(O97>S97,O97,S97) -> 4 | T97: 2021 | U97: Sat | V97: =IF($T97+$R97<=2022,"2022","-") -> - | W97: =IF($T97+$R97=2023,"2023","-") -> - | X97: =IF($T97+$R97=2024,"2024","-") -> - | Y97: =IF($T97+$R97=2025,"2025","-") -> 2025 | AA97: =IF($T97>2018,"Y","N") -> Y
A98: Original | B98: RAKINSURANCE | C98: RAKNIC - Channels | D98: Branches | E98: RAKINSURANCE | G98: CEO RAKINSURANCE | H98: Ewen John Mcrobbie | I98: Jason Carey | K98: Neil Jarman | L98: Medium | M98: =IF(T98>2017,U98,"N/A") -> Unrated | N98: Medium | O98: =IF(Q98="y",1,SUMIFS('Rating Grid'!$D$11:$D$34,'Rating Grid'!$B$11:$B$34,Original!$L$30:$L$172,'Rating Grid'!$C$11:$C$34,Original!$M$30:$M$172)) -> 2 | P98: Medium | Q98: N | R98: =IF(O98>S98,O98,S98) -> 2 | T98: 2019 | U98: Unrated | V98: =IF($T98+$R98<=2022,"2022","-") -> 2022 | W98: =IF($T98+$R98=2023,"2023","-") -> - | X98: =IF($T98+$R98=2024,"2024","-") -> - | Y98: =IF($T98+$R98=2025,"2025","-") -> - | Z98: Y | AA98: =IF($T98>2018,"Y","N") -> Y
A99: Original | B99: RAKINSURANCE | C99: RAKNIC - Distribution | D99: Business Development - Distribution | E99: RAKINSURANCE | G99: CEO RAKINSURANCE | H99: Ewen John Mcrobbie | I99: Jason Carey | K99: Neil Jarman | L99: Medium | M99: =IF(T99>2017,U99,"N/A") -> NI | N99: Medium | O99: =IF(Q99="y",1,SUMIFS('Rating Grid'!$D$11:$D$34,'Rating Grid'!$B$11:$B$34,Original!$L$30:$L$172,'Rating Grid'!$C$11:$C$34,Original!$M$30:$M$172)) -> 3 | P99: Medium | Q99: N | R99: =IF(O99>S99,O99,S99) -> 3 | T99: 2020 | U99: NI | V99: =IF($T99+$R99<=2022,"2022","-") -> - | W99: =IF($T99+$R99=2023,"2023","-") -> 2023 | X99: =IF($T99+$R99=2024,"2024","-") -> - | Y99: =IF($T99+$R99=2025,"2025","-") -> - | Z99: Y | AA99: =IF($T99>2018,"Y","N") -> Y
A100: Original | B100: RAKINSURANCE | C100: RAKNIC - Corporate Governance | D100: CEO's Office - Governance, Strategy, Marketing & Product Development | E100: RAKINSURANCE | G100: CEO RAKINSURANCE | H100: Ewen John Mcrobbie | I100: Ewen John Mcrobbie | K100: Neil Jarman | L100: Medium | M100: =IF(T100>2017,U100,"N/A") -> NI | N100: Medium | O100: =IF(Q100="y",1,SUMIFS('Rating Grid'!$D$11:$D$34,'Rating Grid'!$B$11:$B$34,Original!$L$30:$L$172,'Rating Grid'!$C$11:$C$34,Original!$M$30:$M$172)) -> 3 | P100: Medium | Q100: N | R100: =IF(O100>S100,O100,S100) -> 3 | T100: 2020 | U100: NI | V100: =IF($T100+$R100<=2022,"2022","-") -> - | W100: =IF($T100+$R100=2023,"2023","-") -> 2023 | X100: =IF($T100+$R100=2024,"2024","-") -> - | Y100: =IF($T100+$R100=2025,"2025","-") -> - | AA100: =IF($T100>2018,"Y","N") -> Y
A101: Original | B101: RAKINSURANCE | C101: RAKNIC - Financial Control | D101: Finance - Credit control (receivables and collections) | E101: RAKINSURANCE | G101: CEO RAKINSURANCE | H101: Ewen John Mcrobbie | I101: Sherry | K101: Neil Jarman | L101: Medium | M101: =IF(T101>2017,U101,"N/A") -> Unsat | N101: Medium | O101: =IF(Q101="y",1,SUMIFS('Rating Grid'!$D$11:$D$34,'Rating Grid'!$B$11:$B$34,Original!$L$30:$L$172,'Rating Grid'!$C$11:$C$34,Original!$M$30:$M$172)) -> 2 | P101: Medium | Q101: N | R101: =IF(O101>S101,O101,S101) -> 2 | T101: 2020 | U101: Unsat | V101: =IF($T101+$R101<=2022,"2022","-") -> 2022 | W101: =IF($T101+$R101=2023,"2023","-") -> - | X101: =IF($T101+$R101=2024,"2024","-") -> - | Y101: =IF($T101+$R101=2025,"2025","-") -> - | AA101: =IF($T101>2018,"Y","N") -> Y
A102: Original | B102: RAKINSURANCE | C102: RAKNIC - Financial Control | D102: Finance - Finance reporting, fixed assets, cash receipts | E102: RAKINSURANCE | G102: CEO RAKINSURANCE | H102: Ewen John Mcrobbie | I102: Sherry | K102: Neil Jarman | L102: Medium | M102: =IF(T102>2017,U102,"N/A") -> Unrated | N102: Medium | O102: =IF(Q102="y",1,SUMIFS('Rating Grid'!$D$11:$D$34,'Rating Grid'!$B$11:$B$34,Original!$L$30:$L$172,'Rating Grid'!$C$11:$C$34,Original!$M$30:$M$172)) -> 2 | P102: Medium | Q102: N | R102: =IF(O102>S102,O102,S102) -> 2 | T102: 2020 | U102: Unrated | V102: =IF($T102+$R102<=2022,"2022","-") -> 2022 | W102: =IF($T102+$R102=2023,"2023","-") -> - | X102: =IF($T102+$R102=2024,"2024","-") -> - | Y102: =IF($T102+$R102=2025,"2025","-") -> - | AA102: =IF($T102>2018,"Y","N") -> Y
A103: Original | B103: RAKINSURANCE | C103: RAKNIC - Financial Control | D103: Finance - Procurement, payables and payments (including commission and reinsurance expenses) | E103: RAKINSURANCE | G103: CEO RAKINSURANCE | H103: Ewen John Mcrobbie | I103: Sherry | K103: Neil Jarman | L103: Medium | M103: =IF(T103>2017,U103,"N/A") -> Sat | N103: Medium | O103: =IF(Q103="y",1,SUMIFS('Rating Grid'!$D$11:$D$34,'Rating Grid'!$B$11:$B$34,Original!$L$30:$L$172,'Rating Grid'!$C$11:$C$34,Original!$M$30:$M$172)) -> 3 | P103: Medium | Q103: N | R103: =IF(O103>S103,O103,S103) -> 3 | T103: 2021 | U103: Sat | V103: =IF($T103+$R103<=2022,"2022","-") -> - | W103: =IF($T103+$R103=2023,"2023","-") -> - | X103: =IF($T103+$R103=2024,"2024","-") -> 2024 | Y103: =IF($T103+$R103=2025,"2025","-") -> - | AA103: =IF($T103>2018,"Y","N") -> Y
A104: Original | B104: RAKINSURANCE | C104: RAKNIC - Vendor & Third Party Mgt | D104: Finance - Reconciliation (broker, TPA, reinsurance, cash and bank) | E104: RAKINSURANCE | G104: CEO RAKINSURANCE | H104: Ewen John Mcrobbie | I104: Sherry | K104: Neil Jarman | L104: Medium | M104: =IF(T104>2017,U104,"N/A") -> Unrated | N104: Medium | O104: =IF(Q104="y",1,SUMIFS('Rating Grid'!$D$11:$D$34,'Rating Grid'!$B$11:$B$34,Original!$L$30:$L$172,'Rating Grid'!$C$11:$C$34,Original!$M$30:$M$172)) -> 2 | P104: Medium | Q104: N | R104: =IF(O104>S104,O104,S104) -> 2 | T104: 2020 | U104: Unrated | V104: =IF($T104+$R104<=2022,"2022","-") -> 2022 | W104: =IF($T104+$R104=2023,"2023","-") -> - | X104: =IF($T104+$R104=2024,"2024","-") -> - | Y104: =IF($T104+$R104=2025,"2025","-") -> - | Z104: Y | AA104: =IF($T104>2018,"Y","N") -> Y | AB104: Part of Distribution Channels
A105: Original | B105: RAKINSURANCE | C105: RAKNIC - Motor and General Insurance | D105: RAKNIC - Motor and General Insurance | E105: RAKINSURANCE | G105: CEO RAKINSURANCE | H105: Ewen John Mcrobbie | I105: Krishnan Raghunathan | K105: Neil Jarman | L105: Medium | M105: =IF(T105>2017,U105,"N/A") -> Sat | N105: Medium | O105: =IF(Q105="y",1,SUMIFS('Rating Grid'!$D$11:$D$34,'Rating Grid'!$B$11:$B$34,Original!$L$30:$L$172,'Rating Grid'!$C$11:$C$34,Original!$M$30:$M$172)) -> 3 | P105: Medium | Q105: N | R105: =IF(O105>S105,O105,S105) -> 3 | T105: 2021 | U105: Sat | V105: =IF($T105+$R105<=2022,"2022","-") -> - | W105: =IF($T105+$R105=2023,"2023","-") -> - | X105: =IF($T105+$R105=2024,"2024","-") -> 2024 | Y105: =IF($T105+$R105=2025,"2025","-") -> - | AA105: =IF($T105>2018,"Y","N") -> Y
...

Sheet Audit Universe -Audit Plan2 (2)
A1: Status | B1: Area | C1: Auditable Entity | D1: Auditable Sub - Entity | E1: Area | F1: SOL ID | G1: Accountable Exec. Role (N-1) | H1: Accountable Executive | I1: Business Owner (N-2) | J1: Business Owner (N-3) | K1: Audit Owner | L1: Inherent Risk | M1: Control Environment | N1: Calculated Residual Risk | O1: Original Audit Cycle | P1: Manually Adjusted Residual Risk | Q1: Regulatory | R1: Adjusted Audit Cycle | S1: Manual Override | T1: Last Audit Year | U1: Last Audit Rating | V1: Audit Plan 2022 | W1: Audit Plan 2023 | X1: Audit Plan 2024 | Y1: Audit Plan 2025 | Z1: In CY Audit Plan | AA1: Covered in Last 3 Years | AB1: Comments
A2: Master | B2: Retail Channels | C2: Branches | D2: All Branches | E2: Branches | G2: MD Business Banking | H2: Dhiraj Kunwar | I2: Saud (Naji) Mohd. | K2: Neil Jarman | L2: Medium | M2: NI | N2: Medium | O2: 1 | P2: Medium | Q2: Y | R2: =IF(O2>S2,O2,S2) -> 1 | T2: 2020 | U2: Sat | V2: =IF($T2+$R2<=2022,"2022","-") -> 2022 | W2: =IF($T2+$R2=2023,"2023","-") -> - | X2: =IF($T2+$R2=2024,"2024","-") -> - | Y2: =IF($T2+$R2=2025,"2025","-") -> - | AA2: =IF($T2>2018,"Y","N") -> Y
A3: Original | B3: Retail Channels | C3: Branches | D3: Ajman | E3: Branches | F3: 019 | G3: MD Business Banking | H3: Dhiraj Kunwar | I3: Saud (Naji) Mohd. | K3: Sangeetha Abraham | L3: Medium | M3: =IF(T3>2017,U3,"N/A") -> Sat | N3: Medium | O3: =IF(Q3="y",1,SUMIFS('Rating Grid'!$D$11:$D$34,'Rating Grid'!$B$11:$B$34,'Audit Universe -Audit Plan2 (2)'!$L$31:$L$173,'Rating Grid'!$C$11:$C$34,'Audit Universe -Audit Plan2 (2)'!$M$31:$M$173)) -> 0 | P3: Low | Q3: N | R3: =IF(O3>S3,O3,S3) -> 0 | T3: 2020 | U3: Sat | V3: =IF($T3+$R3<=2022,"2022","-") -> 2022 | W3: =IF($T3+$R3=2023,"2023","-") -> - | X3: =IF($T3+$R3=2024,"2024","-") -> - | Y3: =IF($T3+$R3=2025,"2025","-") -> - | AA3: =IF($T3>2018,"Y","N") -> Y
A4: Original | B4: Retail Channels | C4: Branches | D4: Al Ain | E4: Branches | F4: 014 | G4: MD Business Banking | H4: Dhiraj Kunwar | I4: Saud (Naji) Mohd. | K4: Sangeetha Abraham | L4: Medium | M4: =IF(T4>2017,U4,"N/A") -> NI | N4: Medium | O4: =IF(Q4="y",1,SUMIFS('Rating Grid'!$D$11:$D$34,'Rating Grid'!$B$11:$B$34,'Audit Universe -Audit Plan2 (2)'!$L$31:$L$173,'Rating Grid'!$C$11:$C$34,'Audit Universe -Audit Plan2 (2)'!$M$31:$M$173)) -> 0 | P4: Medium | Q4: N | R4: =IF(O4>S4,O4,S4) -> 0 | T4: 2021 | U4: NI | V4: =IF($T4+$R4<=2022,"2022","-") -> 2022 | W4: =IF($T4+$R4=2023,"2023","-") -> - | X4: =IF($T4+$R4=2024,"2024","-") -> - | Y4: =IF($T4+$R4=2025,"2025","-") -> - | AA4: =IF($T4>2018,"Y","N") -> Y
A5: Original | B5: Retail Channels | C5: Branches | D5: Al Dhait | E5: Branches | F5: 031 | G5: MD Business Banking | H5: Dhiraj Kunwar | I5: Saud (Naji) Mohd. | K5: Sangeetha Abraham | L5: Medium | M5: =IF(T5>2017,U5,"N/A") -> NI | N5: Low | O5: =IF(Q5="y",1,SUMIFS('Rating Grid'!$D$11:$D$34,'Rating Grid'!$B$11:$B$34,'Audit Universe -Audit Plan2 (2)'!$L$31:$L$173,'Rating Grid'!$C$11:$C$34,'Audit Universe -Audit Plan2 (2)'!$M$31:$M$173)) -> 0 | P5: Medium | Q5: N | R5: =IF(O5>S5,O5,S5) -> 0 | T5: 2021 | U5: NI | V5: =IF($T5+$R5<=2022,"2022","-") -> 2022 | W5: =IF($T5+$R5=2023,"2023","-") -> - | X5: =IF($T5+$R5=2024,"2024","-") -> - | Y5: =IF($T5+$R5=2025,"2025","-") -> - | AA5: =IF($T5>2018,"Y","N") -> Y
A6: Original | B6: Retail Channels | C6: Branches | D6: Al Hamra | E6: Branches | F6: 065 | G6: MD Business Banking | H6: Dhiraj Kunwar | I6: Saud (Naji) Mohd. | K6: Sangeetha Abraham | L6: Medium | M6: =IF(T6>2017,U6,"N/A") -> Sat | N6: Low | O6: =IF(Q6="y",1,SUMIFS('Rating Grid'!$D$11:$D$34,'Rating Grid'!$B$11:$B$34,'Audit Universe -Audit Plan2 (2)'!$L$31:$L$173,'Rating Grid'!$C$11:$C$34,'Audit Universe -Audit Plan2 (2)'!$M$31:$M$173)) -> 0 | P6: Low | Q6: N | R6: =IF(O6>S6,O6,S6) -> 0 | T6: 2019 | U6: Sat | V6: =IF($T6+$R6<=2022,"2022","-") -> 2022 | W6: =IF($T6+$R6=2023,"2023","-") -> - | X6: =IF($T6+$R6=2024,"2024","-") -> - | Y6: =IF($T6+$R6=2025,"2025","-") -> - | AA6: =IF($T6>2018,"Y","N") -> Y
A7: Original | B7: Retail Channels | C7: Branches | D7: Al Kharan | E7: Branches | F7: 008 | G7: MD Business Banking | H7: Dhiraj Kunwar | I7: Saud (Naji) Mohd. | K7: Sangeetha Abraham | L7: Medium | M7: =IF(T7>2017,U7,"N/A") -> NI | N7: Low | O7: =IF(Q7="y",1,SUMIFS('Rating Grid'!$D$11:$D$34,'Rating Grid'!$B$11:$B$34,'Audit Universe -Audit Plan2 (2)'!$L$31:$L$173,'Rating Grid'!$C$11:$C$34,'Audit Universe -Audit Plan2 (2)'!$M$31:$M$173)) -> 0 | P7: Medium | Q7: N | R7: =IF(O7>S7,O7,S7) -> 0 | T7: 2020 | U7: NI | V7: =IF($T7+$R7<=2022,"2022","-") -> 2022 | W7: =IF($T7+$R7=2023,"2023","-") -> - | X7: =IF($T7+$R7=2024,"2024","-") -> - | Y7: =IF($T7+$R7=2025,"2025","-") -> - | AA7: =IF($T7>2018,"Y","N") -> Y
A8: Original | B8: Retail Channels | C8: Branches | D8: Al Madinah | E8: Branches | F8: 005 | G8: MD Business Banking | H8: Dhiraj Kunwar | I8: Saud (Naji) Mohd. | K8: Sangeetha Abraham | L8: Medium | M8: =IF(T8>2017,U8,"N/A") -> NI | N8: Medium | O8: =IF(Q8="y",1,SUMIFS('Rating Grid'!$D$11:$D$34,'Rating Grid'!$B$11:$B$34,'Audit Universe -Audit Plan2 (2)'!$L$31:$L$173,'Rating Grid'!$C$11:$C$34,'Audit Universe -Audit Plan2 (2)'!$M$31:$M$173)) -> 0 | P8: Medium | Q8: N | R8: =IF(O8>S8,O8,S8) -> 0 | T8: 2020 | U8: NI | V8: =IF($T8+$R8<=2022,"2022","-") -> 2022 | W8: =IF($T8+$R8=2023,"2023","-") -> - | X8: =IF($T8+$R8=2024,"2024","-") -> - | Y8: =IF($T8+$R8=2025,"2025","-") -> - | Z8: Y | AA8: =IF($T8>2018,"Y","N") -> Y | AB8: Q1 2022 Branch Closed
A9: Original | B9: Retail Channels | C9: Branches | D9: Al Mannai | E9: Branches | F9: 016 | G9: MD Business Banking | H9: Dhiraj Kunwar | I9: Saud (Naji) Mohd. | K9: Sangeetha Abraham | L9: Medium | M9: =IF(T9>2017,U9,"N/A") -> NI | N9: Low | O9: =IF(Q9="y",1,SUMIFS('Rating Grid'!$D$11:$D$34,'Rating Grid'!$B$11:$B$34,'Audit Universe -Audit Plan2 (2)'!$L$31:$L$173,'Rating Grid'!$C$11:$C$34,'Audit Universe -Audit Plan2 (2)'!$M$31:$M$173)) -> 0 | P9: Medium | Q9: N | R9: =IF(O9>S9,O9,S9) -> 0 | T9: 2021 | U9: NI | V9: =IF($T9+$R9<=2022,"2022","-") -> 2022 | W9: =IF($T9+$R9=2023,"2023","-") -> - | X9: =IF($T9+$R9=2024,"2024","-") -> - | Y9: =IF($T9+$R9=2025,"2025","-") -> - | AA9: =IF($T9>2018,"Y","N") -> Y
A10: Original | B10: Retail Channels | C10: Branches | D10: Al Nakheel | E10: Branches | F10: 002 | G10: MD Business Banking | H10: Dhiraj Kunwar | I10: Saud (Naji) Mohd. | K10: Sangeetha Abraham | L10: Medium | M10: =IF(T10>2017,U10,"N/A") -> Sat | N10: Low | O10: =IF(Q10="y",1,SUMIFS('Rating Grid'!$D$11:$D$34,'Rating Grid'!$B$11:$B$34,'Audit Universe -Audit Plan2 (2)'!$L$31:$L$173,'Rating Grid'!$C$11:$C$34,'Audit Universe -Audit Plan2 (2)'!$M$31:$M$173)) -> 0 | P10: Low | Q10: N | R10: =IF(O10>S10,O10,S10) -> 0 | T10: 2019 | U10: Sat | V10: =IF($T10+$R10<=2022,"2022","-") -> 2022 | W10: =IF($T10+$R10=2023,"2023","-") -> - | X10: =IF($T10+$R10=2024,"2024","-") -> - | Y10: =IF($T10+$R10=2025,"2025","-") -> - | AA10: =IF($T10>2018,"Y","N") -> Y
A11: Original | B11: Retail Channels | C11: Branches | D11: Al Quoz | E11: Branches | F11: 035 | G11: MD Business Banking | H11: Dhiraj Kunwar | I11: Saud (Naji) Mohd. | K11: Sangeetha Abraham | L11: Medium | M11: =IF(T11>2017,U11,"N/A") -> Sat | N11: Low | O11: =IF(Q11="y",1,SUMIFS('Rating Grid'!$D$11:$D$34,'Rating Grid'!$B$11:$B$34,'Audit Universe -Audit Plan2 (2)'!$L$31:$L$173,'Rating Grid'!$C$11:$C$34,'Audit Universe -Audit Plan2 (2)'!$M$31:$M$173)) -> 0 | P11: Low | Q11: N | R11: =IF(O11>S11,O11,S11) -> 0 | T11: 2019 | U11: Sat | V11: =IF($T11+$R11<=2022,"2022","-") -> 2022 | W11: =IF($T11+$R11=2023,"2023","-") -> - | X11: =IF($T11+$R11=2024,"2024","-") -> - | Y11: =IF($T11+$R11=2025,"2025","-") -> - | AA11: =IF($T11>2018,"Y","N") -> Y
A12: Original | B12: Retail Channels | C12: Branches | D12: Al Qusais | E12: Branches | F12: 037 | G12: MD Business Banking | H12: Dhiraj Kunwar | I12: Saud (Naji) Mohd. | K12: Sangeetha Abraham | L12: Medium | M12: =IF(T12>2017,U12,"N/A") -> Sat | N12: Low | O12: =IF(Q12="y",1,SUMIFS('Rating Grid'!$D$11:$D$34,'Rating Grid'!$B$11:$B$34,'Audit Universe -Audit Plan2 (2)'!$L$31:$L$173,'Rating Grid'!$C$11:$C$34,'Audit Universe -Audit Plan2 (2)'!$M$31:$M$173)) -> 0 | P12: Low | Q12: N | R12: =IF(O12>S12,O12,S12) -> 0 | T12: 2020 | U12: Sat | V12: =IF($T12+$R12<=2022,"2022","-") -> 2022 | W12: =IF($T12+$R12=2023,"2023","-") -> - | X12: =IF($T12+$R12=2024,"2024","-") -> - | Y12: =IF($T12+$R12=2025,"2025","-") -> - | Z12: Y | AA12: =IF($T12>2018,"Y","N") -> Y | AB12: Q1 2022
A13: Original | B13: Retail Channels | C13: Branches | D13: Al Rams | E13: Branches | F13: 011 | G13: MD Business Banking | H13: Dhiraj Kunwar | I13: Saud (Naji) Mohd. | K13: Sangeetha Abraham | L13: Medium | M13: =IF(T13>2017,U13,"N/A") -> Sat | N13: Low | O13: =IF(Q13="y",1,SUMIFS('Rating Grid'!$D$11:$D$34,'Rating Grid'!$B$11:$B$34,'Audit Universe -Audit Plan2 (2)'!$L$31:$L$173,'Rating Grid'!$C$11:$C$34,'Audit Universe -Audit Plan2 (2)'!$M$31:$M$173)) -> 0 | P13: Low | Q13: N | R13: =IF(O13>S13,O13,S13) -> 0 | T13: 2019 | U13: Sat | V13: =IF($T13+$R13<=2022,"2022","-") -> 2022 | W13: =IF($T13+$R13=2023,"2023","-") -> - | X13: =IF($T13+$R13=2024,"2024","-") -> - | Y13: =IF($T13+$R13=2025,"2025","-") -> - | AA13: =IF($T13>2018,"Y","N") -> Y | AB13: Branch Closed
A14: Original | B14: Retail Channels | C14: Branches | D14: Al Rolla | E14: Branches | F14: 057 | G14: MD Business Banking | H14: Dhiraj Kunwar | I14: Saud (Naji) Mohd. | K14: Sangeetha Abraham | L14: Medium | M14: =IF(T14>2017,U14,"N/A") -> Sat | N14: Low | O14: =IF(Q14="y",1,SUMIFS('Rating Grid'!$D$11:$D$34,'Rating Grid'!$B$11:$B$34,'Audit Universe -Audit Plan2 (2)'!$L$31:$L$173,'Rating Grid'!$C$11:$C$34,'Audit Universe -Audit Plan2 (2)'!$M$31:$M$173)) -> 0 | P14: Low | Q14: N | R14: =IF(O14>S14,O14,S14) -> 0 | T14: 2020 | U14: Sat | V14: =IF($T14+$R14<=2022,"2022","-") -> 2022 | W14: =IF($T14+$R14=2023,"2023","-") -> - | X14: =IF($T14+$R14=2024,"2024","-") -> - | Y14: =IF($T14+$R14=2025,"2025","-") -> - | AA14: =IF($T14>2018,"Y","N") -> Y
A15: Original | B15: Retail Channels | C15: Branches | D15: Deira Maktoum Street | E15: Branches | F15: 003 | G15: MD Business Banking | H15: Dhiraj Kunwar | I15: Saud (Naji) Mohd. | K15: Sangeetha Abraham | L15: Medium | M15: =IF(T15>2017,U15,"N/A") -> Sat | N15: Low | O15: =IF(Q15="y",1,SUMIFS('Rating Grid'!$D$11:$D$34,'Rating Grid'!$B$11:$B$34,'Audit Universe -Audit Plan2 (2)'!$L$31:$L$173,'Rating Grid'!$C$11:$C$34,'Audit Universe -Audit Plan2 (2)'!$M$31:$M$173)) -> 0 | P15: Low | Q15: N | R15: =IF(O15>S15,O15,S15) -> 0 | T15: 2020 | U15: Sat | V15: =IF($T15+$R15<=2022,"2022","-") -> 2022 | W15: =IF($T15+$R15=2023,"2023","-") -> - | X15: =IF($T15+$R15=2024,"2024","-") -> - | Y15: =IF($T15+$R15=2025,"2025","-") -> - | AA15: =IF($T15>2018,"Y","N") -> Y
A16: Original | B16: Retail Channels | C16: Branches | D16: Deira Souq | E16: Branches | F16: 025 | G16: MD Business Banking | H16: Dhiraj Kunwar | I16: Saud (Naji) Mohd. | K16: Sangeetha Abraham | L16: Medium | M16: =IF(T16>2017,U16,"N/A") -> Sat | N16: Low | O16: =IF(Q16="y",1,SUMIFS('Rating Grid'!$D$11:$D$34,'Rating Grid'!$B$11:$B$34,'Audit Universe -Audit Plan2 (2)'!$L$31:$L$173,'Rating Grid'!$C$11:$C$34,'Audit Universe -Audit Plan2 (2)'!$M$31:$M$173)) -> 0 | P16: Low | Q16: N | R16: =IF(O16>S16,O16,S16) -> 0 | T16: 2021 | U16: Sat | V16: =IF($T16+$R16<=2022,"2022","-") -> 2022 | W16: =IF($T16+$R16=2023,"2023","-") -> - | X16: =IF($T16+$R16=2024,"2024","-") -> - | Y16: =IF($T16+$R16=2025,"2025","-") -> - | AA16: =IF($T16>2018,"Y","N") -> Y
A17: Original | B17: Retail Channels | C17: Branches | D17: Dragon Mart | E17: Branches | F17: 088 | G17: MD Business Banking | H17: Dhiraj Kunwar | I17: Saud (Naji) Mohd. | K17: Sangeetha Abraham | L17: Medium | M17: =IF(T17>2017,U17,"N/A") -> NI | N17: Medium | O17: =IF(Q17="y",1,SUMIFS('Rating Grid'!$D$11:$D$34,'Rating Grid'!$B$11:$B$34,'Audit Universe -Audit Plan2 (2)'!$L$31:$L$173,'Rating Grid'!$C$11:$C$34,'Audit Universe -Audit Plan2 (2)'!$M$31:$M$173)) -> 0 | P17: Medium | Q17: N | R17: =IF(O17>S17,O17,S17) -> 0 | T17: 2020 | U17: NI | V17: =IF($T17+$R17<=2022,"2022","-") -> 2022 | W17: =IF($T17+$R17=2023,"2023","-") -> - | X17: =IF($T17+$R17=2024,"2024","-") -> - | Y17: =IF($T17+$R17=2025,"2025","-") -> - | AA17: =IF($T17>2018,"Y","N") -> Y
A18: Original | B18: Retail Channels | C18: Branches | D18: Emaar Business Park | E18: Branches | F18: 032 | G18: MD Business Banking | H18: Dhiraj Kunwar | I18: Saud (Naji) Mohd. | K18: Sangeetha Abraham | L18: Medium | M18: =IF(T18>2017,U18,"N/A") -> Sat | N18: Low | O18: =IF(Q18="y",1,SUMIFS('Rating Grid'!$D$11:$D$34,'Rating Grid'!$B$11:$B$34,'Audit Universe -Audit Plan2 (2)'!$L$31:$L$173,'Rating Grid'!$C$11:$C$34,'Audit Universe -Audit Plan2 (2)'!$M$31:$M$173)) -> 0 | P18: Low | Q18: N | R18: =IF(O18>S18,O18,S18) -> 0 | T18: 2020 | U18: Sat | V18: =IF($T18+$R18<=2022,"2022","-") -> 2022 | W18: =IF($T18+$R18=2023,"2023","-") -> - | X18: =IF($T18+$R18=2024,"2024","-") -> - | Y18: =IF($T18+$R18=2025,"2025","-") -> - | AA18: =IF($T18>2018,"Y","N") -> Y
A19: Original | B19: Retail Channels | C19: Branches | D19: Fujairah | E19: Branches | F19: 058 | G19: MD Business Banking | H19: Dhiraj Kunwar | I19: Saud (Naji) Mohd. | K19: Sangeetha Abraham | L19: Medium | M19: =IF(T19>2017,U19,"N/A") -> NI | N19: Low | O19: =IF(Q19="y",1,SUMIFS('Rating Grid'!$D$11:$D$34,'Rating Grid'!$B$11:$B$34,'Audit Universe -Audit Plan2 (2)'!$L$31:$L$173,'Rating Grid'!$C$11:$C$34,'Audit Universe -Audit Plan2 (2)'!$M$31:$M$173)) -> 0 | P19: Medium | Q19: N | R19: =IF(O19>S19,O19,S19) -> 0 | T19: 2019 | U19: NI | V19: =IF($T19+$R19<=2022,"2022","-") -> 2022 | W19: =IF($T19+$R19=2023,"2023","-") -> - | X19: =IF($T19+$R19=2024,"2024","-") -> - | Y19: =IF($T19+$R19=2025,"2025","-") -> - | AA19: =IF($T19>2018,"Y","N") -> Y
A20: Original | B20: Retail Channels | C20: Branches | D20: Ibn Battuta Mall | E20: Branches | F20: 029 | G20: MD Business Banking | H20: Dhiraj Kunwar | I20: Saud (Naji) Mohd. | K20: Sangeetha Abraham | L20: Medium | M20: =IF(T20>2017,U20,"N/A") -> NI | N20: Low | O20: =IF(Q20="y",1,SUMIFS('Rating Grid'!$D$11:$D$34,'Rating Grid'!$B$11:$B$34,'Audit Universe -Audit Plan2 (2)'!$L$31:$L$173,'Rating Grid'!$C$11:$C$34,'Audit Universe -Audit Plan2 (2)'!$M$31:$M$173)) -> 0 | P20: Medium | Q20: N | R20: =IF(O20>S20,O20,S20) -> 0 | T20: 2019 | U20: NI | V20: =IF($T20+$R20<=2022,"2022","-") -> 2022 | W20: =IF($T20+$R20=2023,"2023","-") -> - | X20: =IF($T20+$R20=2024,"2024","-") -> - | Y20: =IF($T20+$R20=2025,"2025","-") -> - | AA20: =IF($T20>2018,"Y","N") -> Y | AB20: Branch Closed
A21: Original | B21: Retail Channels | C21: Branches | D21: Kalba | E21: Branches | F21: 007 | G21: MD Business Banking | H21: Dhiraj Kunwar | I21: Saud (Naji) Mohd. | K21: Sangeetha Abraham | L21: Medium | M21: =IF(T21>2017,U21,"N/A") -> NI | N21: Low | O21: =IF(Q21="y",1,SUMIFS('Rating Grid'!$D$11:$D$34,'Rating Grid'!$B$11:$B$34,'Audit Universe -Audit Plan2 (2)'!$L$31:$L$173,'Rating Grid'!$C$11:$C$34,'Audit Universe -Audit Plan2 (2)'!$M$31:$M$173)) -> 0 | P21: Medium | Q21: N | R21: =IF(O21>S21,O21,S21) -> 0 | T21: 2021 | U21: NI | V21: =IF($T21+$R21<=2022,"2022","-") -> 2022 | W21: =IF($T21+$R21=2023,"2023","-") -> - | X21: =IF($T21+$R21=2024,"2024","-") -> - | Y21: =IF($T21+$R21=2025,"2025","-") -> - | AA21: =IF($T21>2018,"Y","N") -> Y | AB21: Branch Closed
A22: Original | B22: Retail Channels | C22: Branches | D22: Khalidiya | E22: Branches | F22: 030 | G22: MD Business Banking | H22: Dhiraj Kunwar | I22: Saud (Naji) Mohd. | K22: Sangeetha Abraham | L22: Medium | M22: =IF(T22>2017,U22,"N/A") -> NI | N22: Low | O22: =IF(Q22="y",1,SUMIFS('Rating Grid'!$D$11:$D$34,'Rating Grid'!$B$11:$B$34,'Audit Universe -Audit Plan2 (2)'!$L$31:$L$173,'Rating Grid'!$C$11:$C$34,'Audit Universe -Audit Plan2 (2)'!$M$31:$M$173)) -> 0 | P22: Medium | Q22: N | R22: =IF(O22>S22,O22,S22) -> 0 | T22: 2021 | U22: NI | V22: =IF($T22+$R22<=2022,"2022","-") -> 2022 | W22: =IF($T22+$R22=2023,"2023","-") -> - | X22: =IF($T22+$R22=2024,"2024","-") -> - | Y22: =IF($T22+$R22=2025,"2025","-") -> - | AA22: =IF($T22>2018,"Y","N") -> Y
A23: Original | B23: Retail Channels | C23: Branches | D23: King Faisal Street | E23: Branches | F23: 024 | G23: MD Business Banking | H23: Dhiraj Kunwar | I23: Saud (Naji) Mohd. | K23: Sangeetha Abraham | L23: Medium | M23: =IF(T23>2017,U23,"N/A") -> Sat | N23: Low | O23: =IF(Q23="y",1,SUMIFS('Rating Grid'!$D$11:$D$34,'Rating Grid'!$B$11:$B$34,'Audit Universe -Audit Plan2 (2)'!$L$31:$L$173,'Rating Grid'!$C$11:$C$34,'Audit Universe -Audit Plan2 (2)'!$M$31:$M$173)) -> 0 | P23: Low | Q23: N | R23: =IF(O23>S23,O23,S23) -> 0 | T23: 2019 | U23: Sat | V23: =IF($T23+$R23<=2022,"2022","-") -> 2022 | W23: =IF($T23+$R23=2023,"2023","-") -> - | X23: =IF($T23+$R23=2024,"2024","-") -> - | Y23: =IF($T23+$R23=2025,"2025","-") -> - | AA23: =IF($T23>2018,"Y","N") -> Y
A24: Original | B24: Retail Channels | C24: Branches | D24: Motor City | E24: Branches | F24: 033 | G24: MD Business Banking | H24: Dhiraj Kunwar | I24: Saud (Naji) Mohd. | K24: Sangeetha Abraham | L24: Medium | M24: =IF(T24>2017,U24,"N/A") -> Sat | N24: Low | O24: =IF(Q24="y",1,SUMIFS('Rating Grid'!$D$11:$D$34,'Rating Grid'!$B$11:$B$34,'Audit Universe -Audit Plan2 (2)'!$L$31:$L$173,'Rating Grid'!$C$11:$C$34,'Audit Universe -Audit Plan2 (2)'!$M$31:$M$173)) -> 0 | P24: Low | Q24: N | R24: =IF(O24>S24,O24,S24) -> 0 | T24: 2021 | U24: Sat | V24: =IF($T24+$R24<=2022,"2022","-") -> 2022 | W24: =IF($T24+$R24=2023,"2023","-") -> - | X24: =IF($T24+$R24=2024,"2024","-") -> - | Y24: =IF($T24+$R24=2025,"2025","-") -> - | AA24: =IF($T24>2018,"Y","N") -> Y
A25: Original | B25: Retail Channels | C25: Branches | D25: Mussafah | E25: Branches | F25: 039 | G25: MD Business Banking | H25: Dhiraj Kunwar | I25: Saud (Naji) Mohd. | K25: Sangeetha Abraham | L25: Medium | M25: =IF(T25>2017,U25,"N/A") -> NI | N25: Low | O25: =IF(Q25="y",1,SUMIFS('Rating Grid'!$D$11:$D$34,'Rating Grid'!$B$11:$B$34,'Audit Universe -Audit Plan2 (2)'!$L$31:$L$173,'Rating Grid'!$C$11:$C$34,'Audit Universe -Audit Plan2 (2)'!$M$31:$M$173)) -> 0 | P25: Medium | Q25: N | R25: =IF(O25>S25,O25,S25) -> 0 | T25: 2021 | U25: NI | V25: =IF($T25+$R25<=2022,"2022","-") -> 2022 | W25: =IF($T25+$R25=2023,"2023","-") -> - | X25: =IF($T25+$R25=2024,"2024","-") -> - | Y25: =IF($T25+$R25=2025,"2025","-") -> - | AA25: =IF($T25>2018,"Y","N") -> Y
A26: Original | B26: Retail Channels | C26: Branches | D26: Oud Metha | E26: Branches | F26: 018 | G26: MD Business Banking | H26: Dhiraj Kunwar | I26: Saud (Naji) Mohd. | K26: Sangeetha Abraham | L26: Medium | M26: =IF(T26>2017,U26,"N/A") -> Sat | N26: Low | O26: =IF(Q26="y",1,SUMIFS('Rating Grid'!$D$11:$D$34,'Rating Grid'!$B$11:$B$34,'Audit Universe -Audit Plan2 (2)'!$L$31:$L$173,'Rating Grid'!$C$11:$C$34,'Audit Universe -Audit Plan2 (2)'!$M$31:$M$173)) -> 0 | P26: Low | Q26: N | R26: =IF(O26>S26,O26,S26) -> 0 | T26: 2021 | U26: Sat | V26: =IF($T26+$R26<=2022,"2022","-") -> 2022 | W26: =IF($T26+$R26=2023,"2023","-") -> - | X26: =IF($T26+$R26=2024,"2024","-") -> - | Y26: =IF($T26+$R26=2025,"2025","-") -> - | AA26: =IF($T26>2018,"Y","N") -> Y | AB26: Branch Closed
A27: Original | B27: Retail Channels | C27: Branches | D27: Shaam | E27: Branches | F27: 006 | G27: MD Business Banking | H27: Dhiraj Kunwar | I27: Saud (Naji) Mohd. | K27: Sangeetha Abraham | L27: Medium | M27: =IF(T27>2017,U27,"N/A") -> Sat | N27: Low | O27: =IF(Q27="y",1,SUMIFS('Rating Grid'!$D$11:$D$34,'Rating Grid'!$B$11:$B$34,'Audit Universe -Audit Plan2 (2)'!$L$31:$L$173,'Rating Grid'!$C$11:$C$34,'Audit Universe -Audit Plan2 (2)'!$M$31:$M$173)) -> 0 | P27: Low | Q27: N | R27: =IF(O27>S27,O27,S27) -> 0 | T27: 2019 | U27: Sat | V27: =IF($T27+$R27<=2022,"2022","-") -> 2022 | W27: =IF($T27+$R27=2023,"2023","-") -> - | X27: =IF($T27+$R27=2024,"2024","-") -> - | Y27: =IF($T27+$R27=2025,"2025","-") -> - | AA27: =IF($T27>2018,"Y","N") -> Y
A28: Original | B28: Retail Channels | C28: Branches | D28: Shaikh Zayed Road | E28: Branches | F28: 012 | G28: MD Business Banking | H28: Dhiraj Kunwar | I28: Saud (Naji) Mohd. | K28: Sangeetha Abraham | L28: Medium | M28: =IF(T28>2017,U28,"N/A") -> Sat | N28: Low | O28: =IF(Q28="y",1,SUMIFS('Rating Grid'!$D$11:$D$34,'Rating Grid'!$B$11:$B$34,'Audit Universe -Audit Plan2 (2)'!$L$31:$L$173,'Rating Grid'!$C$11:$C$34,'Audit Universe -Audit Plan2 (2)'!$M$31:$M$173)) -> 0 | P28: Low | Q28: N | R28: =IF(O28>S28,O28,S28) -> 0 | T28: 2019 | U28: Sat | V28: =IF($T28+$R28<=2022,"2022","-") -> 2022 | W28: =IF($T28+$R28=2023,"2023","-") -> - | X28: =IF($T28+$R28=2024,"2024","-") -> - | Y28: =IF($T28+$R28=2025,"2025","-") -> - | AA28: =IF($T28>2018,"Y","N") -> Y | AB28: Branch Closed
A29: Original | B29: Retail Channels | C29: Branches | D29: Tourist Club | E29: Branches | F29: 004 | G29: MD Business Banking | H29: Dhiraj Kunwar | I29: Saud (Naji) Mohd. | K29: Sangeetha Abraham | L29: Medium | M29: =IF(T29>2017,U29,"N/A") -> NI | N29: Low | O29: =IF(Q29="y",1,SUMIFS('Rating Grid'!$D$11:$D$34,'Rating Grid'!$B$11:$B$34,'Audit Universe -Audit Plan2 (2)'!$L$31:$L$173,'Rating Grid'!$C$11:$C$34,'Audit Universe -Audit Plan2 (2)'!$M$31:$M$173)) -> 0 | P29: Medium | Q29: N | R29: =IF(O29>S29,O29,S29) -> 0 | T29: 2021 | U29: NI | V29: =IF($T29+$R29<=2022,"2022","-") -> 2022 | W29: =IF($T29+$R29=2023,"2023","-") -> - | X29: =IF($T29+$R29=2024,"2024","-") -> - | Y29: =IF($T29+$R29=2025,"2025","-") -> - | AA29: =IF($T29>2018,"Y","N") -> Y | AB29: Branch Closed
A30: Original | B30: Retail Channels | C30: Branches | D30: Umm Hurair | E30: Branches | F30: 033 | G30: MD Business Banking | H30: Dhiraj Kunwar | I30: Saud (Naji) Mohd. | K30: Sangeetha Abraham | L30: Medium | M30: =IF(T30>2017,U30,"N/A") -> Sat | N30: Medium | O30: =IF(Q30="y",1,SUMIFS('Rating Grid'!$D$11:$D$34,'Rating Grid'!$B$11:$B$34,'Audit Universe -Audit Plan2 (2)'!$L$31:$L$173,'Rating Grid'!$C$11:$C$34,'Audit Universe -Audit Plan2 (2)'!$M$31:$M$173)) -> 0 | P30: Low | Q30: N | R30: =IF(O30>S30,O30,S30) -> 0 | T30: 2021 | U30: Sat | V30: =IF($T30+$R30<=2022,"2022","-") -> 2022 | W30: =IF($T30+$R30=2023,"2023","-") -> - | X30: =IF($T30+$R30=2024,"2024","-") -> - | Y30: =IF($T30+$R30=2025,"2025","-") -> - | AA30: =IF($T30>2018,"Y","N") -> Y
A31: Original | B31: Business Banking | C31: BBG - Liabilities | D31: BBG - Liabilities | E31: Business Banking | G31: MD Business Banking | H31: Dhiraj Kunwar | I31: Sulaiman Awan | K31: Neil Jarman | L31: Medium | M31: =IF(T31>2017,U31,"N/A") -> NI | N31: Medium | O31: =IF(Q31="y",1,SUMIFS('Rating Grid'!$D$11:$D$34,'Rating Grid'!$B$11:$B$34,'Audit Universe -Audit Plan2 (2)'!$L$31:$L$173,'Rating Grid'!$C$11:$C$34,'Audit Universe -Audit Plan2 (2)'!$M$31:$M$173)) -> 3 | P31: Medium | Q31: N | R31: =IF(O31>S31,O31,S31) -> 3 | T31: 2020 | U31: NI | V31: =IF($T31+$R31<=2022,"2022","-") -> - | W31: =IF($T31+$R31=2023,"2023","-") -> 2023 | X31: =IF($T31+$R31=2024,"2024","-") -> - | Y31: =IF($T31+$R31=2025,"2025","-") -> - | AA31: =IF($T31>2018,"Y","N") -> Y
A32: Original | B32: Business Banking | C32: BBG - National & Commercial Segment | D32: BBG - National & Commercial Segment | E32: Business Banking | G32: MD Business Banking | H32: Dhiraj Kunwar | I32: Emad Ahmed | K32: Neil Jarman | L32: Medium | M32: N/A | N32: Medium | O32: =IF(Q32="y",1,SUMIFS('Rating Grid'!$D$11:$D$34,'Rating Grid'!$B$11:$B$34,'Audit Universe -Audit Plan2 (2)'!$L$31:$L$173,'Rating Grid'!$C$11:$C$34,'Audit Universe -Audit Plan2 (2)'!$M$31:$M$173)) -> 3 | P32: Medium | Q32: N | R32: =IF(O32>S32,O32,S32) -> 3 | T32: 2021 | U32: Sat | V32: =IF($T32+$R32<=2022,"2022","-") -> - | W32: =IF($T32+$R32=2023,"2023","-") -> - | X32: =IF($T32+$R32=2024,"2024","-") -> 2024 | Y32: =IF($T32+$R32=2025,"2025","-") -> - | AA32: =IF($T32>2018,"Y","N") -> Y | AB32: Commercial Audit to be deferred on a prioritisation
A33: Original | B33: Corporate Functions | C33: Corporate Governance | D33: CEO's Office (Management Committees, Oversight, Strategy, Corp Communication) | E33: Corporate Functions | F33: 702 | G33: CEO | H33: Raheel Ahmed | I33: Amel B | K33: Moez Sassi | L33: Medium | M33: =IF(T33>2017,U33,"N/A") -> Sat | N33: Medium | O33: =IF(Q33="y",1,SUMIFS('Rating Grid'!$D$11:$D$34,'Rating Grid'!$B$11:$B$34,'Audit Universe -Audit Plan2 (2)'!$L$31:$L$173,'Rating Grid'!$C$11:$C$34,'Audit Universe -Audit Plan2 (2)'!$M$31:$M$173)) -> 3 | P33: Medium | Q33: N | R33: =IF(O33>S33,O33,S33) -> 3 | T33: 2018 | U33: Sat | V33: =IF($T33+$R33<=2022,"2022","-") -> 2022 | W33: =IF($T33+$R33=2023,"2023","-") -> - | X33: =IF($T33+$R33=2024,"2024","-") -> - | Y33: =IF($T33+$R33=2025,"2025","-") -> - | Z33: Y | AA33: =IF($T33>2018,"Y","N") -> N | AB33: Action plan till 2022, strategy due for revision
A34: Original | B34: Corporate Functions | C34: Corporate Governance | D34: Company Secretary (Governance, Board and Board Committees) | E34: Corporate Functions | G34: Chief Legal Officer | H34: Ghalia Bushnaq | I34: Imad Khalil | K34: Moez Sassi | L34: Medium | M34: =IF(T34>2017,U34,"N/A") -> Sat | N34: Medium | O34: =IF(Q34="y",1,SUMIFS('Rating Grid'!$D$11:$D$34,'Rating Grid'!$B$11:$B$34,'Audit Universe -Audit Plan2 (2)'!$L$31:$L$173,'Rating Grid'!$C$11:$C$34,'Audit Universe -Audit Plan2 (2)'!$M$31:$M$173)) -> 3 | P34: Medium | Q34: N | R34: =IF(O34>S34,O34,S34) -> 3 | T34: 2018 | U34: Sat | V34: =IF($T34+$R34<=2022,"2022","-") -> 2022 | W34: =IF($T34+$R34=2023,"2023","-") -> - | X34: =IF($T34+$R34=2024,"2024","-") -> - | Y34: =IF($T34+$R34=2025,"2025","-") -> -
A35: Original | B35: Corporate Functions | C35: Strategic Planning & Initiatives | D35: Strategy | E35: Corporate Functions | F35: 702 | G35: Chief Customer Officer | H35: Dongjun Choi | I35: Gregory Thomas | K35: Moez Sassi | L35: Medium | M35: =IF(T35>2017,U35,"N/A") -> Unrated | N35: High | O35: =IF(Q35="y",1,SUMIFS('Rating Grid'!$D$11:$D$34,'Rating Grid'!$B$11:$B$34,'Audit Universe -Audit Plan2 (2)'!$L$31:$L$173,'Rating Grid'!$C$11:$C$34,'Audit Universe -Audit Plan2 (2)'!$M$31:$M$173)) -> 2 | P35: High | Q35: N | R35: =IF(O35>S35,O35,S35) -> 2 | T35: 2020 | U35: Unrated | V35: =IF($T35+$R35<=2022,"2022","-") -> 2022 | W35: =IF($T35+$R35=2023,"2023","-") -> - | X35: =IF($T35+$R35=2024,"2024","-") -> - | Y35: =IF($T35+$R35=2025,"2025","-") -> - | Z35: Y | AA35: =IF($T35>2018,"Y","N") -> Y
A36: Original | B36: Corporate Functions | C36: Investor Relations & Corp Comms | D36: Corporate Communications | E36: Corporate Functions | F36: 702 | G36: Chief Legal Officer | H36: Ghalia Bushnaq | I36: Imad Khalil | K36: Moez Sassi | L36: Low | M36: =IF(T36>2017,U36,"N/A") -> N/A | N36: Medium | O36: =IF(Q36="y",1,SUMIFS('Rating Grid'!$D$11:$D$34,'Rating Grid'!$B$11:$B$34,'Audit Universe -Audit Plan2 (2)'!$L$31:$L$173,'Rating Grid'!$C$11:$C$34,'Audit Universe -Audit Plan2 (2)'!$M$31:$M$173)) -> 4 | P36: Low | Q36: N | R36: =IF(O36>S36,O36,S36) -> 4 | U36: - | V36: =IF($T36+$R36<=2022,"2022","-") -> 2022 | W36: =IF($T36+$R36=2023,"2023","-") -> - | X36: =IF($T36+$R36=2024,"2024","-") -> - | Y36: =IF($T36+$R36=2025,"2025","-") -> -
A37: Original | B37: Corporate Functions | C37: HR | D37: Human Resources (Emiratisation & BRF Reporting) | E37: Corporate Functions | F37: 522, 703, 715 | G37: CHRO | H37: Ahmed Yousef | I37: Ahmed / Manal Ali | K37: Sangeetha Abraham | L37: Medium | M37: =IF(T37>2017,U37,"N/A") -> Sat | N37: Low | O37: =IF(Q37="y",1,SUMIFS('Rating Grid'!$D$11:$D$34,'Rating Grid'!$B$11:$B$34,'Audit Universe -Audit Plan2 (2)'!$L$31:$L$173,'Rating Grid'!$C$11:$C$34,'Audit Universe -Audit Plan2 (2)'!$M$31:$M$173)) -> 3 | P37: Medium | Q37: N | R37: =IF(O37>S37,O37,S37) -> 3 | T37: 2021 | U37: Sat | V37: =IF($T37+$R37<=2022,"2022","-") -> - | W37: =IF($T37+$R37=2023,"2023","-") -> - | X37: =IF($T37+$R37=2024,"2024","-") -> 2024 | Y37: =IF($T37+$R37=2025,"2025","-") -> - | AA37: =IF($T37>2018,"Y","N") -> Y | AB37: Emiratisation and BRF covered in 2019. The rating is changed from NI to SAT
A38: Original | B38: Corporate Functions | C38: HR | D38: Human Resources (Learning & Development) | E38: Corporate Functions | G38: CHRO | H38: Ahmed Yousef | I38: Ahmed / Sultan | K38: Sangeetha Abraham | L38: Medium | M38: =IF(T38>2017,U38,"N/A") -> N/A | N38: Low | O38: =IF(Q38="y",1,SUMIFS('Rating Grid'!$D$11:$D$34,'Rating Grid'!$B$11:$B$34,'Audit Universe -Audit Plan2 (2)'!$L$31:$L$173,'Rating Grid'!$C$11:$C$34,'Audit Universe -Audit Plan2 (2)'!$M$31:$M$173)) -> 3 | P38: Medium | Q38: N | R38: =IF(O38>S38,O38,S38) -> 3 | T38: 2015 | U38: Sat | V38: =IF($T38+$R38<=2022,"2022","-") -> 2022 | W38: =IF($T38+$R38=2023,"2023","-") -> - | X38: =IF($T38+$R38=2024,"2024","-") -> - | Y38: =IF($T38+$R38=2025,"2025","-") -> - | AA38: =IF($T38>2018,"Y","N") -> N
A39: Original | B39: Corporate Functions | C39: HR | D39: Human Resources (Organisational Effectiveness & Business Partnership) | E39: Corporate Functions | F39: 522, 703, 715 | G39: CHRO | H39: Ahmed Yousef | I39: Ahmed / Rajive Nair | K39: Sangeetha Abraham | L39: Medium | M39: =IF(T39>2017,U39,"N/A") -> NI | N39: Low | O39: =IF(Q39="y",1,SUMIFS('Rating Grid'!$D$11:$D$34,'Rating Grid'!$B$11:$B$34,'Audit Universe -Audit Plan2 (2)'!$L$31:$L$173,'Rating Grid'!$C$11:$C$34,'Audit Universe -Audit Plan2 (2)'!$M$31:$M$173)) -> 3 | P39: Medium | Q39: N | R39: =IF(O39>S39,O39,S39) -> 3 | T39: 2021 | U39: NI | V39: =IF($T39+$R39<=2022,"2022","-") -> - | W39: =IF($T39+$R39=2023,"2023","-") -> - | X39: =IF($T39+$R39=2024,"2024","-") -> 2024 | Y39: =IF($T39+$R39=2025,"2025","-") -> - | AA39: =IF($T39>2018,"Y","N") -> Y
A40: Original | B40: Corporate Functions | C40: HR | D40: Human Resources (Reward Strategy, Remuneration, Incentives) | E40: Corporate Functions | F40: 522, 703, 715 | G40: CHRO | H40: Ahmed Yousef | I40: Ahmed / Pooja | K40: Sangeetha Abraham | L40: Medium | M40: =IF(T40>2017,U40,"N/A") -> NI | N40: Low | O40: =IF(Q40="y",1,SUMIFS('Rating Grid'!$D$11:$D$34,'Rating Grid'!$B$11:$B$34,'Audit Universe -Audit Plan2 (2)'!$L$31:$L$173,'Rating Grid'!$C$11:$C$34,'Audit Universe -Audit Plan2 (2)'!$M$31:$M$173)) -> 3 | P40: Medium | Q40: N | R40: =IF(O40>S40,O40,S40) -> 3 | T40: 2021 | U40: NI | V40: =IF($T40+$R40<=2022,"2022","-") -> - | W40: =IF($T40+$R40=2023,"2023","-") -> - | X40: =IF($T40+$R40=2024,"2024","-") -> 2024 | Y40: =IF($T40+$R40=2025,"2025","-") -> - | AA40: =IF($T40>2018,"Y","N") -> Y
A41: Original | B41: Corporate Functions | C41: HR | D41: Human Resources (Talent Acquisition & HR Services) | E41: Corporate Functions | F41: 522, 703, 715 | G41: CHRO | H41: Ahmed Yousef | I41: Ahmed / Rajive | K41: Sangeetha Abraham | L41: Medium | M41: =IF(T41>2017,U41,"N/A") -> NI | N41: Low | O41: =IF(Q41="y",1,SUMIFS('Rating Grid'!$D$11:$D$34,'Rating Grid'!$B$11:$B$34,'Audit Universe -Audit Plan2 (2)'!$L$31:$L$173,'Rating Grid'!$C$11:$C$34,'Audit Universe -Audit Plan2 (2)'!$M$31:$M$173)) -> 3 | P41: Medium | Q41: N | R41: =IF(O41>S41,O41,S41) -> 3 | T41: 2021 | U41: NI | V41: =IF($T41+$R41<=2022,"2022","-") -> - | W41: =IF($T41+$R41=2023,"2023","-") -> - | X41: =IF($T41+$R41=2024,"2024","-") -> 2024 | Y41: =IF($T41+$R41=2025,"2025","-") -> - | AA41: =IF($T41>2018,"Y","N") -> Y
A42: Original | B42: Corporate Functions | C42: Legal | D42: Legal - Advisory | E42: Corporate Functions | F42: 736 | G42: Chief Legal Officer | H42: Ghalia Bushnaq | I42: Raunaq Baid | K42: Moez Sassi | L42: Medium | M42: =IF(T42>2017,U42,"N/A") -> Sat | N42: Medium | O42: =IF(Q42="y",1,SUMIFS('Rating Grid'!$D$11:$D$34,'Rating Grid'!$B$11:$B$34,'Audit Universe -Audit Plan2 (2)'!$L$31:$L$173,'Rating Grid'!$C$11:$C$34,'Audit Universe -Audit Plan2 (2)'!$M$31:$M$173)) -> 3 | P42: Medium | Q42: N | R42: =IF(O42>S42,O42,S42) -> 3 | T42: 2021 | U42: Sat | V42: =IF($T42+$R42<=2022,"2022","-") -> - | W42: =IF($T42+$R42=2023,"2023","-") -> - | X42: =IF($T42+$R42=2024,"2024","-") -> 2024 | Y42: =IF($T42+$R42=2025,"2025","-") -> - | AA42: =IF($T42>2018,"Y","N") -> Y
A43: Original | B43: Corporate Functions | C43: Legal | D43: Legal - Litigation | E43: Corporate Functions | G43: Chief Legal Officer | H43: Ghalia Bushnaq | I43: Abdulrahman Khesro | K43: Moez Sassi | L43: Medium | M43: =IF(T43>2017,U43,"N/A") -> Sat | N43: Medium | O43: =IF(Q43="y",1,SUMIFS('Rating Grid'!$D$11:$D$34,'Rating Grid'!$B$11:$B$34,'Audit Universe -Audit Plan2 (2)'!$L$31:$L$173,'Rating Grid'!$C$11:$C$34,'Audit Universe -Audit Plan2 (2)'!$M$31:$M$173)) -> 3 | P43: Medium | Q43: N | R43: =IF(O43>S43,O43,S43) -> 3 | T43: 2021 | U43: Sat | V43: =IF($T43+$R43<=2022,"2022","-") -> - | W43: =IF($T43+$R43=2023,"2023","-") -> - | X43: =IF($T43+$R43=2024,"2024","-") -> 2024 | Y43: =IF($T43+$R43=2025,"2025","-") -> - | AA43: Y
A44: Original | B44: Corporate Functions | C44: Marketing | D44: Marketing | E44: Corporate Functions | F44: 541 | G44: Chief Customer Officer | H44: Dongjun Choi | I44: Gary XX (resigned) | K44: Sangeetha Abraham | L44: Medium | M44: =IF(T44>2017,U44,"N/A") -> NI | N44: Medium | O44: =IF(Q44="y",1,SUMIFS('Rating Grid'!$D$11:$D$34,'Rating Grid'!$B$11:$B$34,'Audit Universe -Audit Plan2 (2)'!$L$31:$L$173,'Rating Grid'!$C$11:$C$34,'Audit Universe -Audit Plan2 (2)'!$M$31:$M$173)) -> 3 | P44: Medium | Q44: N | R44: =IF(O44>S44,O44,S44) -> 4 | S44: 4 | T44: 2019 | U44: NI | V44: =IF($T44+$R44<=2022,"2022","-") -> - | W44: =IF($T44+$R44=2023,"2023","-") -> 2023 | X44: =IF($T44+$R44=2024,"2024","-") -> - | Y44: =IF($T44+$R44=2025,"2025","-") -> - | Z44: y | AA44: =IF($T44>2018,"Y","N") -> Y | AB44: Manual override to 2023.
A45: Original | B45: Corporate Functions | C45: Project Management | D45: Project Management | E45: Operations | G45: CTO | H45: Saket | I45: James | K45: Neil Jarman | L45: High | M45: =IF(T45>2017,U45,"N/A") -> Unrated | N45: Medium | O45: =IF(Q45="y",1,SUMIFS('Rating Grid'!$D$11:$D$34,'Rating Grid'!$B$11:$B$34,'Audit Universe -Audit Plan2 (2)'!$L$31:$L$173,'Rating Grid'!$C$11:$C$34,'Audit Universe -Audit Plan2 (2)'!$M$31:$M$173)) -> 1 | P45: Medium | Q45: N | R45: =IF(O45>S45,O45,S45) -> 3 | S45: 3 | T45: 2021 | U45: Unrated | V45: =IF($T45+$R45<=2022,"2022","-") -> - | W45: =IF($T45+$R45=2023,"2023","-") -> - | X45: =IF($T45+$R45=2024,"2024","-") -> 2024 | Y45: =IF($T45+$R45=2025,"2025","-") -> - | Z45: Y | AA45: =IF($T45>2018,"Y","N") -> Y | AB45: Under consideration to be conducted in 2022 - Q3/4
A46: Original | B46: Corporate Functions | C46: Service Excellence | D46: Service Excellence Unit | E46: Corporate Functions | F46: 508, 560, 726 | G46: Chief Customer Officer | H46: Dongjun Choi | I46: Lina Yahya | K46: Sangeetha Abraham | L46: Medium | M46: =IF(T46>2017,U46,"N/A") -> NI | N46: Medium | O46: =IF(Q46="y",1,SUMIFS('Rating Grid'!$D$11:$D$34,'Rating Grid'!$B$11:$B$34,'Audit Universe -Audit Plan2 (2)'!$L$31:$L$173,'Rating Grid'!$C$11:$C$34,'Audit Universe -Audit Plan2 (2)'!$M$31:$M$173)) -> 3 | P46: Medium | Q46: N | R46: =IF(O46>S46,O46,S46) -> 3 | T46: 2019 | U46: NI | V46: =IF($T46+$R46<=2022,"2022","-") -> 2022 | W46: =IF($T46+$R46=2023,"2023","-") -> - | X46: =IF($T46+$R46=2024,"2024","-") -> - | Y46: =IF($T46+$R46=2025,"2025","-") -> - | Z46: Y | AA46: =IF($T46>2018,"Y","N") -> Y | AB46: Consumer Protection Framework (2022 - 5 audits covering implementation programme)
A47: Original | B47: Credit | C47: WBG & FIG Underwriting | D47: Wholesale Banking & Financial Institutions Credit | E47: Credit | G47: Chief Credit Officer | H47: Mahadevan Radhakanthan | I47: Pradeep Nehra | K47: Neil Jarman | L47: Medium | M47: =IF(T47>2017,U47,"N/A") -> NI | N47: Medium | O47: =IF(Q47="y",1,SUMIFS('Rating Grid'!$D$11:$D$34,'Rating Grid'!$B$11:$B$34,'Audit Universe -Audit Plan2 (2)'!$L$31:$L$173,'Rating Grid'!$C$11:$C$34,'Audit Universe -Audit Plan2 (2)'!$M$31:$M$173)) -> 3 | P47: Medium | Q47: N | R47: =IF(O47>S47,O47,S47) -> 3 | T47: 2019 | U47: NI | V47: =IF($T47+$R47<=2022,"2022","-") -> 2022 | W47: =IF($T47+$R47=2023,"2023","-") -> - | X47: =IF($T47+$R47=2024,"2024","-") -> - | Y47: =IF($T47+$R47=2025,"2025","-") -> - | Z47: Y | AA47: =IF($T47>2018,"Y","N") -> Y | AB47: Syndicated Lending - Q1
A48: Original | B48: Credit | C48: PBG - Underwriting | D48: Underwriting - (All Products) | E48: Credit | F48: 165, 166, 570 | G48: Chief Credit Officer | H48: Mahadevan Radhakanthan | I48: Maha / Vinay Nair | K48: Sangeetha Abraham | L48: Medium | M48: =IF(T48>2017,U48,"N/A") -> Sat | N48: Low | O48: =IF(Q48="y",1,SUMIFS('Rating Grid'!$D$11:$D$34,'Rating Grid'!$B$11:$B$34,'Audit Universe -Audit Plan2 (2)'!$L$31:$L$173,'Rating Grid'!$C$11:$C$34,'Audit Universe -Audit Plan2 (2)'!$M$31:$M$173)) -> 3 | P48: Low | Q48: N | R48: =IF(O48>S48,O48,S48) -> 3 | T48: 2020 | U48: Sat | V48: =IF($T48+$R48<=2022,"2022","-") -> - | W48: =IF($T48+$R48=2023,"2023","-") -> 2023 | X48: =IF($T48+$R48=2024,"2024","-") -> - | Y48: =IF($T48+$R48=2025,"2025","-") -> - | AA48: =IF($T48>2018,"Y","N") -> Y
A49: Original | B49: Credit | C49: BBG - Underwriting | D49: Business Banking Credit | E49: Credit | G49: Chief Credit Officer | H49: Mahadevan Radhakanthan | I49: Vinay Ambekar | K49: Neil Jarman | L49: Medium | M49: =IF(T49>2017,U49,"N/A") -> Sat | N49: Low | O49: =IF(Q49="y",1,SUMIFS('Rating Grid'!$D$11:$D$34,'Rating Grid'!$B$11:$B$34,'Audit Universe -Audit Plan2 (2)'!$L$31:$L$173,'Rating Grid'!$C$11:$C$34,'Audit Universe -Audit Plan2 (2)'!$M$31:$M$173)) -> 3 | P49: Low | Q49: N | R49: =IF(O49>S49,O49,S49) -> 3 | T49: 2021 | U49: Sat | V49: =IF($T49+$R49<=2022,"2022","-") -> - | W49: =IF($T49+$R49=2023,"2023","-") -> - | X49: =IF($T49+$R49=2024,"2024","-") -> 2024 | Y49: =IF($T49+$R49=2025,"2025","-") -> - | AA49: =IF($T49>2018,"Y","N") -> Y
A50: Original | B50: Credit | C50: BBG - Collections | D50: BBG Collections - All Products | E50: Credit | G50: Chief Credit Officer | H50: Mahadevan Radhakanthan | I50: Prashant | K50: Neil Jarman | L50: Medium | M50: =IF(T50>2017,U50,"N/A") -> NI | N50: Medium | O50: =IF(Q50="y",1,SUMIFS('Rating Grid'!$D$11:$D$34,'Rating Grid'!$B$11:$B$34,'Audit Universe -Audit Plan2 (2)'!$L$31:$L$173,'Rating Grid'!$C$11:$C$34,'Audit Universe -Audit Plan2 (2)'!$M$31:$M$173)) -> 3 | P50: Low | Q50: N | R50: =IF(O50>S50,O50,S50) -> 3 | T50: 2021 | U50: NI | V50: =IF($T50+$R50<=2022,"2022","-") -> - | W50: =IF($T50+$R50=2023,"2023","-") -> - | X50: =IF($T50+$R50=2024,"2024","-") -> 2024 | Y50: =IF($T50+$R50=2025,"2025","-") -> - | AA50: =IF($T50>2018,"Y","N") -> Y
A51: Original | B51: Credit | C51: WBG & FIG Collections | D51: WBG & FIG Collections (All Products) | E51: Credit | G51: Chief Credit Officer | H51: Mahadevan Radhakanthan | I51: Prashant | K51: Neil Jarman | L51: Medium | M51: =IF(T51>2017,U51,"N/A") -> N/A | N51: Medium | O51: =IF(Q51="y",1,SUMIFS('Rating Grid'!$D$11:$D$34,'Rating Grid'!$B$11:$B$34,'Audit Universe -Audit Plan2 (2)'!$L$31:$L$173,'Rating Grid'!$C$11:$C$34,'Audit Universe -Audit Plan2 (2)'!$M$31:$M$173)) -> 3 | P51: Medium | Q51: N | R51: =IF(O51>S51,O51,S51) -> 3 | T51: 2010 | U51: - | V51: =IF($T51+$R51<=2022,"2022","-") -> 2022 | W51: =IF($T51+$R51=2023,"2023","-") -> - | X51: =IF($T51+$R51=2024,"2024","-") -> - | Y51: =IF($T51+$R51=2025,"2025","-") -> -
A52: Original | B52: Credit | C52: WM - Underwriting | D52: Wealth Management & Investments - Underwriting (Credit) | E52: Credit | F52: 164 | G52: Chief Credit Officer | H52: Mahadevan Radhakanthan | I52: Maha / Vinay Nair | K52: Sangeetha Abraham | L52: Low | M52: =IF(T52>2017,U52,"N/A") -> Sat | N52: Low | O52: =IF(Q52="y",1,SUMIFS('Rating Grid'!$D$11:$D$34,'Rating Grid'!$B$11:$B$34,'Audit Universe -Audit Plan2 (2)'!$L$31:$L$173,'Rating Grid'!$C$11:$C$34,'Audit Universe -Audit Plan2 (2)'!$M$31:$M$173)) -> 4 | P52: Low | Q52: N | R52: =IF(O52>S52,O52,S52) -> 4 | T52: 2018 | U52: Sat | V52: =IF($T52+$R52<=2022,"2022","-") -> 2022 | W52: =IF($T52+$R52=2023,"2023","-") -> - | X52: =IF($T52+$R52=2024,"2024","-") -> - | Y52: =IF($T52+$R52=2025,"2025","-") -> - | Z52: Y | AA52: =IF($T52>2018,"Y","N") -> N | AB52: LAI
A53: Original | B53: Finance | C53: Financial Control | D53: Budgeting & Forecasting | E53: Finance | F53: 701 | G53: CFO | H53: Jaffar Nini | I53: Mridul | K53: Moez Sassi | L53: Medium | M53: =IF(T53>2017,U53,"N/A") -> Sat | N53: Medium | O53: =IF(Q53="y",1,SUMIFS('Rating Grid'!$D$11:$D$34,'Rating Grid'!$B$11:$B$34,'Audit Universe -Audit Plan2 (2)'!$L$31:$L$173,'Rating Grid'!$C$11:$C$34,'Audit Universe -Audit Plan2 (2)'!$M$31:$M$173)) -> 3 | P53: Medium | Q53: N | R53: =IF(O53>S53,O53,S53) -> 3 | T53: 2021 | U53: Sat | V53: =IF($T53+$R53<=2022,"2022","-") -> - | W53: =IF($T53+$R53=2023,"2023","-") -> - | X53: =IF($T53+$R53=2024,"2024","-") -> 2024 | Y53: =IF($T53+$R53=2025,"2025","-") -> - | AA53: =IF($T53>2018,"Y","N") -> Y
A54: Original | B54: Finance | C54: Financial Control | D54: Financial Accounting, Reporting & Controls (incl. provisions) | E54: Finance | F54: 701 | G54: CFO | H54: Jaffar Nini | I54: Manohar Bhoir/ Gireeshan | K54: Moez Sassi | L54: Medium | M54: =IF(T54>2017,U54,"N/A") -> Sat | N54: Medium | O54: =IF(Q54="y",1,SUMIFS('Rating Grid'!$D$11:$D$34,'Rating Grid'!$B$11:$B$34,'Audit Universe -Audit Plan2 (2)'!$L$31:$L$173,'Rating Grid'!$C$11:$C$34,'Audit Universe -Audit Plan2 (2)'!$M$31:$M$173)) -> 3 | P54: Medium | Q54: N | R54: =IF(O54>S54,O54,S54) -> 3 | T54: 2021 | U54: Sat | V54: =IF($T54+$R54<=2022,"2022","-") -> - | W54: =IF($T54+$R54=2023,"2023","-") -> - | X54: =IF($T54+$R54=2024,"2024","-") -> 2024 | Y54: =IF($T54+$R54=2025,"2025","-") -> - | AA54: =IF($T54>2018,"Y","N") -> Y
A55: Original | B55: Risk | C55: WBG - Credit Provisions (WBG, FIG & Treasury) | D55: Provisions - All Products | E55: Risk | G55: Chief Risk Officer | H55: Farhan Mahmoud | K55: Neil Jarman | L55: Medium | M55: =IF(T55>2017,U55,"N/A") -> NI | N55: Medium | O55: =IF(Q55="y",1,SUMIFS('Rating Grid'!$D$11:$D$34,'Rating Grid'!$B$11:$B$34,'Audit Universe -Audit Plan2 (2)'!$L$31:$L$173,'Rating Grid'!$C$11:$C$34,'Audit Universe -Audit Plan2 (2)'!$M$31:$M$173)) -> 1 | P55: Medium | Q55: Y | R55: =IF(O55>S55,O55,S55) -> 1 | T55: 2021 | U55: NI | V55: =IF($T55+$R55<=2022,"2022","-") -> 2022 | W55: =IF($T55+$R55=2023,"2023","-") -> - | X55: =IF($T55+$R55=2024,"2024","-") -> - | Y55: =IF($T55+$R55=2025,"2025","-") -> - | AA55: =IF($T55>2018,"Y","N") -> Y
A56: Original | B56: Finance | C56: Financial Control | D56: Management Reporting | E56: Finance | F56: 701 | G56: CFO | H56: Jaffar Nini | I56: Mridul | K56: Moez Sassi | L56: Medium | M56: =IF(T56>2017,U56,"N/A") -> Sat | N56: Medium | O56: =IF(Q56="y",1,SUMIFS('Rating Grid'!$D$11:$D$34,'Rating Grid'!$B$11:$B$34,'Audit Universe -Audit Plan2 (2)'!$L$31:$L$173,'Rating Grid'!$C$11:$C$34,'Audit Universe -Audit Plan2 (2)'!$M$31:$M$173)) -> 3 | P56: Medium | Q56: N | R56: =IF(O56>S56,O56,S56) -> 3 | T56: 2021 | U56: Sat | V56: =IF($T56+$R56<=2022,"2022","-") -> - | W56: =IF($T56+$R56=2023,"2023","-") -> - | X56: =IF($T56+$R56=2024,"2024","-") -> 2024 | Y56: =IF($T56+$R56=2025,"2025","-") -> - | AA56: =IF($T56>2018,"Y","N") -> Y
A57: Original | B57: Finance | C57: Regulatory Reporting | D57: Regulatory Reporting (BRFs) | E57: Finance | F57: 701 | G57: CFO | H57: Jaffar Nini | I57: Manohar Bhoir | K57: Moez Sassi | L57: Medium | M57: =IF(T57>2017,U57,"N/A") -> Sat | N57: Low | O57: =IF(Q57="y",1,SUMIFS('Rating Grid'!$D$11:$D$34,'Rating Grid'!$B$11:$B$34,'Audit Universe -Audit Plan2 (2)'!$L$31:$L$173,'Rating Grid'!$C$11:$C$34,'Audit Universe -Audit Plan2 (2)'!$M$31:$M$173)) -> 3 | P57: Low | Q57: N | R57: =IF(O57>S57,O57,S57) -> 3 | T57: 2021 | U57: Sat | V57: =IF($T57+$R57<=2022,"2022","-") -> - | W57: =IF($T57+$R57=2023,"2023","-") -> - | X57: =IF($T57+$R57=2024,"2024","-") -> 2024 | Y57: =IF($T57+$R57=2025,"2025","-") -> - | AA57: =IF($T57>2018,"Y","N") -> Y
A58: Original | B58: Finance | C58: Financial Control | D58: Taxation | E58: Finance | F58: 701 | G58: CFO | H58: Jaffar Nini | I58: Manohar Bhoir | K58: Moez Sassi | L58: Medium | M58: =IF(T58>2017,U58,"N/A") -> Unrated | N58: Low | O58: =IF(Q58="y",1,SUMIFS('Rating Grid'!$D$11:$D$34,'Rating Grid'!$B$11:$B$34,'Audit Universe -Audit Plan2 (2)'!$L$31:$L$173,'Rating Grid'!$C$11:$C$34,'Audit Universe -Audit Plan2 (2)'!$M$31:$M$173)) -> 2 | P58: Low | Q58: N | R58: =IF(O58>S58,O58,S58) -> 2 | T58: 2018 | U58: Unrated | V58: =IF($T58+$R58<=2022,"2022","-") -> 2022 | W58: =IF($T58+$R58=2023,"2023","-") -> - | X58: =IF($T58+$R58=2024,"2024","-") -> - | Y58: =IF($T58+$R58=2025,"2025","-") -> - | Z58: Y | AA58: =IF($T58>2018,"Y","N") -> N | AB58: VAT
A59: Original | B59: Wholesale Banking Group | C59: Coverage - Financial Institutions | D59: Financial Institutions | E59: WBG - Coverage | F59: 175 | G59: WBG Co-Head | H59: Jean Pierre Le Roux | I59: Craig Robertson (W); Srinivas Ramadurai (E) | K59: Neil Jarman | L59: Medium | M59: =IF(T59>2017,U59,"N/A") -> Sat | N59: Medium | O59: =IF(Q59="y",1,SUMIFS('Rating Grid'!$D$11:$D$34,'Rating Grid'!$B$11:$B$34,'Audit Universe -Audit Plan2 (2)'!$L$31:$L$173,'Rating Grid'!$C$11:$C$34,'Audit Universe -Audit Plan2 (2)'!$M$31:$M$173)) -> 3 | P59: Medium | Q59: N | R59: =IF(O59>S59,O59,S59) -> 3 | T59: 2019 | U59: Sat | V59: =IF($T59+$R59<=2022,"2022","-") -> 2022 | W59: =IF($T59+$R59=2023,"2023","-") -> - | X59: =IF($T59+$R59=2024,"2024","-") -> - | Y59: =IF($T59+$R59=2025,"2025","-") -> - | AA59: =IF($T59>2018,"Y","N") -> Y | AB59: To be covered under Syndicated Loans across WBG
A60: Original | B60: Wholesale Banking Group | C60: Coverage - Business Operational Risk Management | D60: Business Operational Risk Management | E60: WBG - Coverage | G60: WBG Co-Head | H60: Jean Pierre Le Roux | I60: Kartik Jayaram | K60: Neil Jarman | L60: Low | M60: =IF(T60>2017,U60,"N/A") -> Sat | N60: Low | O60: =IF(Q60="y",1,SUMIFS('Rating Grid'!$D$11:$D$34,'Rating Grid'!$B$11:$B$34,'Audit Universe -Audit Plan2 (2)'!$L$31:$L$173,'Rating Grid'!$C$11:$C$34,'Audit Universe -Audit Plan2 (2)'!$M$31:$M$173)) -> 4 | P60: Low | Q60: N | R60: =IF(O60>S60,O60,S60) -> 4 | T60: 2019 | U60: Sat | V60: 2022 | X60: =IF($T60+$R60=2024,"2024","-") -> - | Y60: =IF($T60+$R60=2025,"2025","-") -> - | Z60: Y | AA60: =IF($T60>2018,"Y","N") -> Y | AB60: Q1 - Syndicated Lending
A61: Original | B61: Wholesale Banking Group | C61: Product - Transaction Banking | D61: Transaction Banking | E61: WBG - Product | F61: 168, 169, 558 | G61: WBG Co-Head | H61: Vikas Suri | I61: Zavone Krotz | K61: Neil Jarman | L61: Medium | M61: Unrated | N61: Medium | O61: 3 | P61: Medium | Q61: N | R61: =IF(O61>S61,O61,S61) -> 3 | T61: 2017 | U61: Sat | V61: - | W61: 2023 | X61: =IF($T61+$R61=2024,"2024","-") -> - | Y61: =IF($T61+$R61=2025,"2025","-") -> - | AA61: =IF($T61>2018,"Y","N") -> N | AB61: TF strategy under development, audit planned post implementation PP2023
A62: Original | B62: Islamic Banking | C62: Sharia Governance & Risk Oversight | D62: Islamic Banking - Governance | E62: Islamic Banking | F62: 905 | G62: Director - Islamic Banking | H62: Abdul Karim Juma | I62: Husain Cuttleriwala | K62: Muhammad Abdulla | L62: Medium | M62: =IF(T62>2017,U62,"N/A") -> NI | N62: Medium | O62: =IF(Q62="y",1,SUMIFS('Rating Grid'!$D$11:$D$34,'Rating Grid'!$B$11:$B$34,'Audit Universe -Audit Plan2 (2)'!$L$31:$L$173,'Rating Grid'!$C$11:$C$34,'Audit Universe -Audit Plan2 (2)'!$M$31:$M$173)) -> 1 | P62: Medium | Q62: Y | R62: =IF(O62>S62,O62,S62) -> 1 | T62: 2021 | U62: NI | V62: =IF($T62+$R62<=2022,"2022","-") -> 2022 | W62: =IF($T62+$R62=2023,"2023","-") -> - | X62: =IF($T62+$R62=2024,"2024","-") -> - | Y62: =IF($T62+$R62=2025,"2025","-") -> - | Z62: Y | AA62: =IF($T62>2018,"Y","N") -> Y | AB62: Q3 / Q4
A63: Original | B63: Islamic Banking | C63: Sharia Operations | D63: Islamic Banking - Operations | E63: Islamic Banking | F63: 904 | G63: Head of Operations | H63: Juzer Netterwala | I63: Zeena Salim | K63: Muhammad Abdulla | L63: Medium | M63: =IF(T63>2017,U63,"N/A") -> NI | N63: Medium | O63: =IF(Q63="y",1,SUMIFS('Rating Grid'!$D$11:$D$34,'Rating Grid'!$B$11:$B$34,'Audit Universe -Audit Plan2 (2)'!$L$31:$L$173,'Rating Grid'!$C$11:$C$34,'Audit Universe -Audit Plan2 (2)'!$M$31:$M$173)) -> 1 | P63: Medium | Q63: Y | R63: =IF(O63>S63,O63,S63) -> 1 | T63: 2021 | U63: NI | V63: =IF($T63+$R63<=2022,"2022","-") -> 2022 | W63: =IF($T63+$R63=2023,"2023","-") -> - | X63: =IF($T63+$R63=2024,"2024","-") -> - | Y63: =IF($T63+$R63=2025,"2025","-") -> - | AA63: =IF($T63>2018,"Y","N") -> Y
A64: Original | B64: Islamic Banking | C64: Sharia Compliance | D64: Islamic Banking - Compliance | E64: Islamic Banking | F64: 905 | G64: Director - Islamic Banking | H64: Abdul Karim Juma | I64: Husain Cuttleriwala | K64: Muhammad Abdulla | L64: Medium | M64: =IF(T64>2017,U64,"N/A") -> NI | N64: Medium | O64: =IF(Q64="y",1,SUMIFS('Rating Grid'!$D$11:$D$34,'Rating Grid'!$B$11:$B$34,'Audit Universe -Audit Plan2 (2)'!$L$31:$L$173,'Rating Grid'!$C$11:$C$34,'Audit Universe -Audit Plan2 (2)'!$M$31:$M$173)) -> 1 | P64: Medium | Q64: Y | R64: =IF(O64>S64,O64,S64) -> 1 | T64: 2021 | U64: NI | V64: =IF($T64+$R64<=2022,"2022","-") -> 2022 | W64: =IF($T64+$R64=2023,"2023","-") -> - | X64: =IF($T64+$R64=2024,"2024","-") -> - | Y64: =IF($T64+$R64=2025,"2025","-") -> - | Z64: Y | AA64: =IF($T64>2018,"Y","N") -> Y | AB64: Q3 / Q4
A65: Original | B65: IT | C65: Business Applications | D65: Finacle Static Data | E65: IT | F65: 705 | G65: CTO | H65: Saket | I65: Robert Lee | J65: Vijay Harshen | K65: Biju Varughese | L65: High | M65: =IF(T65>2017,U65,"N/A") -> N/A | N65: Medium | O65: =IF(Q65="y",1,SUMIFS('Rating Grid'!$D$11:$D$34,'Rating Grid'!$B$11:$B$34,'Audit Universe -Audit Plan2 (2)'!$L$31:$L$173,'Rating Grid'!$C$11:$C$34,'Audit Universe -Audit Plan2 (2)'!$M$31:$M$173)) -> 2 | P65: Medium | Q65: N | R65: =IF(O65>S65,O65,S65) -> 2 | T65: 2017 | U65: Sat | V65: =IF($T65+$R65<=2022,"2022","-") -> 2022 | W65: =IF($T65+$R65=2023,"2023","-") -> - | X65: =IF($T65+$R65=2024,"2024","-") -> - | Y65: =IF($T65+$R65=2025,"2025","-") -> - | Z65: Y | AA65: =IF($T65>2018,"Y","N") -> N
A66: Original | B66: IT | C66: IT Governance, Process & Services | D66: IT Change & Service Management | E66: IT | F66: 705 | G66: CTO | H66: Saket | I66: Robert Lee | J66: Tabrez Sheikh | K66: Biju Varughese | L66: Medium | M66: =IF(T66>2017,U66,"N/A") -> NI | N66: Medium | O66: =IF(Q66="y",1,SUMIFS('Rating Grid'!$D$11:$D$34,'Rating Grid'!$B$11:$B$34,'Audit Universe -Audit Plan2 (2)'!$L$31:$L$173,'Rating Grid'!$C$11:$C$34,'Audit Universe -Audit Plan2 (2)'!$M$31:$M$173)) -> 3 | P66: Medium | Q66: N | R66: =IF(O66>S66,O66,S66) -> 3 | T66: 2021 | U66: NI | V66: =IF($T66+$R66<=2022,"2022","-") -> - | W66: =IF($T66+$R66=2023,"2023","-") -> - | X66: =IF($T66+$R66=2024,"2024","-") -> 2024 | Y66: =IF($T66+$R66=2025,"2025","-") -> - | AA66: =IF($T66>2018,"Y","N") -> Y
A67: Original | B67: IT | C67: IT Infrastructure | D67: Cloud applications | E67: IT | F67: 705 | G67: CTO | H67: Saket | I67: Robert Lee | J67: Jonathan Gonsalves / Shyam Kesarwani | K67: Biju Varughese | L67: Medium | M67: =IF(T67>2017,U67,"N/A") -> N/A | N67: Medium | O67: =IF(Q67="y",1,SUMIFS('Rating Grid'!$D$11:$D$34,'Rating Grid'!$B$11:$B$34,'Audit Universe -Audit Plan2 (2)'!$L$31:$L$173,'Rating Grid'!$C$11:$C$34,'Audit Universe -Audit Plan2 (2)'!$M$31:$M$173)) -> 3 | P67: Medium | Q67: N | R67: =IF(O67>S67,O67,S67) -> 3 | T67: 2010 | U67: - | V67: =IF($T67+$R67<=2022,"2022","-") -> 2022 | W67: =IF($T67+$R67=2023,"2023","-") -> - | X67: =IF($T67+$R67=2024,"2024","-") -> - | Y67: =IF($T67+$R67=2025,"2025","-") -> - | AA67: =IF($T67>2018,"Y","N") -> N
A68: Original | B68: Risk | C68: IT Risk / Information Security | D68: NESA Compliance | E68: IT | F68: 705 | G68: Chief Risk Officer | H68: Farhan Mahmoud | I68: Safwan Ghaleb | J68: Tushar Vartak | K68: Biju Varughese | L68: Medium | M68: =IF(T68>2017,U68,"N/A") -> NI | N68: Medium | O68: =IF(Q68="y",1,SUMIFS('Rating Grid'!$D$11:$D$34,'Rating Grid'!$B$11:$B$34,'Audit Universe -Audit Plan2 (2)'!$L$31:$L$173,'Rating Grid'!$C$11:$C$34,'Audit Universe -Audit Plan2 (2)'!$M$31:$M$173)) -> 3 | P68: Medium | Q68: N | R68: =IF(O68>S68,O68,S68) -> 3 | T68: 2020 | U68: NI | V68: =IF($T68+$R68<=2022,"2022","-") -> - | W68: =IF($T68+$R68=2023,"2023","-") -> 2023 | X68: =IF($T68+$R68=2024,"2024","-") -> - | Y68: =IF($T68+$R68=2025,"2025","-") -> - | AA68: =IF($T68>2018,"Y","N") -> Y
A69: Original | B69: IT | C69: IT Governance, Process & Services | D69: IT Development | E69: IT | F69: 705 | G69: CTO | H69: Saket | I69: Robert Lee | J69: Ajit Pillai | K69: Biju Varughese | L69: Medium | M69: =IF(T69>2017,U69,"N/A") -> Sat | N69: Low | O69: =IF(Q69="y",1,SUMIFS('Rating Grid'!$D$11:$D$34,'Rating Grid'!$B$11:$B$34,'Audit Universe -Audit Plan2 (2)'!$L$31:$L$173,'Rating Grid'!$C$11:$C$34,'Audit Universe -Audit Plan2 (2)'!$M$31:$M$173)) -> 3 | P69: Low | Q69: N | R69: =IF(O69>S69,O69,S69) -> 3 | T69: 2020 | U69: Sat | V69: =IF($T69+$R69<=2022,"2022","-") -> - | W69: =IF($T69+$R69=2023,"2023","-") -> 2023 | X69: =IF($T69+$R69=2024,"2024","-") -> - | Y69: =IF($T69+$R69=2025,"2025","-") -> - | AA69: =IF($T69>2018,"Y","N") -> Y
A70: Original | B70: IT | C70: IT Infrastructure | D70: IT Network Management, Voice and Security | E70: IT | F70: 705 | G70: CTO | H70: Saket | I70: Robert Lee | J70: Jonathan Gonsalves | K70: Biju Varughese | L70: High | M70: =IF(T70>2017,U70,"N/A") -> Sat | N70: Low | O70: =IF(Q70="y",1,SUMIFS('Rating Grid'!$D$11:$D$34,'Rating Grid'!$B$11:$B$34,'Audit Universe -Audit Plan2 (2)'!$L$31:$L$173,'Rating Grid'!$C$11:$C$34,'Audit Universe -Audit Plan2 (2)'!$M$31:$M$173)) -> 2 | P70: Low | Q70: N | R70: =IF(O70>S70,O70,S70) -> 2 | T70: 2019 | U70: Sat | V70: =IF($T70+$R70<=2022,"2022","-") -> 2022 | W70: =IF($T70+$R70=2023,"2023","-") -> - | X70: =IF($T70+$R70=2024,"2024","-") -> - | Y70: =IF($T70+$R70=2025,"2025","-") -> - | Z70: Y | AA70: =IF($T70>2018,"Y","N") -> Y
A71: Original | B71: IT | C71: IT Infrastructure | D71: Middleware (One-off) | E71: IT | F71: 705 | G71: CTO | H71: Saket | I71: Robert Lee | K71: Biju Varughese | L71: Medium | M71: =IF(T71>2017,U71,"N/A") -> N/A | N71: Medium | O71: =IF(Q71="y",1,SUMIFS('Rating Grid'!$D$11:$D$34,'Rating Grid'!$B$11:$B$34,'Audit Universe -Audit Plan2 (2)'!$L$31:$L$173,'Rating Grid'!$C$11:$C$34,'Audit Universe -Audit Plan2 (2)'!$M$31:$M$173)) -> 3 | P71: Medium | Q71: N | R71: =IF(O71>S71,O71,S71) -> 3 | T71: 2010 | U71: - | V71: =IF($T71+$R71<=2022,"2022","-") -> 2022 | W71: =IF($T71+$R71=2023,"2023","-") -> - | X71: =IF($T71+$R71=2024,"2024","-") -> - | Y71: =IF($T71+$R71=2025,"2025","-") -> - | AA71: =IF($T71>2018,"Y","N") -> N | AB71: One-off due to changing Middleware structure
A72: Original | B72: IT | C72: Third Parties | D72: Third party IT controls | E72: IT | F72: 705 | G72: CTO | H72: Saket | I72: BU Director &Robert Lee | K72: Biju Varughese | L72: Medium | M72: =IF(T72>2017,U72,"N/A") -> N/A | N72: Medium | O72: =IF(Q72="y",1,SUMIFS('Rating Grid'!$D$11:$D$34,'Rating Grid'!$B$11:$B$34,'Audit Universe -Audit Plan2 (2)'!$L$31:$L$173,'Rating Grid'!$C$11:$C$34,'Audit Universe -Audit Plan2 (2)'!$M$31:$M$173)) -> 3 | P72: High | Q72: N | R72: =IF(O72>S72,O72,S72) -> 3 | T72: 2010 | U72: - | V72: =IF($T72+$R72<=2022,"2022","-") -> 2022 | W72: =IF($T72+$R72=2023,"2023","-") -> - | X72: =IF($T72+$R72=2024,"2024","-") -> - | Y72: =IF($T72+$R72=2025,"2025","-") -> - | AA72: =IF($T72>2018,"Y","N") -> N
A73: Original | B73: IT | C73: Business Applications | D73: Swift & Payment Gateways | E73: IT | F73: 551 | G73: CTO | H73: Saket | I73: Robert Lee | K73: Biju Varughese | L73: High | M73: =IF(T73>2017,U73,"N/A") -> NI | N73: Medium | O73: =IF(Q73="y",1,SUMIFS('Rating Grid'!$D$11:$D$34,'Rating Grid'!$B$11:$B$34,'Audit Universe -Audit Plan2 (2)'!$L$31:$L$173,'Rating Grid'!$C$11:$C$34,'Audit Universe -Audit Plan2 (2)'!$M$31:$M$173)) -> 2 | P73: High | Q73: N | R73: =IF(O73>S73,O73,S73) -> 2 | T73: 2020 | U73: NI | V73: =IF($T73+$R73<=2022,"2022","-") -> 2022 | W73: =IF($T73+$R73=2023,"2023","-") -> - | X73: =IF($T73+$R73=2024,"2024","-") -> - | Y73: =IF($T73+$R73=2025,"2025","-") -> - | AA73: =IF($T73>2018,"Y","N") -> Y
A74: Original | B74: IT | C74: IT Infrastructure | D74: IT Infrastructure | E74: IT | F74: 705 | G74: CTO | H74: Saket | I74: Robert Lee | J74: Jonathan Gonsalves | K74: Biju Varughese | L74: High | M74: =IF(T74>2017,U74,"N/A") -> NI | N74: Medium | O74: =IF(Q74="y",1,SUMIFS('Rating Grid'!$D$11:$D$34,'Rating Grid'!$B$11:$B$34,'Audit Universe -Audit Plan2 (2)'!$L$31:$L$173,'Rating Grid'!$C$11:$C$34,'Audit Universe -Audit Plan2 (2)'!$M$31:$M$173)) -> 2 | P74: Medium | Q74: N | R74: =IF(O74>S74,O74,S74) -> 3 | S74: 3 | T74: 2019 | U74: NI | V74: =IF($T74+$R74<=2022,"2022","-") -> 2022 | W74: =IF($T74+$R74=2023,"2023","-") -> - | X74: =IF($T74+$R74=2024,"2024","-") -> - | Y74: =IF($T74+$R74=2025,"2025","-") -> - | AA74: =IF($T74>2018,"Y","N") -> Y
A75: Original | B75: IT | C75: Business Applications | D75: User Access Management | E75: IT | F75: 705 | G75: CTO | H75: Saket | I75: Robert Lee | J75: Sh Abdullah | K75: Biju Varughese | L75: Medium | M75: =IF(T75>2017,U75,"N/A") -> NI | N75: Medium | O75: =IF(Q75="y",1,SUMIFS('Rating Grid'!$D$11:$D$34,'Rating Grid'!$B$11:$B$34,'Audit Universe -Audit Plan2 (2)'!$L$31:$L$173,'Rating Grid'!$C$11:$C$34,'Audit Universe -Audit Plan2 (2)'!$M$31:$M$173)) -> 3 | P75: high | Q75: N | R75: =IF(O75>S75,O75,S75) -> 3 | T75: 2018 | U75: NI | V75: =IF($T75+$R75<=2022,"2022","-") -> 2022 | W75: =IF($T75+$R75=2023,"2023","-") -> - | X75: =IF($T75+$R75=2024,"2024","-") -> - | Y75: =IF($T75+$R75=2025,"2025","-") -> - | Z75: Y | AA75: =IF($T75>2018,"Y","N") -> N | AB75: Q1
A76: Original | B76: Corporate Functions | C76: Administration & Asset Management | D76: Administration & Asset Management | E76: Corporate Functions | F76: 704 | G76: CFO | H76: Deepak Majithia | I76: Shameek | K76: Sangeetha Abraham | L76: Low | M76: =IF(T76>2017,U76,"N/A") -> NI | N76: Medium | O76: =IF(Q76="y",1,SUMIFS('Rating Grid'!$D$11:$D$34,'Rating Grid'!$B$11:$B$34,'Audit Universe -Audit Plan2 (2)'!$L$31:$L$173,'Rating Grid'!$C$11:$C$34,'Audit Universe -Audit Plan2 (2)'!$M$31:$M$173)) -> 4 | P76: Medium | Q76: N | R76: =IF(O76>S76,O76,S76) -> 4 | T76: 2019 | U76: NI | V76: =IF($T76+$R76<=2022,"2022","-") -> - | W76: =IF($T76+$R76=2023,"2023","-") -> 2023 | X76: =IF($T76+$R76=2024,"2024","-") -> - | Y76: =IF($T76+$R76=2025,"2025","-") -> - | AA76: =IF($T76>2018,"Y","N") -> Y
A77: Original | B77: Operations | C77: Business Continuity Management | D77: Business Continuity Management & Disaster Recovery | E77: Operations | F77: 709 | G77: CRO | H77: Farhan Mahmoud | I77: Jiju | J77: Prem Achutha | K77: Biju Varughese | L77: High | M77: =IF(T77>2017,U77,"N/A") -> Sat | N77: Medium | O77: =IF(Q77="y",1,SUMIFS('Rating Grid'!$D$11:$D$34,'Rating Grid'!$B$11:$B$34,'Audit Universe -Audit Plan2 (2)'!$L$31:$L$173,'Rating Grid'!$C$11:$C$34,'Audit Universe -Audit Plan2 (2)'!$M$31:$M$173)) -> 2 | P77: Medium | Q77: N | R77: =IF(O77>S77,O77,S77) -> 2 | T77: 2021 | U77: Sat | V77: =IF($T77+$R77<=2022,"2022","-") -> - | W77: =IF($T77+$R77=2023,"2023","-") -> 2023 | X77: =IF($T77+$R77=2024,"2024","-") -> - | Y77: =IF($T77+$R77=2025,"2025","-") -> - | AA77: =IF($T77>2018,"Y","N") -> Y
A78: Original | B78: Operations | C78: Cash Management | D78: Cash Management (Clearing, Nostros) | E78: Operations | G78: COO | H78: Michael Power | I78: Juzer Netterwala | J78: Saeed | K78: Sangeetha Abraham | L78: Medium | M78: =IF(T78>2017,U78,"N/A") -> Sat | N78: Medium | O78: =IF(Q78="y",1,SUMIFS('Rating Grid'!$D$11:$D$34,'Rating Grid'!$B$11:$B$34,'Audit Universe -Audit Plan2 (2)'!$L$31:$L$173,'Rating Grid'!$C$11:$C$34,'Audit Universe -Audit Plan2 (2)'!$M$31:$M$173)) -> 3 | P78: Medium | Q78: N | R78: =IF(O78>S78,O78,S78) -> 3 | T78: 2018 | U78: Sat | V78: =IF($T78+$R78<=2022,"2022","-") -> 2022 | W78: =IF($T78+$R78=2023,"2023","-") -> - | X78: =IF($T78+$R78=2024,"2024","-") -> - | Y78: =IF($T78+$R78=2025,"2025","-") -> - | Z78: Y | AA78: =IF($T78>2018,"Y","N") -> N | AB78: Not in initial audit plan. Not consistent with the rating. Inherent risk should be Medium not High.
A79: Original | B79: Operations | C79: Central Operations (Financial) | D79: Central Operations (Financial) | E79: Operations | F79: 510 | G79: COO | H79: Michael Power | I79: Juzer Netterwala | J79: Saeed | K79: Sangeetha Abraham | L79: Medium | M79: =IF(T79>2017,U79,"N/A") -> Sat | N79: Low | O79: =IF(Q79="y",1,SUMIFS('Rating Grid'!$D$11:$D$34,'Rating Grid'!$B$11:$B$34,'Audit Universe -Audit Plan2 (2)'!$L$31:$L$173,'Rating Grid'!$C$11:$C$34,'Audit Universe -Audit Plan2 (2)'!$M$31:$M$173)) -> 3 | P79: Medium | Q79: N | R79: =IF(O79>S79,O79,S79) -> 3 | T79: 2021 | U79: Sat | V79: =IF($T79+$R79<=2022,"2022","-") -> - | W79: =IF($T79+$R79=2023,"2023","-") -> - | X79: =IF($T79+$R79=2024,"2024","-") -> 2024 | Y79: =IF($T79+$R79=2025,"2025","-") -> - | AA79: =IF($T79>2018,"Y","N") -> Y
A80: Original | B80: Operations | C80: Central Operations (Non-Financial) | D80: Central Operations (Non-Financial) | E80: Operations | F80: 510 | G80: COO | H80: Michael Power | I80: Juzer Netterwala | J80: Saeed | K80: Sangeetha Abraham | L80: Low | M80: =IF(T80>2017,U80,"N/A") -> Sat | N80: Very Low | O80: =IF(Q80="y",1,SUMIFS('Rating Grid'!$D$11:$D$34,'Rating Grid'!$B$11:$B$34,'Audit Universe -Audit Plan2 (2)'!$L$31:$L$173,'Rating Grid'!$C$11:$C$34,'Audit Universe -Audit Plan2 (2)'!$M$31:$M$173)) -> 4 | P80: low | Q80: N | R80: =IF(O80>S80,O80,S80) -> 4 | T80: 2021 | U80: Sat | V80: =IF($T80+$R80<=2022,"2022","-") -> - | W80: =IF($T80+$R80=2023,"2023","-") -> - | X80: =IF($T80+$R80=2024,"2024","-") -> - | Y80: =IF($T80+$R80=2025,"2025","-") -> 2025 | AA80: =IF($T80>2018,"Y","N") -> Y
A81: Original | B81: Operations | C81: BBG - Operations & Acct Monitoring | D81: Commercial Banking - Operations & Account monitoring | E81: Operations | G81: COO | H81: Michael Power | I81: Juzer Netterwala | J81: Shalini Mehta | K81: Neil Jarman | L81: Medium | M81: =IF(T81>2017,U81,"N/A") -> Sat | N81: Low | O81: =IF(Q81="y",1,SUMIFS('Rating Grid'!$D$11:$D$34,'Rating Grid'!$B$11:$B$34,'Audit Universe -Audit Plan2 (2)'!$L$31:$L$173,'Rating Grid'!$C$11:$C$34,'Audit Universe -Audit Plan2 (2)'!$M$31:$M$173)) -> 3 | P81: Medium | Q81: N | R81: =IF(O81>S81,O81,S81) -> 3 | T81: 2021 | U81: Sat | V81: =IF($T81+$R81<=2022,"2022","-") -> - | W81: =IF($T81+$R81=2023,"2023","-") -> - | X81: =IF($T81+$R81=2024,"2024","-") -> 2024 | Y81: =IF($T81+$R81=2025,"2025","-") -> - | AA81: =IF($T81>2018,"Y","N") -> Y
A82: Original | B82: Operations | C82: WBG - Operations & Acct Monitoring | D82: Corporate Banking - Operations & Account monitoring - All Products | E82: Operations | G82: COO | H82: Michael Power | I82: Juzer Netterwala | J82: Shalini Mehta | K82: Neil Jarman | L82: Medium | M82: =IF(T82>2017,U82,"N/A") -> Sat | N82: Low | O82: =IF(Q82="y",1,SUMIFS('Rating Grid'!$D$11:$D$34,'Rating Grid'!$B$11:$B$34,'Audit Universe -Audit Plan2 (2)'!$L$31:$L$173,'Rating Grid'!$C$11:$C$34,'Audit Universe -Audit Plan2 (2)'!$M$31:$M$173)) -> 3 | P82: Medium | Q82: N | R82: =IF(O82>S82,O82,S82) -> 3 | T82: 2020 | U82: Sat | V82: =IF($T82+$R82<=2022,"2022","-") -> - | W82: =IF($T82+$R82=2023,"2023","-") -> 2023 | X82: =IF($T82+$R82=2024,"2024","-") -> - | Y82: =IF($T82+$R82=2025,"2025","-") -> - | Z82: Y | AA82: =IF($T82>2018,"Y","N") -> Y | AB82: Q1
A83: Original | B83: Operations | C83: PBG - Operations & Acct Monitoring | D83: Credit Operations - (All Products) | E83: Operations | F83: 151, 556 | G83: COO | H83: Michael Power | I83: Juzer Netterwala | K83: Sangeetha Abraham | L83: Medium | M83: =IF(T83>2017,U83,"N/A") -> Sat | N83: Low | O83: =IF(Q83="y",1,SUMIFS('Rating Grid'!$D$11:$D$34,'Rating Grid'!$B$11:$B$34,'Audit Universe -Audit Plan2 (2)'!$L$31:$L$173,'Rating Grid'!$C$11:$C$34,'Audit Universe -Audit Plan2 (2)'!$M$31:$M$173)) -> 3 | P83: Medium | Q83: N | R83: =IF(O83>S83,O83,S83) -> 3 | T83: 2020 | U83: Sat | V83: =IF($T83+$R83<=2022,"2022","-") -> - | W83: =IF($T83+$R83=2023,"2023","-") -> 2023 | X83: =IF($T83+$R83=2024,"2024","-") -> - | Y83: =IF($T83+$R83=2025,"2025","-") -> - | AA83: =IF($T83>2018,"Y","N") -> Y | AB83: Information incorrect. The audit was performed in 2019. Included as part of mortgage audit.
A84: Original | B84: Operations | C84: Documents Archival & Retrieval | D84: Documents Archival & Retrieval | E84: Operations | F84: 731 | G84: COO | H84: Michael Power | I84: Shameek | K84: Sangeetha Abraham | L84: Very Low | M84: =IF(T84>2017,U84,"N/A") -> NI | N84: Very Low | O84: =IF(Q84="y",1,SUMIFS('Rating Grid'!$D$11:$D$34,'Rating Grid'!$B$11:$B$34,'Audit Universe -Audit Plan2 (2)'!$L$31:$L$173,'Rating Grid'!$C$11:$C$34,'Audit Universe -Audit Plan2 (2)'!$M$31:$M$173)) -> 0 | P84: Very Low | Q84: N | R84: =IF(O84>S84,O84,S84) -> 4 | S84: 4 | T84: 2019 | U84: NI | V84: =IF($T84+$R84<=2022,"2022","-") -> - | W84: =IF($T84+$R84=2023,"2023","-") -> 2023 | X84: =IF($T84+$R84=2024,"2024","-") -> - | Y84: =IF($T84+$R84=2025,"2025","-") -> - | AA84: =IF($T84>2018,"Y","N") -> Y | AB84: Administrative framework
A85: Original | B85: Operations | C85: Third Parties | D85: Outsourced Activities - General and Strategy | E85: Operations | F85: 705 | G85: COO | H85: Michael Power | I85: Juzer Netterwala | J85: Sandeep Athavale | K85: Sangeetha Abraham | L85: Medium | M85: =IF(T85>2017,U85,"N/A") -> Sat | N85: Medium | O85: =IF(Q85="y",1,SUMIFS('Rating Grid'!$D$11:$D$34,'Rating Grid'!$B$11:$B$34,'Audit Universe -Audit Plan2 (2)'!$L$31:$L$173,'Rating Grid'!$C$11:$C$34,'Audit Universe -Audit Plan2 (2)'!$M$31:$M$173)) -> 3 | P85: Medium | Q85: N | R85: =IF(O85>S85,O85,S85) -> 3 | T85: 2021 | U85: Sat | V85: =IF($T85+$R85<=2022,"2022","-") -> - | W85: =IF($T85+$R85=2023,"2023","-") -> - | X85: =IF($T85+$R85=2024,"2024","-") -> 2024 | Y85: =IF($T85+$R85=2025,"2025","-") -> - | AA85: =IF($T85>2018,"Y","N") -> Y | AB85: WIPRO Only - Covered as central Ops, WM Ops, remittance audit and customer on-boarding 2022.
A86: Original | B86: Corporate Functions | C86: Premises & Facilities Management | D86: Premises & Facilities Management | E86: Corporate Functions | F86: 711 | G86: CFO | H86: Deepak Majithia | I86: Shameek | K86: Sangeetha Abraham | L86: Very Low | M86: =IF(T86>2017,U86,"N/A") -> N/A | N86: Very Low | O86: =IF(Q86="y",1,SUMIFS('Rating Grid'!$D$11:$D$34,'Rating Grid'!$B$11:$B$34,'Audit Universe -Audit Plan2 (2)'!$L$31:$L$173,'Rating Grid'!$C$11:$C$34,'Audit Universe -Audit Plan2 (2)'!$M$31:$M$173)) -> 0 | P86: Very Low | Q86: N | R86: 0 | S86: 4 | T86: 2015 | U86: Sat | W86: 2023 | X86: =IF($T86+$R86=2024,"2024","-") -> - | Y86: =IF($T86+$R86=2025,"2025","-") -> - | AA86: =IF($T86>2018,"Y","N") -> N | AB86: Stakeholder Management only.
A87: Original | B87: Corporate Functions | C87: Procurement & Vendor Management | D87: Procurement / Vendor Management | E87: Corporate Functions | G87: CFO | H87: Deepak Majithia | I87: Shameek | K87: Sangeetha Abraham | L87: Medium | M87: =IF(T87>2017,U87,"N/A") -> NI | N87: Medium | O87: =IF(Q87="y",1,SUMIFS('Rating Grid'!$D$11:$D$34,'Rating Grid'!$B$11:$B$34,'Audit Universe -Audit Plan2 (2)'!$L$31:$L$173,'Rating Grid'!$C$11:$C$34,'Audit Universe -Audit Plan2 (2)'!$M$31:$M$173)) -> 3 | P87: Medium | Q87: N | R87: =IF(O87>S87,O87,S87) -> 3 | T87: 2020 | U87: NI | V87: =IF($T87+$R87<=2022,"2022","-") -> - | W87: =IF($T87+$R87=2023,"2023","-") -> 2023 | X87: =IF($T87+$R87=2024,"2024","-") -> - | Y87: =IF($T87+$R87=2025,"2025","-") -> - | AA87: =IF($T87>2018,"Y","N") -> Y | AB87: Look into IT Audit coverage????
A88: Original | B88: Operations | C88: Remittances (Non-Trade) | D88: Remittances (Non-Trade) | E88: Operations | F88: 551 | G88: COO | H88: Michael Power | I88: Juzer Netterwala | J88: Saeed | K88: Sangeetha Abraham | L88: Medium | M88: =IF(T88>2017,U88,"N/A") -> Sat | N88: Low | O88: =IF(Q88="y",1,SUMIFS('Rating Grid'!$D$11:$D$34,'Rating Grid'!$B$11:$B$34,'Audit Universe -Audit Plan2 (2)'!$L$31:$L$173,'Rating Grid'!$C$11:$C$34,'Audit Universe -Audit Plan2 (2)'!$M$31:$M$173)) -> 3 | P88: Medium | Q88: N | R88: =IF(O88>S88,O88,S88) -> 3 | S88: 3 | T88: 2021 | U88: Sat | V88: =IF($T88+$R88<=2022,"2022","-") -> - | W88: =IF($T88+$R88=2023,"2023","-") -> - | X88: =IF($T88+$R88=2024,"2024","-") -> 2024 | Y88: =IF($T88+$R88=2025,"2025","-") -> - | AA88: =IF($T88>2018,"Y","N") -> Y
A89: Original | B89: Operations | C89: Trade Finance - Operations & Acct Monitoring | D89: Trade Finance - Operations | E89: Operations | G89: COO | H89: Michael Power | I89: Juzer Netterwala | J89: Shalini Mehta | K89: Neil Jarman | L89: Medium | M89: =IF(T89>2017,U89,"N/A") -> N/A | N89: Medium | O89: =IF(Q89="y",1,SUMIFS('Rating Grid'!$D$11:$D$34,'Rating Grid'!$B$11:$B$34,'Audit Universe -Audit Plan2 (2)'!$L$31:$L$173,'Rating Grid'!$C$11:$C$34,'Audit Universe -Audit Plan2 (2)'!$M$31:$M$173)) -> 3 | P89: Medium | Q89: N | R89: =IF(O89>S89,O89,S89) -> 3 | T89: 2017 | U89: Sat | V89: =IF($T89+$R89<=2022,"2022","-") -> 2022 | W89: =IF($T89+$R89=2023,"2023","-") -> - | X89: =IF($T89+$R89=2024,"2024","-") -> - | Y89: =IF($T89+$R89=2025,"2025","-") -> - | Z89: Y | AA89: =IF($T89>2018,"Y","N") -> N | AB89: H2
A90: Original | B90: Operations | C90: WM - Operations & Acct Monitoring | D90: Wealth Management and Investments - Operations | E90: Operations | G90: COO | H90: Michael Power | I90: Juzer Netterwala | J90: Warren | K90: Sangeetha Abraham | L90: Medium | M90: =IF(T90>2017,U90,"N/A") -> Sat | N90: Low | O90: =IF(Q90="y",1,SUMIFS('Rating Grid'!$D$11:$D$34,'Rating Grid'!$B$11:$B$34,'Audit Universe -Audit Plan2 (2)'!$L$31:$L$173,'Rating Grid'!$C$11:$C$34,'Audit Universe -Audit Plan2 (2)'!$M$31:$M$173)) -> 3 | P90: Low | Q90: N | R90: =IF(O90>S90,O90,S90) -> 3 | T90: 2021 | U90: Sat | V90: =IF($T90+$R90<=2022,"2022","-") -> - | W90: =IF($T90+$R90=2023,"2023","-") -> - | X90: =IF($T90+$R90=2024,"2024","-") -> 2024 | Y90: =IF($T90+$R90=2025,"2025","-") -> - | AA90: =IF($T90>2018,"Y","N") -> Y
A91: Original | B91: Personal Banking | C91: Branch Controls | D91: Branch Controls & Distribution | E91: Personal Banking | F91: 578 | G91: MD Personal Banking | H91: Shehzad Hameed | I91: Naji Mohd. | K91: Sangeetha Abraham | L91: Low | M91: =IF(T91>2017,U91,"N/A") -> Sat | N91: Very Low | O91: =IF(Q91="y",1,SUMIFS('Rating Grid'!$D$11:$D$34,'Rating Grid'!$B$11:$B$34,'Audit Universe -Audit Plan2 (2)'!$L$31:$L$173,'Rating Grid'!$C$11:$C$34,'Audit Universe -Audit Plan2 (2)'!$M$31:$M$173)) -> 4 | P91: Low | Q91: N | R91: =IF(O91>S91,O91,S91) -> 4 | T91: 2020 | U91: Sat | V91: =IF($T91+$R91<=2022,"2022","-") -> - | W91: =IF($T91+$R91=2023,"2023","-") -> - | X91: =IF($T91+$R91=2024,"2024","-") -> 2024 | Y91: =IF($T91+$R91=2025,"2025","-") -> - | Z91: Y | AA91: =IF($T91>2018,"Y","N") -> Y | AB91: Embedded as part of on-going branch audits, however will be covered in 2022.
A92: Original | B92: Personal Banking | C92: Business Analytics | D92: Business Performance & Strategic Analytics | E92: Personal Banking | F92: 513 | G92: MD Personal Banking | H92: Shehzad Hameed | I92: HPB / Ramzi | K92: Sangeetha Abraham | L92: Medium | M92: =IF(T92>2017,U92,"N/A") -> Sat | N92: Low | O92: =IF(Q92="y",1,SUMIFS('Rating Grid'!$D$11:$D$34,'Rating Grid'!$B$11:$B$34,'Audit Universe -Audit Plan2 (2)'!$L$31:$L$173,'Rating Grid'!$C$11:$C$34,'Audit Universe -Audit Plan2 (2)'!$M$31:$M$173)) -> 3 | P92: Low | Q92: N | R92: =IF(O92>S92,O92,S92) -> 3 | T92: 2020 | U92: Sat | V92: =IF($T92+$R92<=2022,"2022","-") -> - | W92: =IF($T92+$R92=2023,"2023","-") -> 2023 | X92: =IF($T92+$R92=2024,"2024","-") -> - | Y92: =IF($T92+$R92=2025,"2025","-") -> - | AA92: =IF($T92>2018,"Y","N") -> Y
A93: Original | B93: Credit | C93: PBG - Collections | D93: PBG - Collections (All products) | E93: Credit | F93: 509 | G93: CCO | H93: Mahadevan Radhakanthan | I93: Khadija | K93: Sangeetha Abraham | L93: Medium | M93: =IF(T93>2017,U93,"N/A") -> NI | N93: Medium | O93: =IF(Q93="y",1,SUMIFS('Rating Grid'!$D$11:$D$34,'Rating Grid'!$B$11:$B$34,'Audit Universe -Audit Plan2 (2)'!$L$31:$L$173,'Rating Grid'!$C$11:$C$34,'Audit Universe -Audit Plan2 (2)'!$M$31:$M$173)) -> 3 | P93: Medium | Q93: N | R93: =IF(O93>S93,O93,S93) -> 3 | T93: 2019 | U93: NI | V93: =IF($T93+$R93<=2022,"2022","-") -> 2022 | W93: =IF($T93+$R93=2023,"2023","-") -> - | X93: =IF($T93+$R93=2024,"2024","-") -> - | Y93: =IF($T93+$R93=2025,"2025","-") -> - | Z93: Y | AA93: =IF($T93>2018,"Y","N") -> Y | AB93: CPF - Q2
A94: Original | B94: Personal Banking | C94: PBG - Assets | D94: Sales (All products) | E94: Personal Banking | F94: 513, 523, 550 | G94: MD Personal Banking | H94: Shehzad Hameed | K94: Sangeetha Abraham | L94: Medium | M94: =IF(T94>2017,U94,"N/A") -> Sat | N94: Low | O94: =IF(Q94="y",1,SUMIFS('Rating Grid'!$D$11:$D$34,'Rating Grid'!$B$11:$B$34,'Audit Universe -Audit Plan2 (2)'!$L$31:$L$173,'Rating Grid'!$C$11:$C$34,'Audit Universe -Audit Plan2 (2)'!$M$31:$M$173)) -> 3 | P94: Medium | Q94: N | R94: =IF(O94>S94,O94,S94) -> 3 | T94: 2021 | U94: Sat | V94: =IF($T94+$R94<=2022,"2022","-") -> - | W94: =IF($T94+$R94=2023,"2023","-") -> - | X94: =IF($T94+$R94=2024,"2024","-") -> 2024 | Y94: =IF($T94+$R94=2025,"2025","-") -> - | AA94: =IF($T94>2018,"Y","N") -> Y | AB94: Direct sales for credit card covered
A95: Original | B95: Personal Banking | C95: PBG - Assets | D95: Merchant Acquiring (Product & Sales) | E95: Personal Banking | F95: 174 | G95: MD Personal Banking | H95: Shehzad Hameed | I95: Elcin | K95: Sangeetha Abraham | L95: Medium | M95: =IF(T95>2017,U95,"N/A") -> NI | N95: Medium | O95: =IF(Q95="y",1,SUMIFS('Rating Grid'!$D$11:$D$34,'Rating Grid'!$B$11:$B$34,'Audit Universe -Audit Plan2 (2)'!$L$31:$L$173,'Rating Grid'!$C$11:$C$34,'Audit Universe -Audit Plan2 (2)'!$M$31:$M$173)) -> 3 | P95: Medium | Q95: N | R95: =IF(O95>S95,O95,S95) -> 3 | T95: 2020 | U95: NI | V95: =IF($T95+$R95<=2022,"2022","-") -> - | W95: =IF($T95+$R95=2023,"2023","-") -> 2023 | X95: =IF($T95+$R95=2024,"2024","-") -> - | Y95: =IF($T95+$R95=2025,"2025","-") -> - | Z95: Y | AA95: =IF($T95>2018,"Y","N") -> Y | AB95: Included in the CPF review no.2.
A96: Original | B96: Personal Banking | C96: PBG - Governance, Products & Service | D96: All Products | E96: Personal Banking | F96: 513, 523, 550 | G96: MD Personal Banking | H96: Shehzad Hameed | I96: Shibani / Shalab | K96: Sangeetha Abraham | L96: Medium | M96: =IF(T96>2017,U96,"N/A") -> Sat | N96: Medium | O96: =IF(Q96="y",1,SUMIFS('Rating Grid'!$D$11:$D$34,'Rating Grid'!$B$11:$B$34,'Audit Universe -Audit Plan2 (2)'!$L$31:$L$173,'Rating Grid'!$C$11:$C$34,'Audit Universe -Audit Plan2 (2)'!$M$31:$M$173)) -> 3 | P96: Medium | Q96: N | R96: =IF(O96>S96,O96,S96) -> 3 | T96: 2020 | U96: Sat | V96: =IF($T96+$R96<=2022,"2022","-") -> - | W96: =IF($T96+$R96=2023,"2023","-") -> 2023 | X96: =IF($T96+$R96=2024,"2024","-") -> - | Y96: =IF($T96+$R96=2025,"2025","-") -> - | Z96: Y | AA96: =IF($T96>2018,"Y","N") -> Y | AB96: CPF (LAI - WM)
A97: Original | B97: Personal Banking | C97: WM and Bancassurance - Sales | D97: WM and Bancassurance - Sales | E97: Personal Banking | F97: 159, 160, 163, 164, 534, 535, 536, 548 | G97: MD Personal Banking | H97: Shehzad Hameed | I97: Kieron Franklyn | K97: Sangeetha Abraham | L97: Medium | M97: =IF(T97>2017,U97,"N/A") -> Unrated | N97: Low | O97: =IF(Q97="y",1,SUMIFS('Rating Grid'!$D$11:$D$34,'Rating Grid'!$B$11:$B$34,'Audit Universe -Audit Plan2 (2)'!$L$31:$L$173,'Rating Grid'!$C$11:$C$34,'Audit Universe -Audit Plan2 (2)'!$M$31:$M$173)) -> 2 | P97: Medium | Q97: N | R97: =IF(O97>S97,O97,S97) -> 2 | T97: 2021 | U97: Unrated | V97: =IF($T97+$R97<=2022,"2022","-") -> - | W97: =IF($T97+$R97=2023,"2023","-") -> 2023 | X97: =IF($T97+$R97=2024,"2024","-") -> - | Y97: =IF($T97+$R97=2025,"2025","-") -> - | AA97: =IF($T97>2018,"Y","N") -> Y | AB97: WM and Bancassurance clubbed together.
A98: Original | B98: Personal Banking | C98: WM and Bancassurance - Governance, Products & Service | D98: Wealth Management & Investments - Products | E98: Personal Banking | F98: 548 | G98: MD Personal Banking | H98: Shehzad Hameed | I98: Gaurav Dixit | K98: Sangeetha Abraham | L98: Low | M98: =IF(T98>2017,U98,"N/A") -> Sat | N98: Very Low | O98: =IF(Q98="y",1,SUMIFS('Rating Grid'!$D$11:$D$34,'Rating Grid'!$B$11:$B$34,'Audit Universe -Audit Plan2 (2)'!$L$31:$L$173,'Rating Grid'!$C$11:$C$34,'Audit Universe -Audit Plan2 (2)'!$M$31:$M$173)) -> 4 | P98: Low | Q98: N | R98: =IF(O98>S98,O98,S98) -> 4 | T98: 2021 | U98: Sat | V98: =IF($T98+$R98<=2022,"2022","-") -> - | W98: =IF($T98+$R98=2023,"2023","-") -> - | X98: =IF($T98+$R98=2024,"2024","-") -> - | Y98: =IF($T98+$R98=2025,"2025","-") -> 2025 | AA98: =IF($T98>2018,"Y","N") -> Y
A99: Original | B99: RAKINSURANCE | C99: RAKNIC - Channels | D99: Branches | E99: RAKINSURANCE | G99: CEO RAKINSURANCE | H99: Ewen John Mcrobbie | I99: Jason Carey | K99: Neil Jarman | L99: Medium | M99: =IF(T99>2017,U99,"N/A") -> Unrated | N99: Medium | O99: =IF(Q99="y",1,SUMIFS('Rating Grid'!$D$11:$D$34,'Rating Grid'!$B$11:$B$34,'Audit Universe -Audit Plan2 (2)'!$L$31:$L$173,'Rating Grid'!$C$11:$C$34,'Audit Universe -Audit Plan2 (2)'!$M$31:$M$173)) -> 2 | P99: Medium | Q99: N | R99: =IF(O99>S99,O99,S99) -> 2 | T99: 2019 | U99: Unrated | V99: =IF($T99+$R99<=2022,"2022","-") -> 2022 | W99: =IF($T99+$R99=2023,"2023","-") -> - | X99: =IF($T99+$R99=2024,"2024","-") -> - | Y99: =IF($T99+$R99=2025,"2025","-") -> - | Z99: Y | AA99: =IF($T99>2018,"Y","N") -> Y
A100: Original | B100: RAKINSURANCE | C100: RAKNIC - Distribution | D100: Business Development - Distribution | E100: RAKINSURANCE | G100: CEO RAKINSURANCE | H100: Ewen John Mcrobbie | I100: Jason Carey | K100: Neil Jarman | L100: Medium | M100: =IF(T100>2017,U100,"N/A") -> NI | N100: Medium | O100: =IF(Q100="y",1,SUMIFS('Rating Grid'!$D$11:$D$34,'Rating Grid'!$B$11:$B$34,'Audit Universe -Audit Plan2 (2)'!$L$31:$L$173,'Rating Grid'!$C$11:$C$34,'Audit Universe -Audit Plan2 (2)'!$M$31:$M$173)) -> 3 | P100: Medium | Q100: N | R100: =IF(O100>S100,O100,S100) -> 3 | T100: 2020 | U100: NI | V100: =IF($T100+$R100<=2022,"2022","-") -> - | W100: =IF($T100+$R100=2023,"2023","-") -> 2023 | X100: =IF($T100+$R100=2024,"2024","-") -> - | Y100: =IF($T100+$R100=2025,"2025","-") -> - | Z100: Y | AA100: =IF($T100>2018,"Y","N") -> Y
...

Sheet AU before last cleanse
A1: Status | B1: Area | C1: Auditable Entity | D1: Auditable Sub - Entity | E1: Area | F1: SOL ID | G1: Accountable Exec. Role (N-1) | H1: Accountable Executive | I1: Business Owner (N-2) | J1: Business Owner (N-3) | K1: Audit Owner | L1: Inherent Risk | M1: Control Environment | N1: Calculated Residual Risk | O1: Original Audit Cycle | P1: Manually Adjusted Residual Risk | Q1: Regulatory | R1: Adjusted Audit Cycle | S1: Manual Override | T1: Last Audit Year | U1: Last Audit Rating | V1: Audit Plan 2022 | W1: Audit Plan 2023 | X1: Audit Plan 2024 | Y1: Audit Plan 2025 | Z1: In CY Audit Plan | AA1: Covered in Last 3 Years | AB1: Comments
A2: Original | B2: Retail Channels | C2: Branches | D2: All Branches | E2: Branches | G2: MD Business Banking | H2: Dhiraj Kunwar | I2: Saud Mohammed (Naji) | K2: Neil Jarman | L2: Medium | M2: NI | N2: Medium | O2: 1 | P2: Medium | Q2: N | R2: =IF(O2>S2,O2,S2) -> 1 | T2: 2022 | U2: NI | V2: =IF($T2+$R2<=2022,"2022","-") -> - | W2: =IF($T2+$R2=2023,"2023","-") -> 2023 | X2: =IF($T2+$R2=2024,"2024","-") -> - | Y2: =IF($T2+$R2=2025,"2025","-") -> - | AA2: =IF($T2>2018,"Y","N") -> Y
A3: Original | B3: Business Banking | C3: BBG - Liabilities | D3: BBG - Liabilities | E3: Business Banking | G3: MD Business Banking | H3: Dhiraj Kunwar | I3: Sulaiman Awan | K3: Neil Jarman | L3: Medium | M3: =IF(T3>2017,U3,"N/A") -> NI | N3: Medium | O3: =IF(Q3="y",1,SUMIFS('Rating Grid'!$D$11:$D$34,'Rating Grid'!$B$11:$B$34,'AU before last cleanse'!$L$3:$L$143,'Rating Grid'!$C$11:$C$34,'AU before last cleanse'!$M$3:$M$143)) -> 3 | P3: Medium | Q3: N | R3: =IF(O3>S3,O3,S3) -> 3 | T3: 2020 | U3: NI | V3: =IF($T3+$R3<=2022,"2022","-") -> - | W3: =IF($T3+$R3=2023,"2023","-") -> 2023 | X3: =IF($T3+$R3=2024,"2024","-") -> - | Y3: =IF($T3+$R3=2025,"2025","-") -> - | AA3: =IF($T3>2018,"Y","N") -> Y
A4: Original | B4: Business Banking | C4: BBG - National & Commercial Segment | D4: BBG - National & Commercial Segment | E4: Business Banking | G4: MD Business Banking | H4: Dhiraj Kunwar | I4: Emad Ahmed | K4: Neil Jarman | L4: Medium | M4: N/A | N4: Medium | O4: =IF(Q4="y",1,SUMIFS('Rating Grid'!$D$11:$D$34,'Rating Grid'!$B$11:$B$34,'AU before last cleanse'!$L$3:$L$143,'Rating Grid'!$C$11:$C$34,'AU before last cleanse'!$M$3:$M$143)) -> 3 | P4: Medium | Q4: N | R4: =IF(O4>S4,O4,S4) -> 3 | T4: 2021 | U4: Sat | V4: =IF($T4+$R4<=2022,"2022","-") -> - | W4: =IF($T4+$R4=2023,"2023","-") -> - | X4: =IF($T4+$R4=2024,"2024","-") -> 2024 | Y4: =IF($T4+$R4=2025,"2025","-") -> - | AA4: =IF($T4>2018,"Y","N") -> Y | AB4: Commercial Audit to be deferred on a prioritisation
A5: Original | B5: Retail Channels | C5: BBG - Customer service offices | D5: BBG - Customer service offices | E5: Retail Channels | G5: MD Business Banking | H5: Dhiraj Kunwar | I5: Sachin Brado | K5: Neil Jarman | L5: Medium | M5: =IF(T5>2017,U5,"N/A") -> N/A | N5: Low | O5: =IF(Q5="y",1,SUMIFS('Rating Grid'!$D$11:$D$34,'Rating Grid'!$B$11:$B$34,'AU before last cleanse'!$L$3:$L$143,'Rating Grid'!$C$11:$C$34,'AU before last cleanse'!$M$3:$M$143)) -> 3 | P5: Low | Q5: N | R5: =IF(O5>S5,O5,S5) -> 3 | T5: 2010 | U5: - | V5: =IF($T5+$R5<=2022,"2022","-") -> 2022 | W5: =IF($T5+$R5=2023,"2023","-") -> - | X5: =IF($T5+$R5=2024,"2024","-") -> - | Y5: =IF($T5+$R5=2025,"2025","-") -> -
A6: Original | B6: Business Banking | C6: BBG - Products & Value Proposition | D6: BBG - Products & Value Proposition | E6: Business Banking | G6: MD Business Banking | H6: Dhiraj Kunwar | I6: Archana Pavithran | K6: Neil Jarman | L6: Medium | M6: =IF(T6>2017,U6,"N/A") -> N/A | N6: Medium | O6: =IF(Q6="y",1,SUMIFS('Rating Grid'!$D$11:$D$34,'Rating Grid'!$B$11:$B$34,'AU before last cleanse'!$L$3:$L$143,'Rating Grid'!$C$11:$C$34,'AU before last cleanse'!$M$3:$M$143)) -> 3 | P6: Medium | Q6: N | R6: =IF(O6>S6,O6,S6) -> 3 | U6: - | V6: =IF($T6+$R6<=2022,"2022","-") -> 2022 | W6: =IF($T6+$R6=2023,"2023","-") -> - | X6: =IF($T6+$R6=2024,"2024","-") -> - | Y6: =IF($T6+$R6=2025,"2025","-") -> - | Z6: Y | AB6: CPF
A7: Original | B7: Business Banking | C7: BBG - Distribution | D7: BBG - Distribution | E7: Business Banking | G7: MD Business Banking | H7: Dhiraj Kunwar | I7: Sachin Brado | K7: Neil Jarman | L7: High | M7: Sat | N7: Medium | O7: 3 | P7: Medium | Q7: N | R7: =IF(O7>S7,O7,S7) -> 3 | T7: 2021 | U7: NI | V7: =IF($T7+$R7<=2022,"2022","-") -> - | W7: =IF($T7+$R7=2023,"2023","-") -> - | X7: =IF($T7+$R7=2024,"2024","-") -> 2024 | Y7: =IF($T7+$R7=2025,"2025","-") -> - | AA7: =IF($T7>2018,"Y","N") -> Y | AB7: Product-related E2E process audit
A8: Original | B8: Business Banking | C8: BBG - Governance | D8: BBG - Governance | E8: Business Banking | G8: MD Business Banking | H8: Dhiraj Kunwar | I8: Neha Agarwal | K8: Neil Jarman | L8: High | M8: Sat | N8: Medium | O8: 3 | P8: High | Q8: N | R8: 1 | T8: 2021 | U8: Sat | V8: =IF($T8+$R8<=2022,"2022","-") -> 2022 | W8: =IF($T8+$R8=2023,"2023","-") -> - | X8: =IF($T8+$R8=2024,"2024","-") -> - | Y8: =IF($T8+$R8=2025,"2025","-") -> - | Z8: Y | AA8: =IF($T8>2018,"Y","N") -> Y | AB8: Rating driven by Onboarding responsibilities,
A9: Original | B9: Business Banking | C9: BBG - Trade & Working Capital | D9: BBG - Trade & Working Capital | E9: Business Banking | G9: MD Business Banking | H9: Dhiraj Kunwar | I9: Lalatendu Mohanty | K9: Neil Jarman | L9: Medium | M9: N/A | N9: Medium | O9: 3 | P9: Medium | Q9: N | R9: =IF(O9>S9,O9,S9) -> 3 | T9: 2021 | U9: NI | V9: =IF($T9+$R9<=2022,"2022","-") -> - | W9: 2023 | X9: - | Y9: =IF($T9+$R9=2025,"2025","-") -> - | AA9: N | AB9: TF Operations is in CY audit plan but front office deferred due to strategy and proposition change. Move to 2024
A10: Addition | B10: Business Banking | C10: Business Banking Projects | D10: Business Banking Projects | E10: Business Banking | G10: MD Business Banking | H10: Dhiraj Kunwar | I10: Ashutosh Ashish | AB10: New Additions on Organizational Structure
A11: Addition | B11: Business Banking | C11: Business Banking Value Proposition | D11: Business Banking Value Proposition | E11: Business Banking | G11: MD Business Banking | H11: Dhiraj Kunwar | I11: Thomas Baxendale | AB11: New Additions on Organizational Structure
A12: Original | B12: Corporate Functions | C12: Corporate Governance | D12: CEO's Office (Management Committees, Oversight, Strategy, Corp Communication) | E12: Corporate Functions | F12: 702 | G12: CEO | H12: Jaffar Nini / Raheel Ahmed | I12: Amel Berhouma | K12: Moez Sassi | L12: Medium | M12: =IF(T12>2017,U12,"N/A") -> Sat | N12: Medium | O12: =IF(Q12="y",1,SUMIFS('Rating Grid'!$D$11:$D$34,'Rating Grid'!$B$11:$B$34,'AU before last cleanse'!$L$3:$L$143,'Rating Grid'!$C$11:$C$34,'AU before last cleanse'!$M$3:$M$143)) -> 3 | P12: Medium | Q12: N | R12: =IF(O12>S12,O12,S12) -> 3 | T12: 2018 | U12: Sat | V12: =IF($T12+$R12<=2022,"2022","-") -> 2022 | W12: =IF($T12+$R12=2023,"2023","-") -> - | X12: =IF($T12+$R12=2024,"2024","-") -> - | Y12: =IF($T12+$R12=2025,"2025","-") -> - | Z12: Y | AA12: =IF($T12>2018,"Y","N") -> N | AB12: Action plan till 2022, strategy due for revision
A13: Original | B13: Corporate Functions | C13: Corporate Governance | D13: Company Secretary (Governance, Board and Board Committees) | E13: Corporate Functions | G13: Group General Counsel | H13: Ghalia Bushnaq | I13: Imad Khalil | K13: Moez Sassi | L13: Medium | M13: =IF(T13>2017,U13,"N/A") -> Sat | N13: Medium | O13: =IF(Q13="y",1,SUMIFS('Rating Grid'!$D$11:$D$34,'Rating Grid'!$B$11:$B$34,'AU before last cleanse'!$L$3:$L$143,'Rating Grid'!$C$11:$C$34,'AU before last cleanse'!$M$3:$M$143)) -> 3 | P13: Medium | Q13: N | R13: =IF(O13>S13,O13,S13) -> 3 | T13: 2018 | U13: Sat | V13: =IF($T13+$R13<=2022,"2022","-") -> 2022 | W13: =IF($T13+$R13=2023,"2023","-") -> - | X13: =IF($T13+$R13=2024,"2024","-") -> - | Y13: =IF($T13+$R13=2025,"2025","-") -> -
A14: Original | B14: Corporate Functions | C14: Investor Relations & Corp Comms | D14: Corporate Communications | E14: Corporate Functions | F14: 702 | G14: Group General Counsel | H14: Ghalia Bushnaq | I14: Imad Khalil | K14: Moez Sassi | L14: Low | M14: =IF(T14>2017,U14,"N/A") -> N/A | N14: Medium | O14: =IF(Q14="y",1,SUMIFS('Rating Grid'!$D$11:$D$34,'Rating Grid'!$B$11:$B$34,'AU before last cleanse'!$L$3:$L$143,'Rating Grid'!$C$11:$C$34,'AU before last cleanse'!$M$3:$M$143)) -> 4 | P14: Low | Q14: N | R14: =IF(O14>S14,O14,S14) -> 4 | U14: - | V14: =IF($T14+$R14<=2022,"2022","-") -> 2022 | W14: =IF($T14+$R14=2023,"2023","-") -> - | X14: =IF($T14+$R14=2024,"2024","-") -> - | Y14: =IF($T14+$R14=2025,"2025","-") -> -
A15: Original | B15: Corporate Functions | C15: HR | D15: Human Resources (Emiratisation & BRF Reporting) | E15: Corporate Functions | F15: 522, 703, 715 | G15: Group General Counsel | H15: Ahmed Yousef | I15: Manal Alharmoodi | K15: Sangeetha Abraham | L15: Medium | M15: =IF(T15>2017,U15,"N/A") -> Sat | N15: Low | O15: =IF(Q15="y",1,SUMIFS('Rating Grid'!$D$11:$D$34,'Rating Grid'!$B$11:$B$34,'AU before last cleanse'!$L$3:$L$143,'Rating Grid'!$C$11:$C$34,'AU before last cleanse'!$M$3:$M$143)) -> 3 | P15: Medium | Q15: N | R15: =IF(O15>S15,O15,S15) -> 3 | T15: 2021 | U15: Sat | V15: =IF($T15+$R15<=2022,"2022","-") -> - | W15: =IF($T15+$R15=2023,"2023","-") -> - | X15: =IF($T15+$R15=2024,"2024","-") -> 2024 | Y15: =IF($T15+$R15=2025,"2025","-") -> - | AA15: =IF($T15>2018,"Y","N") -> Y | AB15: Emiratisation and BRF covered in 2019. The rating is changed from NI to SAT
A16: Original | B16: Corporate Functions | C16: HR | D16: Human Resources (Learning & Development) | E16: Corporate Functions | G16: Group General Counsel | H16: Ahmed Yousef | I16: Sultan Ali / Wandusjka Jennison | K16: Sangeetha Abraham | L16: Medium | M16: =IF(T16>2017,U16,"N/A") -> N/A | N16: Low | O16: =IF(Q16="y",1,SUMIFS('Rating Grid'!$D$11:$D$34,'Rating Grid'!$B$11:$B$34,'AU before last cleanse'!$L$3:$L$143,'Rating Grid'!$C$11:$C$34,'AU before last cleanse'!$M$3:$M$143)) -> 3 | P16: Medium | Q16: N | R16: =IF(O16>S16,O16,S16) -> 3 | T16: 2015 | U16: Sat | V16: =IF($T16+$R16<=2022,"2022","-") -> 2022 | W16: =IF($T16+$R16=2023,"2023","-") -> - | X16: =IF($T16+$R16=2024,"2024","-") -> - | Y16: =IF($T16+$R16=2025,"2025","-") -> - | AA16: =IF($T16>2018,"Y","N") -> N
A17: Original | B17: Corporate Functions | C17: HR | D17: Human Resources (Organisational Effectiveness & Business Partnership) | E17: Corporate Functions | F17: 522, 703, 715 | G17: Group General Counsel | H17: Ahmed Yousef | I17: Kiran Rayaroth / Sonal Hingorani | K17: Sangeetha Abraham | L17: Medium | M17: =IF(T17>2017,U17,"N/A") -> NI | N17: Low | O17: =IF(Q17="y",1,SUMIFS('Rating Grid'!$D$11:$D$34,'Rating Grid'!$B$11:$B$34,'AU before last cleanse'!$L$3:$L$143,'Rating Grid'!$C$11:$C$34,'AU before last cleanse'!$M$3:$M$143)) -> 3 | P17: Medium | Q17: N | R17: =IF(O17>S17,O17,S17) -> 3 | T17: 2021 | U17: NI | V17: =IF($T17+$R17<=2022,"2022","-") -> - | W17: =IF($T17+$R17=2023,"2023","-") -> - | X17: =IF($T17+$R17=2024,"2024","-") -> 2024 | Y17: =IF($T17+$R17=2025,"2025","-") -> - | AA17: =IF($T17>2018,"Y","N") -> Y
A18: Original | B18: Corporate Functions | C18: HR | D18: Human Resources (Reward Strategy, Remuneration, Incentives) | E18: Corporate Functions | F18: 522, 703, 715 | G18: Group General Counsel | H18: Ahmed Yousef | I18: Parvesh Tohan | K18: Sangeetha Abraham | L18: Medium | M18: =IF(T18>2017,U18,"N/A") -> NI | N18: Low | O18: =IF(Q18="y",1,SUMIFS('Rating Grid'!$D$11:$D$34,'Rating Grid'!$B$11:$B$34,'AU before last cleanse'!$L$3:$L$143,'Rating Grid'!$C$11:$C$34,'AU before last cleanse'!$M$3:$M$143)) -> 3 | P18: Medium | Q18: N | R18: =IF(O18>S18,O18,S18) -> 3 | T18: 2021 | U18: NI | V18: =IF($T18+$R18<=2022,"2022","-") -> - | W18: =IF($T18+$R18=2023,"2023","-") -> - | X18: =IF($T18+$R18=2024,"2024","-") -> 2024 | Y18: =IF($T18+$R18=2025,"2025","-") -> - | AA18: =IF($T18>2018,"Y","N") -> Y
A19: Original | B19: Corporate Functions | C19: HR | D19: Human Resources (Talent Acquisition & HR Services) | E19: Corporate Functions | F19: 522, 703, 715 | G19: Group General Counsel | H19: Ahmed Yousef | I19: Ian Hughes | K19: Sangeetha Abraham | L19: Medium | M19: =IF(T19>2017,U19,"N/A") -> NI | N19: Low | O19: =IF(Q19="y",1,SUMIFS('Rating Grid'!$D$11:$D$34,'Rating Grid'!$B$11:$B$34,'AU before last cleanse'!$L$3:$L$143,'Rating Grid'!$C$11:$C$34,'AU before last cleanse'!$M$3:$M$143)) -> 3 | P19: Medium | Q19: N | R19: =IF(O19>S19,O19,S19) -> 3 | T19: 2021 | U19: NI | V19: =IF($T19+$R19<=2022,"2022","-") -> - | W19: =IF($T19+$R19=2023,"2023","-") -> - | X19: =IF($T19+$R19=2024,"2024","-") -> 2024 | Y19: =IF($T19+$R19=2025,"2025","-") -> - | AA19: =IF($T19>2018,"Y","N") -> Y
A20: Original | B20: Subsidiaries | C20: BOSS | D20: BOSS | E20: Subsidiaries | G20: Group General Counsel | H20: Ahmed Yousef | I20: Ian Hughes | K20: Sangeetha Abraham | L20: Very Low | M20: =IF(T20>2017,U20,"N/A") -> NI | N20: Low | O20: =IF(Q20="y",1,SUMIFS('Rating Grid'!$D$11:$D$34,'Rating Grid'!$B$11:$B$34,'AU before last cleanse'!$L$3:$L$143,'Rating Grid'!$C$11:$C$34,'AU before last cleanse'!$M$3:$M$143)) -> 0 | P20: Low | Q20: N | R20: =IF(O20>S20,O20,S20) -> 0 | T20: 2021 | U20: NI | V20: =IF($T20+$R20<=2022,"2022","-") -> 2022 | W20: =IF($T20+$R20=2023,"2023","-") -> - | X20: =IF($T20+$R20=2024,"2024","-") -> - | Y20: =IF($T20+$R20=2025,"2025","-") -> - | AA20: =IF($T20>2018,"Y","N") -> Y
A21: Original | B21: Subsidiaries | C21: RAKTech FZCo | D21: RAKTech FZCo | E21: Subsidiaries | G21: Group General Counsel | H21: Ahmed Yousef | I21: Ian Hughes | K21: Sangeetha Abraham | L21: Very Low | M21: =IF(T21>2017,U21,"N/A") -> NI | N21: Low | O21: =IF(Q21="y",1,SUMIFS('Rating Grid'!$D$11:$D$34,'Rating Grid'!$B$11:$B$34,'AU before last cleanse'!$L$3:$L$143,'Rating Grid'!$C$11:$C$34,'AU before last cleanse'!$M$3:$M$143)) -> 0 | P21: Low | Q21: N | R21: =IF(O21>S21,O21,S21) -> 0 | T21: 2021 | U21: NI | V21: =IF($T21+$R21<=2022,"2022","-") -> 2022 | W21: =IF($T21+$R21=2023,"2023","-") -> - | X21: =IF($T21+$R21=2024,"2024","-") -> - | Y21: =IF($T21+$R21=2025,"2025","-") -> - | AA21: =IF($T21>2018,"Y","N") -> Y
A22: Original | B22: Corporate Functions | C22: Culture | D22: Culture | E22: Corporate Functions | G22: Group General Counsel | H22: Ahmed Yousef | I22: Ahmed Yousef | K22: Moez Sassi | L22: Medium | M22: =IF(T22>2017,U22,"N/A") -> N/A | N22: Medium | O22: =IF(Q22="y",1,SUMIFS('Rating Grid'!$D$11:$D$34,'Rating Grid'!$B$11:$B$34,'AU before last cleanse'!$L$3:$L$143,'Rating Grid'!$C$11:$C$34,'AU before last cleanse'!$M$3:$M$143)) -> 3 | P22: Medium | Q22: N | R22: =IF(O22>S22,O22,S22) -> 3 | T22: 2010 | U22: - | V22: =IF($T22+$R22<=2022,"2022","-") -> 2022 | W22: =IF($T22+$R22=2023,"2023","-") -> - | X22: =IF($T22+$R22=2024,"2024","-") -> - | Y22: =IF($T22+$R22=2025,"2025","-") -> -
A23: Original | B23: Corporate Functions | C23: Legal | D23: Legal - Advisory | E23: Corporate Functions | F23: 736 | G23: Group General Counsel | H23: Ghalia Bushnaq | I23: Raunaq Baid | K23: Moez Sassi | L23: Medium | M23: =IF(T23>2017,U23,"N/A") -> Sat | N23: Medium | O23: =IF(Q23="y",1,SUMIFS('Rating Grid'!$D$11:$D$34,'Rating Grid'!$B$11:$B$34,'AU before last cleanse'!$L$3:$L$143,'Rating Grid'!$C$11:$C$34,'AU before last cleanse'!$M$3:$M$143)) -> 3 | P23: Medium | Q23: N | R23: =IF(O23>S23,O23,S23) -> 3 | T23: 2021 | U23: Sat | V23: =IF($T23+$R23<=2022,"2022","-") -> - | W23: =IF($T23+$R23=2023,"2023","-") -> - | X23: =IF($T23+$R23=2024,"2024","-") -> 2024 | Y23: =IF($T23+$R23=2025,"2025","-") -> - | AA23: =IF($T23>2018,"Y","N") -> Y
A24: Original | B24: Corporate Functions | C24: Legal | D24: Legal - Litigation | E24: Corporate Functions | G24: Group General Counsel | H24: Ghalia Bushnaq | I24: Abdulrahman Khesro | K24: Moez Sassi | L24: Medium | M24: =IF(T24>2017,U24,"N/A") -> Sat | N24: Medium | O24: =IF(Q24="y",1,SUMIFS('Rating Grid'!$D$11:$D$34,'Rating Grid'!$B$11:$B$34,'AU before last cleanse'!$L$3:$L$143,'Rating Grid'!$C$11:$C$34,'AU before last cleanse'!$M$3:$M$143)) -> 3 | P24: Medium | Q24: N | R24: =IF(O24>S24,O24,S24) -> 3 | T24: 2021 | U24: Sat | V24: =IF($T24+$R24<=2022,"2022","-") -> - | W24: =IF($T24+$R24=2023,"2023","-") -> - | X24: =IF($T24+$R24=2024,"2024","-") -> 2024 | Y24: =IF($T24+$R24=2025,"2025","-") -> - | AA24: Y
A25: Original | B25: Corporate Functions | C25: Marketing | D25: Marketing | E25: Corporate Functions | F25: 541 | G25: Chief Customer Officer | H25: Dongjun Choi | I25: Gary Koeb | K25: Sangeetha Abraham | L25: Medium | M25: =IF(T25>2017,U25,"N/A") -> NI | N25: Medium | O25: =IF(Q25="y",1,SUMIFS('Rating Grid'!$D$11:$D$34,'Rating Grid'!$B$11:$B$34,'AU before last cleanse'!$L$3:$L$143,'Rating Grid'!$C$11:$C$34,'AU before last cleanse'!$M$3:$M$143)) -> 3 | P25: Medium | Q25: N | R25: =IF(O25>S25,O25,S25) -> 4 | S25: 4 | T25: 2019 | U25: NI | V25: =IF($T25+$R25<=2022,"2022","-") -> - | W25: =IF($T25+$R25=2023,"2023","-") -> 2023 | X25: =IF($T25+$R25=2024,"2024","-") -> - | Y25: =IF($T25+$R25=2025,"2025","-") -> - | Z25: y | AA25: =IF($T25>2018,"Y","N") -> Y | AB25: Manual override to 2023.
A26: Original | B26: Corporate Functions | C26: Service Excellence | D26: Customer Excellence & Protection | E26: Corporate Functions | F26: 508, 560, 726 | G26: Chief Customer Officer | H26: Dongjun Choi | I26: Lina Yahya / Anish Mohandas | K26: Sangeetha Abraham | L26: Medium | M26: =IF(T26>2017,U26,"N/A") -> NI | N26: Medium | O26: =IF(Q26="y",1,SUMIFS('Rating Grid'!$D$11:$D$34,'Rating Grid'!$B$11:$B$34,'AU before last cleanse'!$L$3:$L$143,'Rating Grid'!$C$11:$C$34,'AU before last cleanse'!$M$3:$M$143)) -> 3 | P26: Medium | Q26: N | R26: =IF(O26>S26,O26,S26) -> 3 | T26: 2019 | U26: NI | V26: =IF($T26+$R26<=2022,"2022","-") -> 2022 | W26: =IF($T26+$R26=2023,"2023","-") -> - | X26: =IF($T26+$R26=2024,"2024","-") -> - | Y26: =IF($T26+$R26=2025,"2025","-") -> - | Z26: Y | AA26: =IF($T26>2018,"Y","N") -> Y | AB26: Consumer Protection Framework (2022 - 5 audits covering implementation programme)
A27: Original | B27: Corporate Functions | C27: Strategic Planning & Initiatives | D27: Strategy | E27: Corporate Functions | F27: 702 | G27: Chief Customer Officer | H27: Dongjun Choi | I27: Gregory Thomas | K27: Moez Sassi | L27: Medium | M27: =IF(T27>2017,U27,"N/A") -> Unrated | N27: High | O27: =IF(Q27="y",1,SUMIFS('Rating Grid'!$D$11:$D$34,'Rating Grid'!$B$11:$B$34,'AU before last cleanse'!$L$3:$L$143,'Rating Grid'!$C$11:$C$34,'AU before last cleanse'!$M$3:$M$143)) -> 2 | P27: High | Q27: N | R27: =IF(O27>S27,O27,S27) -> 2 | T27: 2020 | U27: Unrated | V27: =IF($T27+$R27<=2022,"2022","-") -> 2022 | W27: =IF($T27+$R27=2023,"2023","-") -> - | X27: =IF($T27+$R27=2024,"2024","-") -> - | Y27: =IF($T27+$R27=2025,"2025","-") -> - | Z27: Y | AA27: =IF($T27>2018,"Y","N") -> Y
A28: Addition | C28: Digital Transformation & Enterprise PMO | D28: Digital Transformation & Enterprise PMO | G28: Chief Customer Officer | H28: Dongjun Choi | I28: Tristan Brandt
A29: Original | B29: Personal Banking | C29: Business Analytics | D29: Business Performance & Strategic Analytics | E29: Personal Banking | F29: 513 | G29: MD Personal Banking / Chief Customer Officer | H29: Dongjun Choi / Shehzad Hameed | I29: Ramzi Aissa | K29: Sangeetha Abraham | L29: Medium | M29: =IF(T29>2017,U29,"N/A") -> Sat | N29: Low | O29: =IF(Q29="y",1,SUMIFS('Rating Grid'!$D$11:$D$34,'Rating Grid'!$B$11:$B$34,'AU before last cleanse'!$L$3:$L$143,'Rating Grid'!$C$11:$C$34,'AU before last cleanse'!$M$3:$M$143)) -> 3 | P29: Low | Q29: N | R29: =IF(O29>S29,O29,S29) -> 3 | T29: 2020 | U29: Sat | V29: =IF($T29+$R29<=2022,"2022","-") -> - | W29: =IF($T29+$R29=2023,"2023","-") -> 2023 | X29: =IF($T29+$R29=2024,"2024","-") -> - | Y29: =IF($T29+$R29=2025,"2025","-") -> - | AA29: =IF($T29>2018,"Y","N") -> Y
A30: Original | B30: Corporate Functions | C30: Project Management | D30: Project Management | E30: Operations | G30: CTO | H30: Saket | I30: James | K30: Neil Jarman | L30: High | M30: =IF(T30>2017,U30,"N/A") -> Unrated | N30: Medium | O30: =IF(Q30="y",1,SUMIFS('Rating Grid'!$D$11:$D$34,'Rating Grid'!$B$11:$B$34,'AU before last cleanse'!$L$3:$L$143,'Rating Grid'!$C$11:$C$34,'AU before last cleanse'!$M$3:$M$143)) -> 1 | P30: Medium | Q30: N | R30: =IF(O30>S30,O30,S30) -> 3 | S30: 3 | T30: 2021 | U30: Unrated | V30: =IF($T30+$R30<=2022,"2022","-") -> - | W30: =IF($T30+$R30=2023,"2023","-") -> - | X30: =IF($T30+$R30=2024,"2024","-") -> 2024 | Y30: =IF($T30+$R30=2025,"2025","-") -> - | Z30: Y | AA30: =IF($T30>2018,"Y","N") -> Y | AB30: Under consideration to be conducted in 2022 - Q3/4
A31: Original | B31: Credit | C31: WBG & FIG Underwriting | D31: Wholesale Banking, Financial Institutions Credit & BBG Commercial | E31: Credit | G31: Chief Credit Officer | H31: Mahadevan Radhakanthan | I31: Pradeep Nehra | K31: Neil Jarman | L31: Medium | M31: =IF(T31>2017,U31,"N/A") -> NI | N31: Medium | O31: =IF(Q31="y",1,SUMIFS('Rating Grid'!$D$11:$D$34,'Rating Grid'!$B$11:$B$34,'AU before last cleanse'!$L$3:$L$143,'Rating Grid'!$C$11:$C$34,'AU before last cleanse'!$M$3:$M$143)) -> 3 | P31: Medium | Q31: N | R31: =IF(O31>S31,O31,S31) -> 3 | T31: 2019 | U31: NI | V31: =IF($T31+$R31<=2022,"2022","-") -> 2022 | W31: =IF($T31+$R31=2023,"2023","-") -> - | X31: =IF($T31+$R31=2024,"2024","-") -> - | Y31: =IF($T31+$R31=2025,"2025","-") -> - | Z31: Y | AA31: =IF($T31>2018,"Y","N") -> Y | AB31: Syndicated Lending - Q1
A32: Original | B32: Credit | C32: RBG - Underwriting | D32: Underwriting - (All Retail Products) | E32: Credit | F32: 165, 166, 570 | G32: Chief Credit Officer | H32: Mahadevan Radhakanthan | I32: Vinay Nair | K32: Sangeetha Abraham | L32: Medium | M32: =IF(T32>2017,U32,"N/A") -> Sat | N32: Low | O32: =IF(Q32="y",1,SUMIFS('Rating Grid'!$D$11:$D$34,'Rating Grid'!$B$11:$B$34,'AU before last cleanse'!$L$3:$L$143,'Rating Grid'!$C$11:$C$34,'AU before last cleanse'!$M$3:$M$143)) -> 3 | P32: Low | Q32: N | R32: =IF(O32>S32,O32,S32) -> 3 | T32: 2020 | U32: Sat | V32: =IF($T32+$R32<=2022,"2022","-") -> - | W32: =IF($T32+$R32=2023,"2023","-") -> 2023 | X32: =IF($T32+$R32=2024,"2024","-") -> - | Y32: =IF($T32+$R32=2025,"2025","-") -> - | AA32: =IF($T32>2018,"Y","N") -> Y | AB32: Covered in PL and Mortgages
A33: Original | B33: Credit | C33: BBG - Underwriting | D33: Business Banking Credit | E33: Credit | G33: Chief Credit Officer | H33: Mahadevan Radhakanthan | I33: Vinay Ambekar | K33: Neil Jarman | L33: Medium | M33: =IF(T33>2017,U33,"N/A") -> Sat | N33: Low | O33: =IF(Q33="y",1,SUMIFS('Rating Grid'!$D$11:$D$34,'Rating Grid'!$B$11:$B$34,'AU before last cleanse'!$L$3:$L$143,'Rating Grid'!$C$11:$C$34,'AU before last cleanse'!$M$3:$M$143)) -> 3 | P33: Low | Q33: N | R33: =IF(O33>S33,O33,S33) -> 3 | T33: 2021 | U33: Sat | V33: =IF($T33+$R33<=2022,"2022","-") -> - | W33: =IF($T33+$R33=2023,"2023","-") -> - | X33: =IF($T33+$R33=2024,"2024","-") -> 2024 | Y33: =IF($T33+$R33=2025,"2025","-") -> - | AA33: =IF($T33>2018,"Y","N") -> Y
A34: Original | B34: Credit | C34: BBG - Collections | D34: BBG Collections - All Products | E34: Credit | G34: Chief Credit Officer | H34: Mahadevan Radhakanthan | I34: Sunil Chacko | J34: Prashant | K34: Neil Jarman | L34: Medium | M34: =IF(T34>2017,U34,"N/A") -> NI | N34: Medium | O34: =IF(Q34="y",1,SUMIFS('Rating Grid'!$D$11:$D$34,'Rating Grid'!$B$11:$B$34,'AU before last cleanse'!$L$3:$L$143,'Rating Grid'!$C$11:$C$34,'AU before last cleanse'!$M$3:$M$143)) -> 3 | P34: Low | Q34: N | R34: =IF(O34>S34,O34,S34) -> 3 | T34: 2021 | U34: NI | V34: =IF($T34+$R34<=2022,"2022","-") -> - | W34: =IF($T34+$R34=2023,"2023","-") -> - | X34: =IF($T34+$R34=2024,"2024","-") -> 2024 | Y34: =IF($T34+$R34=2025,"2025","-") -> - | AA34: =IF($T34>2018,"Y","N") -> Y
A35: Original | B35: Credit | C35: WBG & FIG Collections | D35: WBG & FIG Collections (All Products) | E35: Credit | G35: Chief Credit Officer | H35: Mahadevan Radhakanthan | I35: Sunil Chacko | J35: Prashant | K35: Neil Jarman | L35: Medium | M35: =IF(T35>2017,U35,"N/A") -> N/A | N35: Medium | O35: =IF(Q35="y",1,SUMIFS('Rating Grid'!$D$11:$D$34,'Rating Grid'!$B$11:$B$34,'AU before last cleanse'!$L$3:$L$143,'Rating Grid'!$C$11:$C$34,'AU before last cleanse'!$M$3:$M$143)) -> 3 | P35: Medium | Q35: N | R35: =IF(O35>S35,O35,S35) -> 3 | T35: 2010 | U35: - | V35: =IF($T35+$R35<=2022,"2022","-") -> 2022 | W35: =IF($T35+$R35=2023,"2023","-") -> - | X35: =IF($T35+$R35=2024,"2024","-") -> - | Y35: =IF($T35+$R35=2025,"2025","-") -> -
A36: Original | B36: Credit | C36: WM - Underwriting | D36: Wealth Management & Investments - Underwriting (Credit) | E36: Credit | F36: 164 | G36: Chief Credit Officer | H36: Mahadevan Radhakanthan | I36: Vinay Nair | K36: Sangeetha Abraham | L36: Low | M36: =IF(T36>2017,U36,"N/A") -> Sat | N36: Low | O36: =IF(Q36="y",1,SUMIFS('Rating Grid'!$D$11:$D$34,'Rating Grid'!$B$11:$B$34,'AU before last cleanse'!$L$3:$L$143,'Rating Grid'!$C$11:$C$34,'AU before last cleanse'!$M$3:$M$143)) -> 4 | P36: Low | Q36: N | R36: =IF(O36>S36,O36,S36) -> 4 | T36: 2018 | U36: Sat | V36: =IF($T36+$R36<=2022,"2022","-") -> 2022 | W36: =IF($T36+$R36=2023,"2023","-") -> - | X36: =IF($T36+$R36=2024,"2024","-") -> - | Y36: =IF($T36+$R36=2025,"2025","-") -> - | Z36: Y | AA36: =IF($T36>2018,"Y","N") -> N | AB36: LAI
A37: Original | B37: Finance | C37: Financial Control | D37: Budgeting & Forecasting | E37: Finance | F37: 701 | G37: CFO | H37: Jaffar Nini | I37: Manohar Bhoir/ Asim Junaidi | K37: Moez Sassi | L37: Medium | M37: =IF(T37>2017,U37,"N/A") -> Sat | N37: Medium | O37: =IF(Q37="y",1,SUMIFS('Rating Grid'!$D$11:$D$34,'Rating Grid'!$B$11:$B$34,'AU before last cleanse'!$L$3:$L$143,'Rating Grid'!$C$11:$C$34,'AU before last cleanse'!$M$3:$M$143)) -> 3 | P37: Medium | Q37: N | R37: =IF(O37>S37,O37,S37) -> 3 | T37: 2021 | U37: Sat | V37: =IF($T37+$R37<=2022,"2022","-") -> - | W37: =IF($T37+$R37=2023,"2023","-") -> - | X37: =IF($T37+$R37=2024,"2024","-") -> 2024 | Y37: =IF($T37+$R37=2025,"2025","-") -> - | AA37: =IF($T37>2018,"Y","N") -> Y
A38: Original | B38: Finance | C38: Financial Control | D38: Financial Accounting, Reporting & Controls (incl. provisions) | E38: Finance | F38: 701 | G38: CFO | H38: Jaffar Nini | I38: Manohar Bhoir/ Gireeshan | K38: Moez Sassi | L38: Medium | M38: =IF(T38>2017,U38,"N/A") -> Sat | N38: Medium | O38: =IF(Q38="y",1,SUMIFS('Rating Grid'!$D$11:$D$34,'Rating Grid'!$B$11:$B$34,'AU before last cleanse'!$L$3:$L$143,'Rating Grid'!$C$11:$C$34,'AU before last cleanse'!$M$3:$M$143)) -> 3 | P38: Medium | Q38: N | R38: =IF(O38>S38,O38,S38) -> 3 | T38: 2021 | U38: Sat | V38: =IF($T38+$R38<=2022,"2022","-") -> - | W38: =IF($T38+$R38=2023,"2023","-") -> - | X38: =IF($T38+$R38=2024,"2024","-") -> 2024 | Y38: =IF($T38+$R38=2025,"2025","-") -> - | AA38: =IF($T38>2018,"Y","N") -> Y
A39: Original | B39: Risk | C39: WBG - Credit Provisions (WBG, FIG & Treasury) | D39: Provisions - All Products | E39: Risk | G39: Chief Risk Officer | H39: Farhan Mahmoud | K39: Neil Jarman | L39: Medium | M39: =IF(T39>2017,U39,"N/A") -> NI | N39: Medium | O39: =IF(Q39="y",1,SUMIFS('Rating Grid'!$D$11:$D$34,'Rating Grid'!$B$11:$B$34,'AU before last cleanse'!$L$3:$L$143,'Rating Grid'!$C$11:$C$34,'AU before last cleanse'!$M$3:$M$143)) -> 1 | P39: Medium | Q39: Y | R39: =IF(O39>S39,O39,S39) -> 1 | T39: 2021 | U39: NI | V39: =IF($T39+$R39<=2022,"2022","-") -> 2022 | W39: =IF($T39+$R39=2023,"2023","-") -> - | X39: =IF($T39+$R39=2024,"2024","-") -> - | Y39: =IF($T39+$R39=2025,"2025","-") -> - | AA39: =IF($T39>2018,"Y","N") -> Y | AB39: Risk and Finance
A40: Original | B40: Finance | C40: Financial Control | D40: Management Reporting | E40: Finance | F40: 701 | G40: CFO | H40: Jaffar Nini | I40: Mridul Baberwal | J40: Husain Jawad | K40: Moez Sassi | L40: Medium | M40: =IF(T40>2017,U40,"N/A") -> Sat | N40: Medium | O40: =IF(Q40="y",1,SUMIFS('Rating Grid'!$D$11:$D$34,'Rating Grid'!$B$11:$B$34,'AU before last cleanse'!$L$3:$L$143,'Rating Grid'!$C$11:$C$34,'AU before last cleanse'!$M$3:$M$143)) -> 3 | P40: Medium | Q40: N | R40: =IF(O40>S40,O40,S40) -> 3 | T40: 2021 | U40: Sat | V40: =IF($T40+$R40<=2022,"2022","-") -> - | W40: =IF($T40+$R40=2023,"2023","-") -> - | X40: =IF($T40+$R40=2024,"2024","-") -> 2024 | Y40: =IF($T40+$R40=2025,"2025","-") -> - | AA40: =IF($T40>2018,"Y","N") -> Y
A41: Original | B41: Finance | C41: Regulatory Reporting | D41: Regulatory Reporting (BRFs) | E41: Finance | F41: 701 | G41: CFO | H41: Jaffar Nini | I41: Manohar Bhoir | K41: Moez Sassi | L41: Medium | M41: =IF(T41>2017,U41,"N/A") -> Sat | N41: Low | O41: =IF(Q41="y",1,SUMIFS('Rating Grid'!$D$11:$D$34,'Rating Grid'!$B$11:$B$34,'AU before last cleanse'!$L$3:$L$143,'Rating Grid'!$C$11:$C$34,'AU before last cleanse'!$M$3:$M$143)) -> 3 | P41: Low | Q41: N | R41: =IF(O41>S41,O41,S41) -> 3 | T41: 2021 | U41: Sat | V41: =IF($T41+$R41<=2022,"2022","-") -> - | W41: =IF($T41+$R41=2023,"2023","-") -> - | X41: =IF($T41+$R41=2024,"2024","-") -> 2024 | Y41: =IF($T41+$R41=2025,"2025","-") -> - | AA41: =IF($T41>2018,"Y","N") -> Y
A42: Original | B42: Finance | C42: Financial Control | D42: Taxation | E42: Finance | F42: 701 | G42: CFO | H42: Jaffar Nini | I42: Manohar Bhoir | K42: Moez Sassi | L42: Medium | M42: =IF(T42>2017,U42,"N/A") -> Unrated | N42: Low | O42: =IF(Q42="y",1,SUMIFS('Rating Grid'!$D$11:$D$34,'Rating Grid'!$B$11:$B$34,'AU before last cleanse'!$L$3:$L$143,'Rating Grid'!$C$11:$C$34,'AU before last cleanse'!$M$3:$M$143)) -> 2 | P42: Low | Q42: N | R42: =IF(O42>S42,O42,S42) -> 2 | T42: 2018 | U42: Unrated | V42: =IF($T42+$R42<=2022,"2022","-") -> 2022 | W42: =IF($T42+$R42=2023,"2023","-") -> - | X42: =IF($T42+$R42=2024,"2024","-") -> - | Y42: =IF($T42+$R42=2025,"2025","-") -> - | Z42: Y | AA42: =IF($T42>2018,"Y","N") -> N | AB42: VAT
A43: Original | B43: Wholesale Banking Group | C43: Coverage - Financial Institutions | D43: Financial Institutions | E43: WBG - Coverage | F43: 175 | G43: WBG Co-Head | H43: Jean Pierre Le Roux | I43: Craig Robertson (W); Srinivas Ramadurai (E) | K43: Neil Jarman | L43: Medium | M43: =IF(T43>2017,U43,"N/A") -> Sat | N43: Medium | O43: =IF(Q43="y",1,SUMIFS('Rating Grid'!$D$11:$D$34,'Rating Grid'!$B$11:$B$34,'AU before last cleanse'!$L$3:$L$143,'Rating Grid'!$C$11:$C$34,'AU before last cleanse'!$M$3:$M$143)) -> 3 | P43: Medium | Q43: N | R43: =IF(O43>S43,O43,S43) -> 3 | T43: 2019 | U43: Sat | V43: =IF($T43+$R43<=2022,"2022","-") -> 2022 | W43: =IF($T43+$R43=2023,"2023","-") -> - | X43: =IF($T43+$R43=2024,"2024","-") -> - | Y43: =IF($T43+$R43=2025,"2025","-") -> - | AA43: =IF($T43>2018,"Y","N") -> Y | AB43: To be covered under Syndicated Loans across WBG
A44: Original | B44: Wholesale Banking Group | C44: Coverage - Business Operational Risk Management | D44: Business Operational Risk Management | E44: WBG - Coverage | G44: WBG Co-Head | H44: Jean Pierre Le Roux | I44: Kartik Jayaram | K44: Neil Jarman | L44: Low | M44: =IF(T44>2017,U44,"N/A") -> Sat | N44: Low | O44: =IF(Q44="y",1,SUMIFS('Rating Grid'!$D$11:$D$34,'Rating Grid'!$B$11:$B$34,'AU before last cleanse'!$L$3:$L$143,'Rating Grid'!$C$11:$C$34,'AU before last cleanse'!$M$3:$M$143)) -> 4 | P44: Low | Q44: N | R44: =IF(O44>S44,O44,S44) -> 4 | T44: 2019 | U44: Sat | V44: 2022 | X44: =IF($T44+$R44=2024,"2024","-") -> - | Y44: =IF($T44+$R44=2025,"2025","-") -> - | Z44: Y | AA44: =IF($T44>2018,"Y","N") -> Y | AB44: Q1 - Syndicated Lending
A45: Original | B45: Wholesale Banking Group | C45: Product - Transaction Banking | D45: Transaction Banking | E45: WBG - Product | F45: 168, 169, 558 | G45: MD Treasury | H45: Vikas Suri | I45: Zavone Krotz | K45: Neil Jarman | L45: Medium | M45: Unrated | N45: Medium | O45: 3 | P45: Medium | Q45: N | R45: =IF(O45>S45,O45,S45) -> 3 | T45: 2017 | U45: Sat | V45: - | W45: 2023 | X45: =IF($T45+$R45=2024,"2024","-") -> - | Y45: =IF($T45+$R45=2025,"2025","-") -> - | AA45: =IF($T45>2018,"Y","N") -> N | AB45: TF strategy under development, audit planned post implementation PP2023
A46: Original | B46: Risk/Islamic Banking | C46: Sharia Governance & Risk Oversight | D46: Islamic Banking - Governance | E46: Islamic Banking / Risk | F46: 905 | G46: Chief Risk Officer | H46: Farhan Mahmoud / Abdul Karim Juma | I46: Husain Cuttleriwala | K46: Muhammad Abdulla | L46: Medium | M46: =IF(T46>2017,U46,"N/A") -> NI | N46: Medium | O46: =IF(Q46="y",1,SUMIFS('Rating Grid'!$D$11:$D$34,'Rating Grid'!$B$11:$B$34,'AU before last cleanse'!$L$3:$L$143,'Rating Grid'!$C$11:$C$34,'AU before last cleanse'!$M$3:$M$143)) -> 1 | P46: Medium | Q46: Y | R46: =IF(O46>S46,O46,S46) -> 1 | T46: 2021 | U46: NI | V46: =IF($T46+$R46<=2022,"2022","-") -> 2022 | W46: =IF($T46+$R46=2023,"2023","-") -> - | X46: =IF($T46+$R46=2024,"2024","-") -> - | Y46: =IF($T46+$R46=2025,"2025","-") -> - | Z46: Y | AA46: =IF($T46>2018,"Y","N") -> Y | AB46: Q3 / Q4
A47: Original | B47: Islamic Banking | C47: Sharia Operations | D47: Islamic Banking - Operations | E47: Islamic Banking | F47: 904 | G47: Head of Operations | H47: Michael Power | I47: Juzer Netterwala | K47: Muhammad Abdulla | L47: Medium | M47: =IF(T47>2017,U47,"N/A") -> NI | N47: Medium | O47: =IF(Q47="y",1,SUMIFS('Rating Grid'!$D$11:$D$34,'Rating Grid'!$B$11:$B$34,'AU before last cleanse'!$L$3:$L$143,'Rating Grid'!$C$11:$C$34,'AU before last cleanse'!$M$3:$M$143)) -> 1 | P47: Medium | Q47: Y | R47: =IF(O47>S47,O47,S47) -> 1 | T47: 2021 | U47: NI | V47: =IF($T47+$R47<=2022,"2022","-") -> 2022 | W47: =IF($T47+$R47=2023,"2023","-") -> - | X47: =IF($T47+$R47=2024,"2024","-") -> - | Y47: =IF($T47+$R47=2025,"2025","-") -> - | AA47: =IF($T47>2018,"Y","N") -> Y
A48: Original | B48: Risk/Islamic Banking | C48: Sharia Compliance | D48: Islamic Banking - Compliance | E48: Islamic Banking / Risk | F48: 905 | G48: Chief Risk Officer | H48: Farhan Mahmoud / Abdul Karim Juma | I48: Husain Cuttleriwala | K48: Muhammad Abdulla | L48: Medium | M48: =IF(T48>2017,U48,"N/A") -> NI | N48: Medium | O48: =IF(Q48="y",1,SUMIFS('Rating Grid'!$D$11:$D$34,'Rating Grid'!$B$11:$B$34,'AU before last cleanse'!$L$3:$L$143,'Rating Grid'!$C$11:$C$34,'AU before last cleanse'!$M$3:$M$143)) -> 1 | P48: Medium | Q48: Y | R48: =IF(O48>S48,O48,S48) -> 1 | T48: 2021 | U48: NI | V48: =IF($T48+$R48<=2022,"2022","-") -> 2022 | W48: =IF($T48+$R48=2023,"2023","-") -> - | X48: =IF($T48+$R48=2024,"2024","-") -> - | Y48: =IF($T48+$R48=2025,"2025","-") -> - | Z48: Y | AA48: =IF($T48>2018,"Y","N") -> Y | AB48: Q3 / Q4
A49: Original | B49: IT | C49: Business Applications | D49: Finacle Static Data | E49: IT | F49: 705 | G49: CTO | H49: Saket | I49: Sumat Kumar | J49: Chelliah Kumar | K49: Biju Varughese | L49: High | M49: =IF(T49>2017,U49,"N/A") -> N/A | N49: Medium | O49: =IF(Q49="y",1,SUMIFS('Rating Grid'!$D$11:$D$34,'Rating Grid'!$B$11:$B$34,'AU before last cleanse'!$L$3:$L$143,'Rating Grid'!$C$11:$C$34,'AU before last cleanse'!$M$3:$M$143)) -> 2 | P49: Medium | Q49: N | R49: =IF(O49>S49,O49,S49) -> 2 | T49: 2017 | U49: Sat | V49: =IF($T49+$R49<=2022,"2022","-") -> 2022 | W49: =IF($T49+$R49=2023,"2023","-") -> - | X49: =IF($T49+$R49=2024,"2024","-") -> - | Y49: =IF($T49+$R49=2025,"2025","-") -> - | Z49: Y | AA49: =IF($T49>2018,"Y","N") -> N
A50: Original | B50: IT | C50: IT Governance, Process & Services | D50: IT Governance | E50: IT | F50: 705 | G50: CTO | H50: Saket | I50: Ram Prasad Rajagopalan | K50: Biju Varughese | L50: Medium | M50: =IF(T50>2017,U50,"N/A") -> NI | N50: Medium | O50: =IF(Q50="y",1,SUMIFS('Rating Grid'!$D$11:$D$34,'Rating Grid'!$B$11:$B$34,'AU before last cleanse'!$L$3:$L$143,'Rating Grid'!$C$11:$C$34,'AU before last cleanse'!$M$3:$M$143)) -> 3 | P50: Medium | Q50: N | R50: =IF(O50>S50,O50,S50) -> 3 | T50: 2021 | U50: NI | V50: =IF($T50+$R50<=2022,"2022","-") -> - | W50: =IF($T50+$R50=2023,"2023","-") -> - | X50: =IF($T50+$R50=2024,"2024","-") -> 2024 | Y50: =IF($T50+$R50=2025,"2025","-") -> - | AA50: =IF($T50>2018,"Y","N") -> Y
A51: Original | B51: IT | C51: Applications Support | D51: Cloud applications | E51: IT | F51: 705 | G51: CTO | H51: Saket | I51: Sumat Kumar | K51: Biju Varughese | L51: Medium | M51: =IF(T51>2017,U51,"N/A") -> N/A | N51: Medium | O51: =IF(Q51="y",1,SUMIFS('Rating Grid'!$D$11:$D$34,'Rating Grid'!$B$11:$B$34,'AU before last cleanse'!$L$3:$L$143,'Rating Grid'!$C$11:$C$34,'AU before last cleanse'!$M$3:$M$143)) -> 3 | P51: Medium | Q51: N | R51: =IF(O51>S51,O51,S51) -> 3 | T51: 2010 | U51: - | V51: =IF($T51+$R51<=2022,"2022","-") -> 2022 | W51: =IF($T51+$R51=2023,"2023","-") -> - | X51: =IF($T51+$R51=2024,"2024","-") -> - | Y51: =IF($T51+$R51=2025,"2025","-") -> - | AA51: =IF($T51>2018,"Y","N") -> N
A52: Original | B52: Risk | C52: IT Risk / Information Security | D52: NESA Compliance | E52: IT | F52: 705 | G52: Chief Risk Officer | H52: Farhan Mahmoud | I52: Safwan Ghaleb | J52: Tushar Vartak | K52: Biju Varughese | L52: Medium | M52: =IF(T52>2017,U52,"N/A") -> NI | N52: Medium | O52: =IF(Q52="y",1,SUMIFS('Rating Grid'!$D$11:$D$34,'Rating Grid'!$B$11:$B$34,'AU before last cleanse'!$L$3:$L$143,'Rating Grid'!$C$11:$C$34,'AU before last cleanse'!$M$3:$M$143)) -> 3 | P52: Medium | Q52: N | R52: =IF(O52>S52,O52,S52) -> 3 | T52: 2020 | U52: NI | V52: =IF($T52+$R52<=2022,"2022","-") -> - | W52: =IF($T52+$R52=2023,"2023","-") -> 2023 | X52: =IF($T52+$R52=2024,"2024","-") -> - | Y52: =IF($T52+$R52=2025,"2025","-") -> - | AA52: =IF($T52>2018,"Y","N") -> Y
A53: Original | B53: IT | C53: IT Engineering | D53: System Development & DEVOPS | E53: IT | F53: 705 | G53: CTO | H53: Saket | I53: Prasad Edlabadkar | K53: Biju Varughese | L53: Medium | M53: =IF(T53>2017,U53,"N/A") -> Sat | N53: Low | O53: =IF(Q53="y",1,SUMIFS('Rating Grid'!$D$11:$D$34,'Rating Grid'!$B$11:$B$34,'AU before last cleanse'!$L$3:$L$143,'Rating Grid'!$C$11:$C$34,'AU before last cleanse'!$M$3:$M$143)) -> 3 | P53: Low | Q53: N | R53: =IF(O53>S53,O53,S53) -> 3 | T53: 2020 | U53: Sat | V53: =IF($T53+$R53<=2022,"2022","-") -> - | W53: =IF($T53+$R53=2023,"2023","-") -> 2023 | X53: =IF($T53+$R53=2024,"2024","-") -> - | Y53: =IF($T53+$R53=2025,"2025","-") -> - | AA53: =IF($T53>2018,"Y","N") -> Y
A54: Original | B54: IT | C54: IT Operations & Support | D54: Network Management, Voice and Security | E54: IT | F54: 705 | G54: CTO | H54: Saket | I54: Sh. Abdullah A. K. Al Qassemi | J54: Jonathan Gonsalves | K54: Biju Varughese | L54: High | M54: =IF(T54>2017,U54,"N/A") -> Sat | N54: Low | O54: =IF(Q54="y",1,SUMIFS('Rating Grid'!$D$11:$D$34,'Rating Grid'!$B$11:$B$34,'AU before last cleanse'!$L$3:$L$143,'Rating Grid'!$C$11:$C$34,'AU before last cleanse'!$M$3:$M$143)) -> 2 | P54: Low | Q54: N | R54: =IF(O54>S54,O54,S54) -> 2 | T54: 2019 | U54: Sat | V54: =IF($T54+$R54<=2022,"2022","-") -> 2022 | W54: =IF($T54+$R54=2023,"2023","-") -> - | X54: =IF($T54+$R54=2024,"2024","-") -> - | Y54: =IF($T54+$R54=2025,"2025","-") -> - | Z54: Y | AA54: =IF($T54>2018,"Y","N") -> Y
A55: Original | B55: IT | C55: IT Engineering | D55: Middleware and APIs | E55: IT | F55: 705 | G55: CTO | H55: Saket | I55: Prasad Edlabadkar | K55: Biju Varughese | L55: Medium | M55: =IF(T55>2017,U55,"N/A") -> N/A | N55: Medium | O55: =IF(Q55="y",1,SUMIFS('Rating Grid'!$D$11:$D$34,'Rating Grid'!$B$11:$B$34,'AU before last cleanse'!$L$3:$L$143,'Rating Grid'!$C$11:$C$34,'AU before last cleanse'!$M$3:$M$143)) -> 3 | P55: Medium | Q55: N | R55: =IF(O55>S55,O55,S55) -> 3 | T55: 2010 | U55: - | V55: =IF($T55+$R55<=2022,"2022","-") -> 2022 | W55: =IF($T55+$R55=2023,"2023","-") -> - | X55: =IF($T55+$R55=2024,"2024","-") -> - | Y55: =IF($T55+$R55=2025,"2025","-") -> - | AA55: =IF($T55>2018,"Y","N") -> N | AB55: One-off due to changing Middleware structure
A56: Original | B56: IT | C56: Third Parties | D56: Wipro IT Controls | E56: IT | F56: 705 | G56: CTO | H56: Saket | I56: Denis Kuznetsov | J56: Ram Prasad | K56: Biju Varughese | L56: Medium | M56: =IF(T56>2017,U56,"N/A") -> N/A | N56: Medium | O56: =IF(Q56="y",1,SUMIFS('Rating Grid'!$D$11:$D$34,'Rating Grid'!$B$11:$B$34,'AU before last cleanse'!$L$3:$L$143,'Rating Grid'!$C$11:$C$34,'AU before last cleanse'!$M$3:$M$143)) -> 3 | P56: High | Q56: N | R56: =IF(O56>S56,O56,S56) -> 3 | T56: 2010 | U56: - | V56: =IF($T56+$R56<=2022,"2022","-") -> 2022 | W56: =IF($T56+$R56=2023,"2023","-") -> - | X56: =IF($T56+$R56=2024,"2024","-") -> - | Y56: =IF($T56+$R56=2025,"2025","-") -> - | AA56: =IF($T56>2018,"Y","N") -> N
A57: Original | B57: IT | C57: Business Applications | D57: Swift & Payment Gateways | E57: IT | F57: 551 | G57: CTO | H57: Saket | I57: Sumat Kumar | J57: Guru Prasad | K57: Biju Varughese | L57: High | M57: =IF(T57>2017,U57,"N/A") -> NI | N57: Medium | O57: =IF(Q57="y",1,SUMIFS('Rating Grid'!$D$11:$D$34,'Rating Grid'!$B$11:$B$34,'AU before last cleanse'!$L$3:$L$143,'Rating Grid'!$C$11:$C$34,'AU before last cleanse'!$M$3:$M$143)) -> 2 | P57: High | Q57: N | R57: =IF(O57>S57,O57,S57) -> 2 | T57: 2020 | U57: NI | V57: =IF($T57+$R57<=2022,"2022","-") -> 2022 | W57: =IF($T57+$R57=2023,"2023","-") -> - | X57: =IF($T57+$R57=2024,"2024","-") -> - | Y57: =IF($T57+$R57=2025,"2025","-") -> - | AA57: =IF($T57>2018,"Y","N") -> Y
A58: Original | B58: IT | C58: IT Operations & Support | D58: IT Infrastructure | E58: IT | F58: 705 | G58: CTO | H58: Saket | I58: Sh. Abdullah A. K. Al Qassemi | J58: Jonathan Gonsalves | K58: Biju Varughese | L58: High | M58: =IF(T58>2017,U58,"N/A") -> NI | N58: Medium | O58: =IF(Q58="y",1,SUMIFS('Rating Grid'!$D$11:$D$34,'Rating Grid'!$B$11:$B$34,'AU before last cleanse'!$L$3:$L$143,'Rating Grid'!$C$11:$C$34,'AU before last cleanse'!$M$3:$M$143)) -> 2 | P58: Medium | Q58: N | R58: =IF(O58>S58,O58,S58) -> 3 | S58: 3 | T58: 2019 | U58: NI | V58: =IF($T58+$R58<=2022,"2022","-") -> 2022 | W58: =IF($T58+$R58=2023,"2023","-") -> - | X58: =IF($T58+$R58=2024,"2024","-") -> - | Y58: =IF($T58+$R58=2025,"2025","-") -> - | AA58: =IF($T58>2018,"Y","N") -> Y
A59: Original | B59: IT | C59: IT Operations & Support | D59: User and Privilege Access Management | E59: IT | F59: 705 | G59: CTO | H59: Saket | I59: Sh. Abdullah A. K. Al Qassemi | J59: Divya Babu | K59: Biju Varughese | L59: Medium | M59: =IF(T59>2017,U59,"N/A") -> NI | N59: Medium | O59: =IF(Q59="y",1,SUMIFS('Rating Grid'!$D$11:$D$34,'Rating Grid'!$B$11:$B$34,'AU before last cleanse'!$L$3:$L$143,'Rating Grid'!$C$11:$C$34,'AU before last cleanse'!$M$3:$M$143)) -> 3 | P59: high | Q59: N | R59: =IF(O59>S59,O59,S59) -> 3 | T59: 2018 | U59: NI | V59: =IF($T59+$R59<=2022,"2022","-") -> 2022 | W59: =IF($T59+$R59=2023,"2023","-") -> - | X59: =IF($T59+$R59=2024,"2024","-") -> - | Y59: =IF($T59+$R59=2025,"2025","-") -> - | Z59: Y | AA59: =IF($T59>2018,"Y","N") -> N | AB59: Q1
A60: Original | B60: Corporate Functions | C60: Administration & Asset Management | D60: Administration & Asset Management | E60: Corporate Functions | F60: 704 | G60: COO | H60: Michael Power | I60: Shameek | K60: Sangeetha Abraham | L60: Low | M60: =IF(T60>2017,U60,"N/A") -> NI | N60: Medium | O60: =IF(Q60="y",1,SUMIFS('Rating Grid'!$D$11:$D$34,'Rating Grid'!$B$11:$B$34,'AU before last cleanse'!$L$3:$L$143,'Rating Grid'!$C$11:$C$34,'AU before last cleanse'!$M$3:$M$143)) -> 4 | P60: Medium | Q60: N | R60: =IF(O60>S60,O60,S60) -> 4 | T60: 2019 | U60: NI | V60: =IF($T60+$R60<=2022,"2022","-") -> - | W60: =IF($T60+$R60=2023,"2023","-") -> 2023 | X60: =IF($T60+$R60=2024,"2024","-") -> - | Y60: =IF($T60+$R60=2025,"2025","-") -> - | AA60: =IF($T60>2018,"Y","N") -> Y
A61: Original | B61: Operations | C61: Business Continuity Management | D61: Business Continuity Management & Disaster Recovery | E61: Operations | F61: 709 | G61: Chief Risk Officer | H61: Farhan Mahmoud | I61: Safwan Ghaleb | J61: Jiju Thomas Philip | K61: Biju Varughese | L61: High | M61: =IF(T61>2017,U61,"N/A") -> Sat | N61: Medium | O61: =IF(Q61="y",1,SUMIFS('Rating Grid'!$D$11:$D$34,'Rating Grid'!$B$11:$B$34,'AU before last cleanse'!$L$3:$L$143,'Rating Grid'!$C$11:$C$34,'AU before last cleanse'!$M$3:$M$143)) -> 2 | P61: Medium | Q61: N | R61: =IF(O61>S61,O61,S61) -> 2 | T61: 2021 | U61: Sat | V61: =IF($T61+$R61<=2022,"2022","-") -> - | W61: =IF($T61+$R61=2023,"2023","-") -> 2023 | X61: =IF($T61+$R61=2024,"2024","-") -> - | Y61: =IF($T61+$R61=2025,"2025","-") -> - | AA61: =IF($T61>2018,"Y","N") -> Y
A62: Original | B62: Operations | C62: Cash Management | D62: Cash Management (ATMs) | E62: Operations | G62: COO | H62: Michael Power | I62: Juzer Netterwala | J62: Saeed | K62: Sangeetha Abraham | L62: Medium | M62: =IF(T62>2017,U62,"N/A") -> Sat | N62: Medium | O62: =IF(Q62="y",1,SUMIFS('Rating Grid'!$D$11:$D$34,'Rating Grid'!$B$11:$B$34,'AU before last cleanse'!$L$3:$L$143,'Rating Grid'!$C$11:$C$34,'AU before last cleanse'!$M$3:$M$143)) -> 3 | P62: Medium | Q62: N | R62: =IF(O62>S62,O62,S62) -> 3 | T62: 2018 | U62: Sat | V62: =IF($T62+$R62<=2022,"2022","-") -> 2022 | W62: =IF($T62+$R62=2023,"2023","-") -> - | X62: =IF($T62+$R62=2024,"2024","-") -> - | Y62: =IF($T62+$R62=2025,"2025","-") -> - | Z62: Y | AA62: =IF($T62>2018,"Y","N") -> N | AB62: Not in initial audit plan. Not consistent with the rating. Inherent risk should be Medium not High.
A63: Original | B63: Operations | C63: Central Operations (Financial) | D63: Central Operations (Financial) | E63: Operations | F63: 510 | G63: COO | H63: Michael Power | I63: Juzer Netterwala | J63: Saeed | K63: Sangeetha Abraham | L63: Medium | M63: =IF(T63>2017,U63,"N/A") -> Sat | N63: Low | O63: =IF(Q63="y",1,SUMIFS('Rating Grid'!$D$11:$D$34,'Rating Grid'!$B$11:$B$34,'AU before last cleanse'!$L$3:$L$143,'Rating Grid'!$C$11:$C$34,'AU before last cleanse'!$M$3:$M$143)) -> 3 | P63: Medium | Q63: N | R63: =IF(O63>S63,O63,S63) -> 3 | T63: 2021 | U63: Sat | V63: =IF($T63+$R63<=2022,"2022","-") -> - | W63: =IF($T63+$R63=2023,"2023","-") -> - | X63: =IF($T63+$R63=2024,"2024","-") -> 2024 | Y63: =IF($T63+$R63=2025,"2025","-") -> - | AA63: =IF($T63>2018,"Y","N") -> Y
A64: Original | B64: Operations | C64: Central Operations (Non-Financial) | D64: Central Operations (Non-Financial) | E64: Operations | F64: 510 | G64: COO | H64: Michael Power | I64: Juzer Netterwala | J64: Saeed | K64: Sangeetha Abraham | L64: Low | M64: =IF(T64>2017,U64,"N/A") -> Sat | N64: Very Low | O64: =IF(Q64="y",1,SUMIFS('Rating Grid'!$D$11:$D$34,'Rating Grid'!$B$11:$B$34,'AU before last cleanse'!$L$3:$L$143,'Rating Grid'!$C$11:$C$34,'AU before last cleanse'!$M$3:$M$143)) -> 4 | P64: low | Q64: N | R64: =IF(O64>S64,O64,S64) -> 4 | T64: 2021 | U64: Sat | V64: =IF($T64+$R64<=2022,"2022","-") -> - | W64: =IF($T64+$R64=2023,"2023","-") -> - | X64: =IF($T64+$R64=2024,"2024","-") -> - | Y64: =IF($T64+$R64=2025,"2025","-") -> 2025 | AA64: =IF($T64>2018,"Y","N") -> Y
A65: Original | B65: Operations | C65: BBG - Operations & Acct Monitoring | D65: Commercial Banking - Operations & Account monitoring | E65: Operations | G65: COO | H65: Michael Power | I65: Juzer Netterwala | J65: Shalini Mehta | K65: Neil Jarman | L65: Medium | M65: =IF(T65>2017,U65,"N/A") -> Sat | N65: Low | O65: =IF(Q65="y",1,SUMIFS('Rating Grid'!$D$11:$D$34,'Rating Grid'!$B$11:$B$34,'AU before last cleanse'!$L$3:$L$143,'Rating Grid'!$C$11:$C$34,'AU before last cleanse'!$M$3:$M$143)) -> 3 | P65: Medium | Q65: N | R65: =IF(O65>S65,O65,S65) -> 3 | T65: 2021 | U65: Sat | V65: =IF($T65+$R65<=2022,"2022","-") -> - | W65: =IF($T65+$R65=2023,"2023","-") -> - | X65: =IF($T65+$R65=2024,"2024","-") -> 2024 | Y65: =IF($T65+$R65=2025,"2025","-") -> - | AA65: =IF($T65>2018,"Y","N") -> Y
